Workbook

Sheet Metrics
A1: =Invoice!A8+OrderingShipping!A9 -> 233 | B1: Total Records
A2: =COUNTA(B11:B4994) -> 59 | B2: Total Attributes
A3: =A1*A2 -> 13747 | B3: Total to Cleanse
A4: =(COUNTIF(L:L,100%)*A1) -> 13281 | B4: Cleansed Attributes
A5: =A3-A4 -> 466 | B5: Dirty Attributes Remaining
A6: =AVERAGEIFS(L:L, G:G, "Yes", H:H, "Business", M:M, "<>Phase 1 - Non STIBO") -> 0.99984672 | B6: Av. % Complete
A7: =Invoice!B7/Invoice!A8 -> 1 | B7: Complete Invoice Records
A8: =OrderingShipping!B7/OrderingShipping!A8 -> 1 | B8: Complete O/S Records
A9: TBC | B9: Completed Non STIBO
A10: Tab | B10: Field Name | C10: Field Description | D10: Source location | E10: Source Field Name | F10: Field Type | G10: Mandatory? | H10: Responsible | I10: Incomplete | J10: Invalid | K10: Total | L10: % Complete | M10: MVP/Phase1 | N10: Okay to go in Jeeves/File? | O10: General Comment | P10: Transformation RULE | Q10: Transformation comment
A11: Invoice | B11: =Invoice!F6 -> Company Registration Number | C11: Add Company Registration Number | D11: STIBO | E11: Company Registration Number | F11: Alphanumeric | G11: Yes | H11: Business | I11: =Invoice!G7 -> 0 | J11: =Invoice!H7 -> 0 | K11: =Invoice!$A$8 -> 233 | L11: =IFERROR(((K11-J11)/K11),"0%") -> 1 | M11: MVP | N11: FALSE
A12: Invoice | B12: =Invoice!I6 -> VAT | C12: Vendor VAT Number | D12: STIBO | E12: VAT | F12: Text | G12: No | H12: Business | I12: =Invoice!J7 -> 0 | J12: =Invoice!K7 -> 0 | K12: =Invoice!$A$8 -> 233 | L12: =IFERROR(((K12-J12)/K12),"0%") -> 1 | M12: MVP | N12: FALSE
A13: Invoice | B13: =Invoice!L6 -> Address Line 1 | C13: Address field | D13: STIBO | E13: Address Line 1 | F13: Text | G13: Yes | H13: Business | I13: =Invoice!M7 -> 0 | J13: =Invoice!N7 -> 0 | K13: =Invoice!$A$8 -> 233 | L13: =IFERROR(((K13-J13)/K13),"0%") -> 1 | M13: MVP | N13: FALSE
A14: Invoice | B14: =Invoice!O6 -> Address Line 2 | C14: Address field | D14: STIBO | E14: Address Line 2 | F14: Text | G14: No | H14: Business | I14: =Invoice!P7 -> 0 | J14: =Invoice!Q7 -> 0 | K14: =Invoice!$A$8 -> 233 | L14: =IFERROR(((K14-J14)/K14),"0%") -> 1 | M14: MVP | N14: FALSE
A15: Invoice | B15: =Invoice!R6 -> Town/City | C15: Address field | D15: STIBO | E15: Town/City | F15: Text | G15: Yes | H15: Business | I15: =Invoice!S7 -> 0 | J15: =Invoice!T7 -> 0 | K15: =Invoice!$A$8 -> 233 | L15: =IFERROR(((K15-J15)/K15),"0%") -> 1 | M15: MVP | N15: FALSE
A16: Invoice | B16: =Invoice!U6 -> County/District | C16: Address field | D16: STIBO | E16: County/District | F16: Text | G16: No | H16: Business | I16: =Invoice!V7 -> 0 | J16: =Invoice!W7 -> 0 | K16: =Invoice!$A$8 -> 233 | L16: =IFERROR(((K16-J16)/K16),"0%") -> 1 | M16: MVP | N16: FALSE
A17: Invoice | B17: =Invoice!X6 -> Zip/Postal Code | C17: Address field | D17: STIBO | E17: Zip/Postal Code | F17: Text | G17: Yes | H17: Business | I17: =Invoice!Y7 -> 0 | J17: =Invoice!Z7 -> 0 | K17: =Invoice!$A$8 -> 233 | L17: =IFERROR(((K17-J17)/K17),"0%") -> 1 | M17: MVP | N17: FALSE
A18: Invoice | B18: =Invoice!AA6 -> Country | C18: ISO-2 country code | D18: STIBO | E18: Country | F18: LOV | G18: Yes | H18: Business | I18: =Invoice!AB7 -> 0 | J18: =Invoice!AC7 -> 0 | K18: =Invoice!$A$8 -> 233 | L18: =IFERROR(((K18-J18)/K18),"0%") -> 1 | M18: MVP | N18: FALSE
A19: Invoice | B19: =Invoice!AD6 -> Currency Code | C19: 3 characters code | D19: STIBO | E19: Currency Code | F19: LOV | G19: Yes | H19: Business | I19: =Invoice!AE7 -> 0 | J19: =Invoice!AF7 -> 0 | K19: =Invoice!$A$8 -> 233 | L19: =IFERROR(((K19-J19)/K19),"0%") -> 1 | M19: MVP | N19: FALSE
A20: Invoice | B20: =Invoice!AG6 -> Payment Terms | C20: Select Payment terms for Invoice vendor | D20: STIBO | E20: Payment Terms | F20: LOV | G20: Yes | H20: Business | I20: =Invoice!AH7 -> 0 | J20: =Invoice!AI7 -> 0 | K20: =Invoice!$A$8 -> 233 | L20: =IFERROR(((K20-J20)/K20),"0%") -> 1 | M20: MVP | N20: FALSE
A21: Invoice | B21: =Invoice!AJ6 -> Method of Payment | C21: Select method of payment for Invoice vendor | D21: Jeeves | E21: UtbSlag | F21: LOV | G21: Yes | H21: Business | I21: =Invoice!AK7 -> 0 | J21: =Invoice!AL7 -> 0 | K21: =Invoice!$A$8 -> 233 | L21: =IFERROR(((K21-J21)/K21),"0%") -> 1 | M21: Phase 1 | N21: FALSE
A22: Invoice | B22: =Invoice!AM6 -> VAT Group | C22: Vendor VAT grouping | D22: Jeeves | E22: LevKategori | F22: LOV | G22: Yes | H22: Business | I22: =Invoice!AN7 -> 0 | J22: =Invoice!AO7 -> 0 | K22: =Invoice!$A$8 -> 233 | L22: =IFERROR(((K22-J22)/K22),"0%") -> 1 | M22: Phase 1 | N22: FALSE
A23: Invoice | B23: =Invoice!AP6 -> Known As Name | C23: Name field | D23: NA | F23: Text | G23: No | H23: Business | I23: =Invoice!AQ7 -> 0 | J23: =Invoice!AR7 -> 0 | K23: =Invoice!$A$8 -> 233 | L23: =IFERROR(((K23-J23)/K23),"0%") -> 1 | M23: Phase 1 | N23: FALSE
A24: Invoice | B24: =Invoice!AS6 -> Legal Name | C24: Name field | D24: STIBO | F24: Text | G24: Yes | H24: Business | I24: =Invoice!AT7 -> 0 | J24: =Invoice!AU7 -> 0 | K24: =Invoice!$A$8 -> 233 | L24: =IFERROR(((K24-J24)/K24),"0%") -> 1 | M24: Phase 1 | N24: FALSE
A25: Invoice | B25: =Invoice!AV6 -> Search Name | C25: Name field | F25: Text | G25: Yes | H25: OSD | I25: =Invoice!AW7 -> 0 | J25: =Invoice!AX7 -> 0 | K25: =Invoice!$A$8 -> 233 | L25: =IFERROR(((K25-J25)/K25),"0%") -> 1 | M25: Phase 1 | N25: FALSE
A26: Invoice | B26: =Invoice!AY6 -> EU Master Vendor | C26: Europe level vendor grouping | D26: NA | F26: LOV | G26: Yes | H26: OSD | I26: =Invoice!AZ7 -> 0 | J26: =Invoice!BA7 -> 1 | K26: =Invoice!$A$8 -> 233 | L26: =IFERROR(((K26-J26)/K26),"0%") -> 0.99570815 | M26: Phase 1 | N26: FALSE
A27: Invoice | B27: =Invoice!BB6 -> Certificate of Insurance | C27: End date for insurance certificate | D27: NA | F27: Date | G27: No | H27: Business | I27: =Invoice!BC7 -> 0 | J27: =Invoice!BD7 -> 0 | K27: =Invoice!$A$8 -> 233 | L27: =IFERROR(((K27-J27)/K27),"0%") -> 1 | M27: Phase 1 | N27: FALSE
A28: Invoice | B28: =Invoice!BE6 -> Hold Harmless | C28: End date for Hold Harmless Agreement | D28: NA | F28: Date | G28: No | H28: Business | I28: =Invoice!BF7 -> 0 | J28: =Invoice!BG7 -> 0 | K28: =Invoice!$A$8 -> 233 | L28: =IFERROR(((K28-J28)/K28),"0%") -> 1 | M28: Phase 1 | N28: FALSE
A29: Invoice | B29: =Invoice!BH6 -> GLN | C29: Global Location Number | F29: Numeric | G29: No | H29: Business | I29: =Invoice!BI7 -> 0 | J29: =Invoice!BJ7 -> 0 | K29: =Invoice!$A$8 -> 233 | L29: =IFERROR(((K29-J29)/K29),"0%") -> 1 | M29: Phase 1 | N29: FALSE
A30: Invoice | B30: =Invoice!BK6 -> Address Purpose | C30: Select Address Purpose, defaulted to Invoice | D30: NA | F30: LOV | G30: Yes | H30: Business | I30: =Invoice!BL7 -> 1 | J30: =Invoice!BM7 -> 1 | K30: =Invoice!$A$8 -> 233 | L30: =IFERROR(((K30-J30)/K30),"0%") -> 0.99570815 | M30: Phase 1 | N30: FALSE
A31: Invoice | B31: =Invoice!BN6 -> Vendor Status | C31: Active/Delisted Status | D31: Extern file | F31: LOV | G31: Yes | H31: Business | I31: =Invoice!BO7 -> 0 | J31: =Invoice!BP7 -> 0 | K31: =Invoice!$A$8 -> 233 | L31: =IFERROR(((K31-J31)/K31),"0%") -> 1 | M31: Phase 1 | N31: FALSE | O31: WIP (done 6 oct)
A32: Invoice | B32: =Invoice!BQ6 -> Intercompany/Trading Partner | C32: Select if Vendor is Sysco company | F32: LOV | G32: No | H32: Business | I32: =Invoice!BR7 -> 0 | J32: =Invoice!BS7 -> 0 | K32: =Invoice!$A$8 -> 233 | L32: =IFERROR(((K32-J32)/K32),"0%") -> 1 | M32: Phase 1 | N32: FALSE
A33: Invoice | B33: =Invoice!BT6 -> Duty Paid/Bond | C33: Select if alcoholic items are duty paid/bond. Specific to Classic Drinks Ireland | D33: NA | F33: LOV | G33: No | H33: Business | I33: =Invoice!BU7 -> 0 | J33: =Invoice!BV7 -> 0 | K33: =Invoice!$A$8 -> 233 | L33: =IFERROR(((K33-J33)/K33),"0%") -> 1 | M33: Phase 1 | N33: FALSE
A34: OrderingShipping | B34: =OrderingShipping!F6 -> Address Line 1 | C34: Address field | D34: STIBO | E34: Address Line 1 | F34: Text | G34: Yes | H34: Business | I34: =OrderingShipping!G7 -> 0 | J34: =OrderingShipping!H7 -> 0 | K34: =OrderingShipping!$A$8 -> 101 | L34: =IFERROR(((K34-J34)/K34),"0%") -> 1 | M34: MVP | N34: FALSE
A35: OrderingShipping | B35: =OrderingShipping!I6 -> Address Line 2 | C35: Address field | D35: STIBO | E35: Address Line 2 | F35: Text | G35: No | H35: Business | I35: =OrderingShipping!J7 -> 0 | J35: =OrderingShipping!K7 -> 0 | K35: =OrderingShipping!$A$8 -> 101 | L35: =IFERROR(((K35-J35)/K35),"0%") -> 1 | M35: MVP | N35: FALSE
A36: OrderingShipping | B36: =OrderingShipping!L6 -> Town/City | C36: Address field | D36: STIBO | E36: Town/City | F36: Text | G36: Yes | H36: Business | I36: =OrderingShipping!M7 -> 0 | J36: =OrderingShipping!N7 -> 0 | K36: =OrderingShipping!$A$8 -> 101 | L36: =IFERROR(((K36-J36)/K36),"0%") -> 1 | M36: MVP | N36: FALSE
A37: OrderingShipping | B37: =OrderingShipping!O6 -> County/District | C37: Address field | D37: STIBO | E37: County/District | F37: Text | G37: No | H37: Business | I37: =OrderingShipping!P7 -> 0 | J37: =OrderingShipping!Q7 -> 0 | K37: =OrderingShipping!$A$8 -> 101 | L37: =IFERROR(((K37-J37)/K37),"0%") -> 1 | M37: MVP | N37: FALSE
A38: OrderingShipping | B38: =OrderingShipping!R6 -> Zip/Postal Code | C38: Address field | D38: STIBO | E38: Zip/Postal Code | F38: Text | G38: Yes | H38: Business | I38: =OrderingShipping!S7 -> 0 | J38: =OrderingShipping!T7 -> 0 | K38: =OrderingShipping!$A$8 -> 101 | L38: =IFERROR(((K38-J38)/K38),"0%") -> 1 | M38: MVP | N38: FALSE
A39: OrderingShipping | B39: =OrderingShipping!U6 -> Country | C39: ISO-2 country code | D39: STIBO | E39: Country | F39: LOV | G39: Yes | H39: Business | I39: =OrderingShipping!V7 -> 0 | J39: =OrderingShipping!W7 -> 0 | K39: =OrderingShipping!$A$8 -> 101 | L39: =IFERROR(((K39-J39)/K39),"0%") -> 1 | M39: MVP | N39: FALSE
A40: OrderingShipping | B40: =OrderingShipping!X6 -> Delivery Term | C40: Select Terms of delivery | D40: Jeeves | E40: IncoTerms | F40: LOV | G40: Yes | H40: Business | I40: =OrderingShipping!Y7 -> 0 | J40: =OrderingShipping!Z7 -> 0 | K40: =OrderingShipping!$A$8 -> 101 | L40: =IFERROR(((K40-J40)/K40),"0%") -> 1 | M40: Phase 1 | N40: FALSE
A41: OrderingShipping | B41: =OrderingShipping!AA6 -> Mode of Delivery | C41: Select mode of delivery | D41: Jeeves | E41: LevSattKod or DeliveryMode | F41: LOV | G41: Yes | H41: Business | I41: =OrderingShipping!AB7 -> 0 | J41: =OrderingShipping!AC7 -> 0 | K41: =OrderingShipping!$A$8 -> 101 | L41: =IFERROR(((K41-J41)/K41),"0%") -> 1 | M41: Phase 1 | N41: FALSE
A42: OrderingShipping | B42: =OrderingShipping!AD6 -> Site | C42: Vendor Site | F42: LOV | G42: Yes | H42: OSD | I42: =OrderingShipping!AE7 -> 0 | J42: =OrderingShipping!AF7 -> 101 | K42: =OrderingShipping!$A$8 -> 101 | L42: 1 | M42: Phase 1 | N42: FALSE
A43: OrderingShipping | B43: =OrderingShipping!AG6 -> Warehouse | C43: Vendor Warehouse | F43: LOV | G43: Yes | H43: OSD | I43: =OrderingShipping!AH7 -> 0 | J43: =OrderingShipping!AI7 -> 101 | K43: =OrderingShipping!$A$8 -> 101 | L43: 1 | M43: Phase 1 | N43: FALSE
A44: OrderingShipping | B44: =OrderingShipping!AK6 -> Buyer Group | C44: Select buyer group category for vendor | D44: Jeeves | E44: LineOfBus | F44: LOV | G44: Yes | H44: Business | I44: =OrderingShipping!AL7 -> 0 | J44: =OrderingShipping!AM7 -> 0 | K44: =OrderingShipping!$A$8 -> 101 | L44: =IFERROR(((K44-J44)/K44),"0%") -> 1 | M44: Phase 1 | N44: FALSE
A45: OrderingShipping | B45: =OrderingShipping!AN6 -> Nominated Vendor | C45: Yes/No toggle. Vendor sells nominated items | D45: n/a | F45: LOV | G45: Yes | H45: Business | I45: =OrderingShipping!AO7 -> 0 | J45: =OrderingShipping!AP7 -> 0 | K45: =OrderingShipping!$A$8 -> 101 | L45: =IFERROR(((K45-J45)/K45),"0%") -> 1 | M45: Phase 1 | N45: FALSE
A46: OrderingShipping | B46: =OrderingShipping!AQ6 -> Known As Name | C46: Name field | D46: NA | F46: Text | G46: No | H46: Business | I46: =OrderingShipping!AR7 -> 0 | J46: =OrderingShipping!AS7 -> 0 | K46: =OrderingShipping!$A$8 -> 101 | L46: =IFERROR(((K46-J46)/K46),"0%") -> 1 | M46: Phase 1 | N46: FALSE
A47: OrderingShipping | B47: =OrderingShipping!AT6 -> Legal Name | C47: Name field | F47: Text | G47: Yes | H47: OSD | I47: =OrderingShipping!AU7 -> 0 | J47: =OrderingShipping!AV7 -> 0 | K47: =OrderingShipping!$A$8 -> 101 | L47: =IFERROR(((K47-J47)/K47),"0%") -> 1 | M47: Phase 1 | N47: FALSE | O47: Needs to be updated by Sysco
A48: OrderingShipping | B48: =OrderingShipping!AW6 -> Search Name | C48: Name field | F48: Text | G48: Yes | H48: OSD | I48: =OrderingShipping!AX7 -> 0 | J48: =OrderingShipping!AY7 -> 0 | K48: =OrderingShipping!$A$8 -> 101 | L48: =IFERROR(((K48-J48)/K48),"0%") -> 1 | M48: Phase 1 | N48: FALSE
A49: OrderingShipping | B49: =OrderingShipping!AZ6 -> Vendor Managed Inventory (VMI) | C49: Yes/No toggle. If inventory managed by Vendor | D49: n/a | F49: LOV | G49: Yes | H49: Business | I49: =OrderingShipping!BA7 -> 0 | J49: =OrderingShipping!BB7 -> 0 | K49: =OrderingShipping!$A$8 -> 101 | L49: =IFERROR(((K49-J49)/K49),"0%") -> 1 | M49: Phase 1 | N49: FALSE
A50: OrderingShipping | B50: =OrderingShipping!BC6 -> GLN | C50: Global Location Number | F50: Numeric | G50: No | H50: Business | I50: =OrderingShipping!BD7 -> 0 | J50: =OrderingShipping!BE7 -> 0 | K50: =OrderingShipping!$A$8 -> 101 | L50: =IFERROR(((K50-J50)/K50),"0%") -> 1 | M50: Phase 1 | N50: FALSE
A51: OrderingShipping | B51: =OrderingShipping!BF6 -> Address Purpose | C51: Select Address Purpose, defaulted to Delivery | D51: NA | F51: LOV | G51: Yes | H51: Business | I51: =OrderingShipping!BG7 -> 0 | J51: =OrderingShipping!BH7 -> 0 | K51: =OrderingShipping!$A$8 -> 101 | L51: =IFERROR(((K51-J51)/K51),"0%") -> 1 | M51: Phase 1 | N51: FALSE
A52: OrderingShipping | B52: =OrderingShipping!BI6 -> Vendor Status | C52: Active/Delisted Status | D52: Extern file | F52: LOV | G52: Yes | H52: Business | I52: =OrderingShipping!BJ7 -> 0 | J52: =OrderingShipping!BK7 -> 0 | K52: =OrderingShipping!$A$8 -> 101 | L52: =IFERROR(((K52-J52)/K52),"0%") -> 1 | M52: Phase 1 | N52: FALSE
A53: Additional Address - Invoice | B53: ='Additional Address - Invoice'!C6 -> Address Line 1 | C53: Address field | D53: n/a | F53: Text | G53: Yes | H53: Business | I53: ='Additional Address - Invoice'!D7 -> 0 | J53: ='Additional Address - Invoice'!E7 -> 0 | K53: ='Additional Address - Invoice'!$A$8 -> 0 | L53: 1 | M53: Phase 1 | N53: FALSE
A54: Additional Address - Invoice | B54: ='Additional Address - Invoice'!F6 -> Address Line 2 | C54: Address field | D54: n/a | F54: Text | G54: No | H54: Business | I54: ='Additional Address - Invoice'!G7 -> 0 | J54: ='Additional Address - Invoice'!H7 -> 0 | K54: ='Additional Address - Invoice'!$A$8 -> 0 | L54: 1 | M54: Phase 1 | N54: FALSE
A55: Additional Address - Invoice | B55: ='Additional Address - Invoice'!I6 -> Town/City | C55: Address field | D55: n/a | F55: Text | G55: Yes | H55: Business | I55: ='Additional Address - Invoice'!J7 -> 0 | J55: ='Additional Address - Invoice'!K7 -> 0 | K55: ='Additional Address - Invoice'!$A$8 -> 0 | L55: 1 | M55: Phase 1 | N55: FALSE
A56: Additional Address - Invoice | B56: ='Additional Address - Invoice'!L6 -> County/District | C56: Address field | D56: n/a | F56: Text | G56: No | H56: Business | I56: ='Additional Address - Invoice'!M7 -> 0 | J56: ='Additional Address - Invoice'!N7 -> 0 | K56: ='Additional Address - Invoice'!$A$8 -> 0 | L56: 1 | M56: Phase 1 | N56: FALSE
A57: Additional Address - Invoice | B57: ='Additional Address - Invoice'!O6 -> Zip/Postal Code | C57: Address field | D57: n/a | F57: Text | G57: Yes | H57: Business | I57: ='Additional Address - Invoice'!P7 -> 0 | J57: ='Additional Address - Invoice'!Q7 -> 0 | K57: ='Additional Address - Invoice'!$A$8 -> 0 | L57: 1 | M57: Phase 1 | N57: FALSE
A58: Additional Address - Invoice | B58: ='Additional Address - Invoice'!R6 -> Country | C58: Address field | D58: n/a | F58: LOV | G58: Yes | H58: Business | I58: ='Additional Address - Invoice'!S7 -> 0 | J58: ='Additional Address - Invoice'!T7 -> 0 | K58: ='Additional Address - Invoice'!$A$8 -> 0 | L58: 1 | M58: Phase 1 | N58: FALSE
A59: Additional Address - Invoice | B59: ='Additional Address - Invoice'!U6 -> Address Purpose | C59: Select Address Purpose | D59: n/a | F59: LOV | G59: Yes | H59: Business | I59: ='Additional Address - Invoice'!V7 -> 0 | J59: ='Additional Address - Invoice'!W7 -> 0 | K59: ='Additional Address - Invoice'!$A$8 -> 0 | L59: 1 | M59: Phase 1 | N59: FALSE
A60: Non-STIBO | B60: Bank Account ID | C60: Same as Invoice Code | D60: q_Menigo_BankAccount_Master | E60: BANKACCOUNTNUMBER | F60: Alphanumeric | G60: Yes | H60: Business | I60: ='Non-STIBO Invoice'!F7 -> 0 | J60: ='Non-STIBO Invoice'!G7 -> 0 | K60: =Invoice!$A$8 -> 233 | L60: =IFERROR(((K60-J60)/K60),"0%") -> 1 | M60: Phase 1 - Non STIBO | N60: FALSE | P60: Available in Jeeves | Q60: 1. Mapping Template - Vendors.xlsx FieldId #31 Here it says same as Invoice Code, in ERP mapping it says default bank account for the vendor
A61: Non-STIBO | B61: Bank Account Number | C61: Vendor's Bank Account Number if payment is NOT made by Cash/Card | D61: q_Menigo_BankAccount_Master | E61: BANKACCOUNTNUMBER | F61: Numeric | G61: No | H61: Business | I61: ='Non-STIBO Invoice'!I7 -> 0 | J61: ='Non-STIBO Invoice'!J7 -> 0 | K61: =Invoice!$A$8 -> 233 | L61: =IFERROR(((K61-J61)/K61),"0%") -> 1 | M61: Phase 1 - Non STIBO | N61: FALSE | O61: 16/9: Possible BG/PG | P61: Analyse further | Q61: 2. Mapping Template - VendorBankAccount.xlsx FieldId #22
A62: Non-STIBO | B62: Bank Name | C62: Vendor's Bank Name | F62: Alphanumeric | G62: No | H62: Business | I62: ='Non-STIBO Invoice'!L7 -> 0 | J62: ='Non-STIBO Invoice'!M7 -> 0 | K62: =Invoice!$A$8 -> 233 | L62: =IFERROR(((K62-J62)/K62),"0%") -> 1 | M62: Phase 1 - Non STIBO | N62: FALSE | P62: N/A
A63: Non-STIBO | B63: Routing Number | C63: For international accounts | D63: q_Menigo_BankAccount_Master | E63: ROUTINGNUMBER | F63: Numeric | G63: Yes | H63: Business | I63: ='Non-STIBO Invoice'!O7 -> 0 | J63: ='Non-STIBO Invoice'!P7 -> 0 | K63: =Invoice!$A$8 -> 233 | L63: =IFERROR(((K63-J63)/K63),"0%") -> 1 | M63: Phase 1 - Non STIBO | N63: FALSE | P63: Analyse further | Q63: 2. Mapping Template - VendorBankAccount.xlsx FieldId #50
A64: Non-STIBO | B64: IBAN Number | C64: Also known as Bankgiro number | D64: q_Menigo_BankAccount_Master | E64: BANKACCOUNTNUMBER | F64: Alphanumeric | G64: No | H64: Business | I64: ='Non-STIBO Invoice'!R7 -> 0 | J64: ='Non-STIBO Invoice'!S7 -> 0 | K64: =Invoice!$A$8 -> 233 | L64: =IFERROR(((K64-J64)/K64),"0%") -> 1 | M64: Phase 1 - Non STIBO | N64: FALSE | P64: Available in Jeeves | Q64: 1. Mapping Template - Vendors.xlsx FieldId #31
A65: Non-STIBO | B65: SWIFT Code | C65: For international accounts | D65: q_Menigo_BankAccount_Master | E65: SWIFTCODE | F65: Alphanumeric | G65: No | H65: Business | I65: ='Non-STIBO Invoice'!U7 -> 0 | J65: ='Non-STIBO Invoice'!V7 -> 0 | K65: =Invoice!$A$8 -> 233 | L65: =IFERROR(((K65-J65)/K65),"0%") -> 1 | M65: Phase 1 - Non STIBO | N65: FALSE | P65: Available in Jeeves
A66: Non-STIBO | B66: Vendor Hold | C66: Select on hold status from List of values | F66: LOV | G66: Yes | H66: Business | I66: ='Non-STIBO Invoice'!X7 -> 0 | J66: ='Non-STIBO Invoice'!Y7 -> 0 | K66: =Invoice!$A$8 -> 233 | L66: =IFERROR(((K66-J66)/K66),"0%") -> 1 | M66: Phase 1 - Non STIBO | N66: FALSE
A67: Non-STIBO | B67: Credit Limit | C67: If there is no credit limit value, defaulted to 0 | F67: Decimal | G67: Yes | H67: Business | I67: ='Non-STIBO Invoice'!AG7 -> 0 | J67: ='Non-STIBO Invoice'!AH7 -> 0 | K67: =Invoice!$A$8 -> 233 | L67: =IFERROR(((K67-J67)/K67),"0%") -> 1 | M67: Phase 1 - Non STIBO | N67: FALSE
A68: Non-STIBO | B68: Consignment | C68: Yes/No toggle. | F68: LOV | G68: Yes | H68: Business | I68: ='Non-STIBO Invoice'!AJ7 -> 0 | J68: ='Non-STIBO Invoice'!AK7 -> 0 | K68: =Invoice!$A$8 -> 233 | L68: =IFERROR(((K68-J68)/K68),"0%") -> 1 | M68: Phase 1 - Non STIBO | N68: FALSE
A69: Non-STIBO | B69: Invoice Tolerance Group | C69: Select Invoice tolerance from list of value | F69: LOV | G69: Yes | H69: Business | I69: ='Non-STIBO Invoice'!AM7 -> 0 | J69: ='Non-STIBO Invoice'!AN7 -> 0 | K69: =Invoice!$A$8 -> 233 | L69: =IFERROR(((K69-J69)/K69),"0%") -> 1 | M69: Phase 1 - Non STIBO | N69: FALSE

Sheet Invoice
A1: Mandatory | C1: N/A | D1: N/A | F1: Yes | I1: No | L1: Yes | O1: No | R1: Yes | U1: No | X1: Yes | AA1: Yes | AD1: Yes | AG1: Yes | AJ1: Yes | AM1: Yes | AP1: No | AS1: Yes | AV1: Yes | AY1: Yes | BB1: No | BE1: No | BH1: No | BK1: Yes | BN1: Yes | BQ1: Yes + BR | BT1: No | BW1: No
A2: Main checks | C2: N/A | D2: N/A | F2: Make sure the length is within limit and have no special characters. | I2: Make sure the length is within limit and have no special characters. | L2: Make sure the name length is within limit and have only allowed special characters. | O2: Make sure the name length is within limit and have only allowed special characters. | R2: Make sure the name length is within limit and have only allowed special characters. | U2: Make sure the name length is within limit and have only allowed special characters. | X2: Make sure the name length is within limit and have only allowed special characters. | AA2: Analyse current data to new harmonized table and cleanse to standard | AD2: Analyse current data to new harmonized table and cleanse to standard | AG2: Check if payment term is stored in the system, if not, setup a way to collect and align with the harmozined list of values. | AJ2: Check if payment method is stored in the system, if not, setup a way to collect and align with the harmozined list of values. | AM2: Analyze current data and compare to new harmonized table | AP2: Make sure the name length is within limit and have only allowed special characters. | AS2: Make sure the name length is within limit and have only allowed special characters. | AV2: Auto-populated, OSD team to manage | AY2: No cleanup required, OSD team to manage | BB2: Check if data is collected in local ERP. Make sure the certfication date is in correct Date format | BE2: Check if data is collected in local ERP. Make sure the certfication date is in correct Date format | BH2: No special characters/spaces are allowed, numeric field | BK2: Analyze current data if Address purpose is collected. | BN2: Analyze current data and populate if a local vendor should be Active/Delisted | BQ2: Analyse current data to new harmonized table and cleanse to standard | BT2: Analyse current data to new harmonized table and cleanse to standard
A3: Base type | C3: N/A | D3: N/A | F3: Alphanumeric | I3: Text | L3: Text | O3: Text | R3: Text | U3: Text | X3: Text | AA3: LOV | AD3: LOV | AG3: LOV | AJ3: LOV | AM3: LOV | AP3: Text | AS3: Text | AV3: Text | AY3: LOV | BB3: Date | BE3: Date | BH3: Numeric | BK3: LOV | BN3: LOV | BQ3: LOV | BT3: LOV
A4: Char length | C4: N/A | D4: N/A | F4: 30 | I4: 20 | L4: 8 | O4: 80 | R4: 60 | U4: 60 | X4: 80 | AA4: N/A | AD4: N/A | AG4: N/A | AJ4: N/A | AM4: N/A | AP4: 80 | AS4: 80 | AV4: 20 | AY4: N/A | BB4: N/A | BE4: N/A | BH4: 13 | BK4: N/A | BN4: N/A | BQ4: N/A | BT4: N/A
A5: Special char | C5: N/A | D5: N/A | F5: No | I5: No | L5: Allowed list with exceptions | O5: Allowed list with exceptions | R5: Allowed list only | U5: Allowed list only | X5: Allowed list only | AA5: N/A | AD5: N/A | AG5: N/A | AJ5: N/A | AM5: N/A | AP5: Check MDD for Special Characters | AS5: Check MDD for Special Characters | AV5: Check MDD for Special Characters | AY5: N/A | BB5: N/A | BE5: N/A | BH5: None | BK5: N/A | BN5: N/A | BQ5: N/A | BT5: N/A
A6: Header | C6: Invoice SUVC | D6: Vendor Name | E6: Vendor Account Group | F6: Company Registration Number | G6: Complete | H6: Valid | I6: VAT | J6: Complete | K6: Valid | L6: Address Line 1 | M6: Complete | N6: Valid | O6: Address Line 2 | P6: Complete | Q6: Valid | R6: Town/City | S6: Complete | T6: Valid | U6: County/District | V6: Complete | W6: Valid | X6: Zip/Postal Code | Y6: Complete | Z6: Valid | AA6: Country | AB6: Complete | AC6: Valid | AD6: Currency Code | AE6: Complete | AF6: Valid | AG6: Payment Terms | AH6: Complete | AI6: Valid | AJ6: Method of Payment | AK6: Complete | AL6: Valid | AM6: VAT Group | AN6: Complete | AO6: Valid | AP6: Known As Name | AQ6: Complete | AR6: Valid | AS6: Legal Name | AT6: Complete | AU6: Valid | AV6: Search Name | AW6: Complete | AX6: Valid | AY6: EU Master Vendor | AZ6: Complete | BA6: Valid | BB6: Certificate of Insurance | BC6: Complete | BD6: Valid | BE6: Hold Harmless | BF6: Complete | BG6: Valid | BH6: GLN | BI6: Complete | BJ6: Valid | BK6: Address Purpose | BL6: Complete | BM6: Valid | BN6: Vendor Status | BO6: Complete | BP6: Valid | BQ6: Intercompany/Trading Partner | BR6: Complete | BS6: Valid | BT6: Duty Paid/Bond | BU6: Complete | BV6: Valid | BW6: Is Intercompany | BX6: Complete | BY6: Valid | BZ6: Menigo Focus
A7: Example | B7: =+COUNTIF(B8:B1048570,0) -> 233 | C7: 207622 | D7: Ciaran's Cookware | E7: Trade | F7: A123456 | G7: =COUNTIF(G$8:G$1295,FALSE) -> 0 | H7: =COUNTIF(H$8:H$1295,FALSE) -> 0 | I7: A123456 | J7: =COUNTIF(J$8:J$1295,FALSE) -> 0 | K7: =COUNTIF(K$8:K$1295,FALSE) -> 0 | L7: Unit 1 | M7: =COUNTIF(M$8:M$1295,FALSE) -> 0 | N7: =COUNTIF(N$8:N$1295,FALSE) -> 0 | O7: 1 Pixie Way | P7: =COUNTIF(P$8:P$1295,FALSE) -> 0 | Q7: =COUNTIF(Q$8:Q$1295,FALSE) -> 0 | R7: Los Angeles | S7: =COUNTIF(S$8:S$1295,FALSE) -> 0 | T7: =COUNTIF(T$8:T$1295,FALSE) -> 0 | U7: California | V7: =COUNTIF(V$8:V$1295,FALSE) -> 0 | W7: =COUNTIF(W$8:W$1295,FALSE) -> 0 | X7: 123456 | Y7: =COUNTIF(Y$8:Y$1295,FALSE) -> 0 | Z7: =COUNTIF(Z$8:Z$1295,FALSE) -> 0 | AA7: US | AB7: =COUNTIF(AB$8:AB$1295,FALSE) -> 0 | AC7: =COUNTIF(AC$8:AC$1295,FALSE) -> 0 | AD7: GBP | AE7: =COUNTIF(AE$8:AE$1295,FALSE) -> 0 | AF7: =COUNTIF(AF$8:AF$1295,FALSE) -> 0 | AG7: V_10EOM | AH7: =COUNTIF(AH$8:AH$1295,FALSE) -> 0 | AI7: =COUNTIF(AI$8:AI$1295,FALSE) -> 0 | AJ7: V_DD_BASE | AK7: =COUNTIF(AK$8:AK$1295,FALSE) -> 0 | AL7: =COUNTIF(AL$8:AL$1295,FALSE) -> 0 | AM7: S-DOM | AN7: =COUNTIF(AN$8:AN$1295,FALSE) -> 0 | AO7: =COUNTIF(AO$8:AO$1295,FALSE) -> 0 | AP7: Kraft Heinz Brakes Company | AQ7: =COUNTIF(AQ$8:AQ$1295,FALSE) -> 0 | AR7: =COUNTIF(AR$8:AR$1295,FALSE) -> 0 | AS7: Kraft Heinz GB Co. Limited | AT7: =COUNTIF(AT$8:AT$1295,FALSE) -> 0 | AU7: =COUNTIF(AU$8:AU$1295,FALSE) -> 0 | AV7: Kraft Heinz Brakes C | AW7: =COUNTIF(AW$8:AW$1295,FALSE) -> 0 | AX7: =COUNTIF(AX$8:AX$1295,FALSE) -> 0 | AY7: Kraft | AZ7: =COUNTIF(AZ$8:AZ$1295,FALSE) -> 0 | BA7: =COUNTIF(BA$8:BA$1295,FALSE) -> 1 | BB7: 45742 | BC7: =COUNTIF(BC$8:BC$1295,FALSE) -> 0 | BD7: =COUNTIF(BD$8:BD$1295,FALSE) -> 0 | BE7: 45742 | BF7: =COUNTIF(BF$8:BF$1295,FALSE) -> 0 | BG7: =COUNTIF(BG$8:BG$1295,FALSE) -> 0 | BH7: GB02 | BI7: =COUNTIF(BI$8:BI$1295,FALSE) -> 0 | BJ7: =COUNTIF(BJ$8:BJ$1295,FALSE) -> 0 | BK7: Director of Sales Address | BL7: =COUNTIF(BL$8:BL$1295,FALSE) -> 1 | BM7: =COUNTIF(BM$8:BM$1295,FALSE) -> 1 | BN7: Active | BO7: =COUNTIF(BO$8:BO$1295,FALSE) -> 0 | BP7: =COUNTIF(BP$8:BP$1295,FALSE) -> 0 | BQ7: GB02 | BR7: =COUNTIF(BR$8:BR$1295,FALSE) -> 0 | BS7: =COUNTIF(BS$8:BS$1295,FALSE) -> 0 | BT7: Duty Paid | BU7: =COUNTIF(BU$8:BU$1295,FALSE) -> 0 | BV7: =COUNTIF(BV$8:BV$1295,FALSE) -> 0 | BW7: Yes | BX7: =COUNTIF(BX$8:BX$1295,FALSE) -> 0 | BY7: =COUNTIF(BY$8:BY$1295,FALSE) -> 0
A8: =COUNTA($C$8:$C$1295) -> 233 | B8: =COUNTIF(C8:XFD8,"FALSE") -> 0 | C8: 217939 | D8: SVENSKA INSJÖFISKARENAS AB | E8: Trade | F8: 5562077049 | G8: =IF(NOT(ISBLANK($C8)),IF(NOT(ISBLANK(F8)),TRUE,FALSE),"") -> TRUE | H8: {=IF(NOT(ISBLANK($C8)),AND(G8=TRUE,LEN(F8)<30,NOT(ISNUMBER(FIND('List of Values'!$C$2:$C$20,F8)))),"")} -> TRUE | I8: SE556207704901 | J8: =IF(NOT(ISBLANK($C8)),TRUE,"") -> TRUE | K8: {=IF(NOT(ISBLANK($C8)),AND(J8=TRUE,LEN(I8)<20,NOT(ISNUMBER(FIND('List of Values'!$C$2:$C$20,I8)))),"")} -> TRUE | L8: LILLÅSGATAN 3 | M8: =IF(NOT(ISBLANK($C8)),IF(NOT(ISBLANK(L8)),TRUE,FALSE),"") -> TRUE | N8: {=IF(NOT(ISBLANK($C8)),AND(M8=TRUE,LEN(L8)<81,NOT(ISNUMBER(FIND('List of Values'!$C$2:$C$20,L8)))),"")} -> TRUE | P8: =IF(NOT(ISBLANK($C8)),TRUE,"") -> TRUE | Q8: {=IF(NOT(ISBLANK($C8)),AND(P8=TRUE,LEN(O8)<81,NOT(ISNUMBER(FIND('List of Values'!$C$2:$C$20,O8)))),"")} -> TRUE | R8: VÄSTRA FRÖLUNDA | S8: =IF(NOT(ISBLANK($C8)),IF(NOT(ISBLANK(R8)),TRUE,FALSE),"") -> TRUE | T8: {=IF(NOT(ISBLANK($C8)),AND(S8=TRUE,LEN(R8)<61,NOT(ISNUMBER(FIND('List of Values'!$C$2:$C$23,R8)))),"")} -> TRUE | V8: =IF(NOT(ISBLANK($C8)),TRUE,"") -> TRUE | W8: {=IF(NOT(ISBLANK($C8)),AND(V8=TRUE,LEN(U8)<61,NOT(ISNUMBER(FIND('List of Values'!$C$2:$C$23,U8)))),"")} -> TRUE | X8: 426 77 | Y8: =IF(NOT(ISBLANK($C8)),IF(NOT(ISBLANK(X8)),TRUE,FALSE),"") -> TRUE | Z8: {=IF(NOT(ISBLANK($C8)),AND(Y8=TRUE,LEN(X8)<81,NOT(ISNUMBER(FIND('List of Values'!$C$2:$C$23,X8)))),"")} -> TRUE | AA8: SE | AB8: =IF(NOT(ISBLANK($C8)),IF(NOT(ISBLANK(AA8)),TRUE,FALSE),"") -> TRUE | AC8: =IF(NOT(ISBLANK($C8)),AND(AB8=TRUE,NOT(COUNTIF('List of Values'!$B$2:$B$255,AA8)=0)),"") -> TRUE | AD8: SEK | AE8: =IF(NOT(ISBLANK($C8)),IF(NOT(ISBLANK(AD8)),TRUE,FALSE),"") -> TRUE | AF8: =IF(NOT(ISBLANK($C8)),AND(AE8=TRUE,NOT(COUNTIF('List of Values'!$F$2:$F$255,AD8)=0)),"") -> TRUE | AG8: V_30NET | AH8: =IF(NOT(ISBLANK($C8)),IF(NOT(ISBLANK(AG8)),TRUE,FALSE),"") -> TRUE | AI8: =IF(NOT(ISBLANK($C8)),AND(AH8=TRUE,NOT(COUNTIF('List of Values'!$N$2:$N$40,AG8)=0)),"") -> TRUE | AJ8: V_BANK | AK8: =IF(NOT(ISBLANK($C8)),IF(NOT(ISBLANK(AJ8)),TRUE,FALSE),"") -> TRUE | AL8: =IF(NOT(ISBLANK($C8)),AND(AK8=TRUE,NOT(COUNTIF('List of Values'!$O$2:$O$30,AJ8)=0)),"") -> TRUE | AM8: S-DOM | AN8: =IF(NOT(ISBLANK($C8)),IF(NOT(ISBLANK(AM8)),TRUE,FALSE),"") -> TRUE | AO8: =IF(NOT(ISBLANK($C8)),AND(AN8=TRUE,NOT(COUNTIF('List of Values'!$AF$2:$AF$20,AM8)=0)),"") -> TRUE | AQ8: =IF(NOT(ISBLANK($C8)),TRUE,"") -> TRUE | AR8: {=IF(NOT(ISBLANK($C8)),AND(AQ8=TRUE,LEN(AP8)<81,NOT(ISNUMBER(FIND('List of Values'!$C$2:$C$20,AP8)))),"")} -> TRUE | AS8: =D8 -> SVENSKA INSJÖFISKARENAS AB | AT8: =IF(NOT(ISBLANK($C8)),IF(NOT(ISBLANK(AS8)),TRUE,FALSE),"") -> TRUE | AU8: {=IF(NOT(ISBLANK($C8)),AND(AT8=TRUE,LEN(AS8)<81,NOT(ISNUMBER(FIND('List of Values'!$C$2:$C$20,AS8)))),"")} -> TRUE | AV8: SVENSKAINSJÖFISKAREN | AW8: =IF(NOT(ISBLANK($C8)),IF(NOT(ISBLANK(AV8)),TRUE,FALSE),"") -> TRUE | AX8: {=IF(NOT(ISBLANK($C8)),AND(AW8=TRUE,LEN(AV8)<21,NOT(ISNUMBER(FIND('List of Values'!$C$2:$C$20,AV8)))),"")} -> TRUE | AY8: 14866 | AZ8: =IF(NOT(ISBLANK($C8)),IF(NOT(ISBLANK(AY8)),TRUE,FALSE),"") -> TRUE | BA8: =IF(NOT(ISBLANK($C8)),AND(AZ8=TRUE,NOT(COUNTIF('List of Values'!$R$2:$R$400,AY8)=0)),"") -> TRUE | BC8: =IF(NOT(ISBLANK($C8)),TRUE,"") -> TRUE | BD8: {=IF(NOT(ISBLANK($C8)),OR(ISBLANK(BB8),AND(NOT(ISNUMBER(FIND('List of Values'!$C$2:$C$23,BB8))),ISNUMBER(DATEVALUE(BB8)))),"")} -> TRUE | BF8: =IF(NOT(ISBLANK($C8)),TRUE,"") -> TRUE | BG8: {=IF(NOT(ISBLANK($C8)),OR(ISBLANK(BE8),AND(NOT(ISNUMBER(FIND('List of Values'!$C$2:$C$23,BE8))),ISNUMBER(DATEVALUE(BE8)))),"")} -> TRUE | BI8: =IF(NOT(ISBLANK($C8)),TRUE,"") -> TRUE | BJ8: =IF(NOT(ISBLANK($C8)),OR(ISBLANK(BH8),AND(LEN(BH8)<14,ISNUMBER(BH8))),"") -> TRUE | BK8: Invoice | BL8: =IF(NOT(ISBLANK($C8)),IF(NOT(ISBLANK(BK8)),TRUE,FALSE),"") -> TRUE | BM8: =IF(NOT(ISBLANK($C8)),AND(BL8=TRUE,NOT(COUNTIF('List of Values'!$A$2:$A$20,BK8)=0)),"") -> TRUE | BN8: Active | BO8: =IF(NOT(ISBLANK($C8)),IF(NOT(ISBLANK(BN8)),TRUE,FALSE),"") -> TRUE | BP8: =IF(NOT(ISBLANK($C8)),OR(BN8="active",BN8="delisted"),"") -> TRUE | BR8: =IF(NOT(ISBLANK($C8)),OR(AND($E8="intercompany",NOT(ISBLANK(BQ8))),AND(NOT($E8="intercompany"),ISBLANK(BQ8))),"") -> TRUE | BS8: =IF(NOT(ISBLANK($C8)),OR(ISBLANK(BQ8),NOT(COUNTIF('List of Values'!$K$2:$K$30,BQ8)=0)),"") -> TRUE | BU8: =IF(NOT(ISBLANK($C8)),TRUE,"") -> TRUE | BV8: =IF(NOT(ISBLANK($C8)),OR(ISBLANK(BT8),BT8="duty paid",BT8="bond"),"") -> TRUE | BX8: =IF(NOT(ISBLANK($C8)),TRUE,"") -> TRUE | BY8: =IF(NOT(ISBLANK($C8)),OR(ISBLANK(BW8),BW8="duty paid",BW8="bond"),"") -> TRUE | BZ8: =_xlfn.XLOOKUP(C8,[1]Blad1!$A:$A,[1]Blad1!$D:$D,"")
B9: =COUNTIF(C9:XFD9,"FALSE") -> 0 | C9: 218036 | D9: FÖRETAGARNA | E9: Indirect | F9: 5560933011 | G9: =IF(NOT(ISBLANK($C9)),IF(NOT(ISBLANK(F9)),TRUE,FALSE),"") -> TRUE | H9: {=IF(NOT(ISBLANK($C9)),AND(G9=TRUE,LEN(F9)<30,NOT(ISNUMBER(FIND('List of Values'!$C$2:$C$20,F9)))),"")} -> TRUE | I9: SE556093301101 | J9: =IF(NOT(ISBLANK($C9)),TRUE,"") -> TRUE | K9: {=IF(NOT(ISBLANK($C9)),AND(J9=TRUE,LEN(I9)<20,NOT(ISNUMBER(FIND('List of Values'!$C$2:$C$20,I9)))),"")} -> TRUE | L9: REGERINGSGATAN 52 | M9: =IF(NOT(ISBLANK($C9)),IF(NOT(ISBLANK(L9)),TRUE,FALSE),"") -> TRUE | N9: {=IF(NOT(ISBLANK($C9)),AND(M9=TRUE,LEN(L9)<81,NOT(ISNUMBER(FIND('List of Values'!$C$2:$C$20,L9)))),"")} -> TRUE | P9: =IF(NOT(ISBLANK($C9)),TRUE,"") -> TRUE | Q9: {=IF(NOT(ISBLANK($C9)),AND(P9=TRUE,LEN(O9)<81,NOT(ISNUMBER(FIND('List of Values'!$C$2:$C$20,O9)))),"")} -> TRUE | R9: STOCKHOLM | S9: =IF(NOT(ISBLANK($C9)),IF(NOT(ISBLANK(R9)),TRUE,FALSE),"") -> TRUE | T9: {=IF(NOT(ISBLANK($C9)),AND(S9=TRUE,LEN(R9)<61,NOT(ISNUMBER(FIND('List of Values'!$C$2:$C$23,R9)))),"")} -> TRUE | V9: =IF(NOT(ISBLANK($C9)),TRUE,"") -> TRUE | W9: {=IF(NOT(ISBLANK($C9)),AND(V9=TRUE,LEN(U9)<61,NOT(ISNUMBER(FIND('List of Values'!$C$2:$C$23,U9)))),"")} -> TRUE | X9: 106 67 | Y9: =IF(NOT(ISBLANK($C9)),IF(NOT(ISBLANK(X9)),TRUE,FALSE),"") -> TRUE | Z9: {=IF(NOT(ISBLANK($C9)),AND(Y9=TRUE,LEN(X9)<81,NOT(ISNUMBER(FIND('List of Values'!$C$2:$C$23,X9)))),"")} -> TRUE | AA9: SE | AB9: =IF(NOT(ISBLANK($C9)),IF(NOT(ISBLANK(AA9)),TRUE,FALSE),"") -> TRUE | AC9: =IF(NOT(ISBLANK($C9)),AND(AB9=TRUE,NOT(COUNTIF('List of Values'!$B$2:$B$255,AA9)=0)),"") -> TRUE | AD9: SEK | AE9: =IF(NOT(ISBLANK($C9)),IF(NOT(ISBLANK(AD9)),TRUE,FALSE),"") -> TRUE | AF9: =IF(NOT(ISBLANK($C9)),AND(AE9=TRUE,NOT(COUNTIF('List of Values'!$F$2:$F$255,AD9)=0)),"") -> TRUE | AG9: V_10EOM | AH9: =IF(NOT(ISBLANK($C9)),IF(NOT(ISBLANK(AG9)),TRUE,FALSE),"") -> TRUE | AI9: =IF(NOT(ISBLANK($C9)),AND(AH9=TRUE,NOT(COUNTIF('List of Values'!$N$2:$N$40,AG9)=0)),"") -> TRUE | AJ9: V_BANK | AK9: =IF(NOT(ISBLANK($C9)),IF(NOT(ISBLANK(AJ9)),TRUE,FALSE),"") -> TRUE | AL9: =IF(NOT(ISBLANK($C9)),AND(AK9=TRUE,NOT(COUNTIF('List of Values'!$O$2:$O$30,AJ9)=0)),"") -> TRUE | AM9: S-DOM | AN9: =IF(NOT(ISBLANK($C9)),IF(NOT(ISBLANK(AM9)),TRUE,FALSE),"") -> TRUE | AO9: =IF(NOT(ISBLANK($C9)),AND(AN9=TRUE,NOT(COUNTIF('List of Values'!$AF$2:$AF$20,AM9)=0)),"") -> TRUE | AQ9: =IF(NOT(ISBLANK($C9)),TRUE,"") -> TRUE | AR9: {=IF(NOT(ISBLANK($C9)),AND(AQ9=TRUE,LEN(AP9)<81,NOT(ISNUMBER(FIND('List of Values'!$C$2:$C$20,AP9)))),"")} -> TRUE | AS9: =D9 -> FÖRETAGARNA | AT9: =IF(NOT(ISBLANK($C9)),IF(NOT(ISBLANK(AS9)),TRUE,FALSE),"") -> TRUE | AU9: {=IF(NOT(ISBLANK($C9)),AND(AT9=TRUE,LEN(AS9)<81,NOT(ISNUMBER(FIND('List of Values'!$C$2:$C$20,AS9)))),"")} -> TRUE | AV9: FÖRETAGARNA | AW9: =IF(NOT(ISBLANK($C9)),IF(NOT(ISBLANK(AV9)),TRUE,FALSE),"") -> TRUE | AX9: {=IF(NOT(ISBLANK($C9)),AND(AW9=TRUE,LEN(AV9)<21,NOT(ISNUMBER(FIND('List of Values'!$C$2:$C$20,AV9)))),"")} -> TRUE | AY9: 10001 | AZ9: =IF(NOT(ISBLANK($C9)),TRUE,"") -> TRUE | BA9: =IF(NOT(ISBLANK($C9)),AND(AZ9=TRUE,NOT(COUNTIF('List of Values'!$R$2:$R$400,AY9)=0)),"") -> TRUE | BC9: =IF(NOT(ISBLANK($C9)),TRUE,"") -> TRUE | BD9: {=IF(NOT(ISBLANK($C9)),OR(ISBLANK(BB9),AND(NOT(ISNUMBER(FIND('List of Values'!$C$2:$C$23,BB9))),ISNUMBER(DATEVALUE(BB9)))),"")} -> TRUE | BF9: =IF(NOT(ISBLANK($C9)),TRUE,"") -> TRUE | BG9: {=IF(NOT(ISBLANK($C9)),OR(ISBLANK(BE9),AND(NOT(ISNUMBER(FIND('List of Values'!$C$2:$C$23,BE9))),ISNUMBER(DATEVALUE(BE9)))),"")} -> TRUE | BI9: =IF(NOT(ISBLANK($C9)),TRUE,"") -> TRUE | BJ9: =IF(NOT(ISBLANK($C9)),OR(ISBLANK(BH9),AND(LEN(BH9)<14,ISNUMBER(BH9))),"") -> TRUE | BK9: Invoice | BL9: =IF(NOT(ISBLANK($C9)),IF(NOT(ISBLANK(BK9)),TRUE,FALSE),"") -> TRUE | BM9: =IF(NOT(ISBLANK($C9)),AND(BL9=TRUE,NOT(COUNTIF('List of Values'!$A$2:$A$20,BK9)=0)),"") -> TRUE | BN9: Active | BO9: =IF(NOT(ISBLANK($C9)),IF(NOT(ISBLANK(BN9)),TRUE,FALSE),"") -> TRUE | BP9: =IF(NOT(ISBLANK($C9)),OR(BN9="active",BN9="delisted"),"") -> TRUE | BR9: =IF(NOT(ISBLANK($C9)),OR(AND($E9="intercompany",NOT(ISBLANK(BQ9))),AND(NOT($E9="intercompany"),ISBLANK(BQ9))),"") -> TRUE | BS9: =IF(NOT(ISBLANK($C9)),OR(ISBLANK(BQ9),NOT(COUNTIF('List of Values'!$K$2:$K$30,BQ9)=0)),"") -> TRUE | BU9: =IF(NOT(ISBLANK($C9)),TRUE,"") -> TRUE | BV9: =IF(NOT(ISBLANK($C9)),OR(ISBLANK(BT9),BT9="duty paid",BT9="bond"),"") -> TRUE | BX9: =IF(NOT(ISBLANK($C9)),TRUE,"") -> TRUE | BY9: =IF(NOT(ISBLANK($C9)),OR(ISBLANK(BW9),BW9="duty paid",BW9="bond"),"") -> TRUE | BZ9: =_xlfn.XLOOKUP(C9,[1]Blad1!$A:$A,[1]Blad1!$D:$D,"")
B10: =COUNTIF(C10:XFD10,"FALSE") -> 0 | C10: 217965 | D10: HAVETS SKAFFERI I KODE AB | E10: Trade | F10: 5567081319 | G10: =IF(NOT(ISBLANK($C10)),IF(NOT(ISBLANK(F10)),TRUE,FALSE),"") -> TRUE | H10: {=IF(NOT(ISBLANK($C10)),AND(G10=TRUE,LEN(F10)<30,NOT(ISNUMBER(FIND('List of Values'!$C$2:$C$20,F10)))),"")} -> TRUE | I10: SE556708131901 | J10: =IF(NOT(ISBLANK($C10)),TRUE,"") -> TRUE | K10: {=IF(NOT(ISBLANK($C10)),AND(J10=TRUE,LEN(I10)<20,NOT(ISNUMBER(FIND('List of Values'!$C$2:$C$20,I10)))),"")} -> TRUE | L10: FISKHAMNEN PIRHUS 1 | M10: =IF(NOT(ISBLANK($C10)),IF(NOT(ISBLANK(L10)),TRUE,FALSE),"") -> TRUE | N10: {=IF(NOT(ISBLANK($C10)),AND(M10=TRUE,LEN(L10)<81,NOT(ISNUMBER(FIND('List of Values'!$C$2:$C$20,L10)))),"")} -> TRUE | P10: =IF(NOT(ISBLANK($C10)),TRUE,"") -> TRUE | Q10: {=IF(NOT(ISBLANK($C10)),AND(P10=TRUE,LEN(O10)<81,NOT(ISNUMBER(FIND('List of Values'!$C$2:$C$20,O10)))),"")} -> TRUE | R10: GÖTEBORG | S10: =IF(NOT(ISBLANK($C10)),IF(NOT(ISBLANK(R10)),TRUE,FALSE),"") -> TRUE | T10: {=IF(NOT(ISBLANK($C10)),AND(S10=TRUE,LEN(R10)<61,NOT(ISNUMBER(FIND('List of Values'!$C$2:$C$23,R10)))),"")} -> TRUE | V10: =IF(NOT(ISBLANK($C10)),TRUE,"") -> TRUE | W10: {=IF(NOT(ISBLANK($C10)),AND(V10=TRUE,LEN(U10)<61,NOT(ISNUMBER(FIND('List of Values'!$C$2:$C$23,U10)))),"")} -> TRUE | X10: 414 58 | Y10: =IF(NOT(ISBLANK($C10)),IF(NOT(ISBLANK(X10)),TRUE,FALSE),"") -> TRUE | Z10: {=IF(NOT(ISBLANK($C10)),AND(Y10=TRUE,LEN(X10)<81,NOT(ISNUMBER(FIND('List of Values'!$C$2:$C$23,X10)))),"")} -> TRUE | AA10: SE | AB10: =IF(NOT(ISBLANK($C10)),IF(NOT(ISBLANK(AA10)),TRUE,FALSE),"") -> TRUE | AC10: =IF(NOT(ISBLANK($C10)),AND(AB10=TRUE,NOT(COUNTIF('List of Values'!$B$2:$B$255,AA10)=0)),"") -> TRUE | AD10: SEK | AE10: =IF(NOT(ISBLANK($C10)),IF(NOT(ISBLANK(AD10)),TRUE,FALSE),"") -> TRUE | AF10: =IF(NOT(ISBLANK($C10)),AND(AE10=TRUE,NOT(COUNTIF('List of Values'!$F$2:$F$255,AD10)=0)),"") -> TRUE | AG10: V_10EOM | AH10: =IF(NOT(ISBLANK($C10)),IF(NOT(ISBLANK(AG10)),TRUE,FALSE),"") -> TRUE | AI10: =IF(NOT(ISBLANK($C10)),AND(AH10=TRUE,NOT(COUNTIF('List of Values'!$N$2:$N$40,AG10)=0)),"") -> TRUE | AJ10: V_BANK | AK10: =IF(NOT(ISBLANK($C10)),IF(NOT(ISBLANK(AJ10)),TRUE,FALSE),"") -> TRUE | AL10: =IF(NOT(ISBLANK($C10)),AND(AK10=TRUE,NOT(COUNTIF('List of Values'!$O$2:$O$30,AJ10)=0)),"") -> TRUE | AM10: S-DOM | AN10: =IF(NOT(ISBLANK($C10)),IF(NOT(ISBLANK(AM10)),TRUE,FALSE),"") -> TRUE | AO10: =IF(NOT(ISBLANK($C10)),AND(AN10=TRUE,NOT(COUNTIF('List of Values'!$AF$2:$AF$20,AM10)=0)),"") -> TRUE | AQ10: =IF(NOT(ISBLANK($C10)),TRUE,"") -> TRUE | AR10: {=IF(NOT(ISBLANK($C10)),AND(AQ10=TRUE,LEN(AP10)<81,NOT(ISNUMBER(FIND('List of Values'!$C$2:$C$20,AP10)))),"")} -> TRUE | AS10: =D10 -> HAVETS SKAFFERI I KODE AB | AT10: =IF(NOT(ISBLANK($C10)),IF(NOT(ISBLANK(AS10)),TRUE,FALSE),"") -> TRUE | AU10: {=IF(NOT(ISBLANK($C10)),AND(AT10=TRUE,LEN(AS10)<81,NOT(ISNUMBER(FIND('List of Values'!$C$2:$C$20,AS10)))),"")} -> TRUE | AV10: HAVETSSKAFFERIIKODEA | AW10: =IF(NOT(ISBLANK($C10)),IF(NOT(ISBLANK(AV10)),TRUE,FALSE),"") -> TRUE | AX10: {=IF(NOT(ISBLANK($C10)),AND(AW10=TRUE,LEN(AV10)<21,NOT(ISNUMBER(FIND('List of Values'!$C$2:$C$20,AV10)))),"")} -> TRUE | AY10: 12418 | AZ10: =IF(NOT(ISBLANK($C10)),TRUE,"") -> TRUE | BA10: =IF(NOT(ISBLANK($C10)),AND(AZ10=TRUE,NOT(COUNTIF('List of Values'!$R$2:$R$400,AY10)=0)),"") -> TRUE | BC10: =IF(NOT(ISBLANK($C10)),TRUE,"") -> TRUE | BD10: {=IF(NOT(ISBLANK($C10)),OR(ISBLANK(BB10),AND(NOT(ISNUMBER(FIND('List of Values'!$C$2:$C$23,BB10))),ISNUMBER(DATEVALUE(BB10)))),"")} -> TRUE | BF10: =IF(NOT(ISBLANK($C10)),TRUE,"") -> TRUE | BG10: {=IF(NOT(ISBLANK($C10)),OR(ISBLANK(BE10),AND(NOT(ISNUMBER(FIND('List of Values'!$C$2:$C$23,BE10))),ISNUMBER(DATEVALUE(BE10)))),"")} -> TRUE | BI10: =IF(NOT(ISBLANK($C10)),TRUE,"") -> TRUE | BJ10: =IF(NOT(ISBLANK($C10)),OR(ISBLANK(BH10),AND(LEN(BH10)<14,ISNUMBER(BH10))),"") -> TRUE | BK10: Invoice | BL10: =IF(NOT(ISBLANK($C10)),IF(NOT(ISBLANK(BK10)),TRUE,FALSE),"") -> TRUE | BM10: =IF(NOT(ISBLANK($C10)),AND(BL10=TRUE,NOT(COUNTIF('List of Values'!$A$2:$A$20,BK10)=0)),"") -> TRUE | BN10: Active | BO10: =IF(NOT(ISBLANK($C10)),IF(NOT(ISBLANK(BN10)),TRUE,FALSE),"") -> TRUE | BP10: =IF(NOT(ISBLANK($C10)),OR(BN10="active",BN10="delisted"),"") -> TRUE | BR10: =IF(NOT(ISBLANK($C10)),OR(AND($E10="intercompany",NOT(ISBLANK(BQ10))),AND(NOT($E10="intercompany"),ISBLANK(BQ10))),"") -> TRUE | BS10: =IF(NOT(ISBLANK($C10)),OR(ISBLANK(BQ10),NOT(COUNTIF('List of Values'!$K$2:$K$30,BQ10)=0)),"") -> TRUE | BU10: =IF(NOT(ISBLANK($C10)),TRUE,"") -> TRUE | BV10: =IF(NOT(ISBLANK($C10)),OR(ISBLANK(BT10),BT10="duty paid",BT10="bond"),"") -> TRUE | BX10: =IF(NOT(ISBLANK($C10)),TRUE,"") -> TRUE | BY10: =IF(NOT(ISBLANK($C10)),OR(ISBLANK(BW10),BW10="duty paid",BW10="bond"),"") -> TRUE | BZ10: =_xlfn.XLOOKUP(C10,[1]Blad1!$A:$A,[1]Blad1!$D:$D,"")
B11: =COUNTIF(C11:XFD11,"FALSE") -> 0 | C11: 218285 | D11: EKO MUSSLOR P.A.C AB | E11: Trade | F11: 5568028244 | G11: =IF(NOT(ISBLANK($C11)),IF(NOT(ISBLANK(F11)),TRUE,FALSE),"") -> TRUE | H11: {=IF(NOT(ISBLANK($C11)),AND(G11=TRUE,LEN(F11)<30,NOT(ISNUMBER(FIND('List of Values'!$C$2:$C$20,F11)))),"")} -> TRUE | I11: SE556802824401 | J11: =IF(NOT(ISBLANK($C11)),TRUE,"") -> TRUE | K11: {=IF(NOT(ISBLANK($C11)),AND(J11=TRUE,LEN(I11)<20,NOT(ISNUMBER(FIND('List of Values'!$C$2:$C$20,I11)))),"")} -> TRUE | L11: RINGÖGATAN 33 | M11: =IF(NOT(ISBLANK($C11)),IF(NOT(ISBLANK(L11)),TRUE,FALSE),"") -> TRUE | N11: {=IF(NOT(ISBLANK($C11)),AND(M11=TRUE,LEN(L11)<81,NOT(ISNUMBER(FIND('List of Values'!$C$2:$C$20,L11)))),"")} -> TRUE | P11: =IF(NOT(ISBLANK($C11)),TRUE,"") -> TRUE | Q11: {=IF(NOT(ISBLANK($C11)),AND(P11=TRUE,LEN(O11)<81,NOT(ISNUMBER(FIND('List of Values'!$C$2:$C$20,O11)))),"")} -> TRUE | R11: GÖTEBORG | S11: =IF(NOT(ISBLANK($C11)),IF(NOT(ISBLANK(R11)),TRUE,FALSE),"") -> TRUE | T11: {=IF(NOT(ISBLANK($C11)),AND(S11=TRUE,LEN(R11)<61,NOT(ISNUMBER(FIND('List of Values'!$C$2:$C$23,R11)))),"")} -> TRUE | V11: =IF(NOT(ISBLANK($C11)),TRUE,"") -> TRUE | W11: {=IF(NOT(ISBLANK($C11)),AND(V11=TRUE,LEN(U11)<61,NOT(ISNUMBER(FIND('List of Values'!$C$2:$C$23,U11)))),"")} -> TRUE | X11: 417 07 | Y11: =IF(NOT(ISBLANK($C11)),IF(NOT(ISBLANK(X11)),TRUE,FALSE),"") -> TRUE | Z11: {=IF(NOT(ISBLANK($C11)),AND(Y11=TRUE,LEN(X11)<81,NOT(ISNUMBER(FIND('List of Values'!$C$2:$C$23,X11)))),"")} -> TRUE | AA11: SE | AB11: =IF(NOT(ISBLANK($C11)),IF(NOT(ISBLANK(AA11)),TRUE,FALSE),"") -> TRUE | AC11: =IF(NOT(ISBLANK($C11)),AND(AB11=TRUE,NOT(COUNTIF('List of Values'!$B$2:$B$255,AA11)=0)),"") -> TRUE | AD11: SEK | AE11: =IF(NOT(ISBLANK($C11)),IF(NOT(ISBLANK(AD11)),TRUE,FALSE),"") -> TRUE | AF11: =IF(NOT(ISBLANK($C11)),AND(AE11=TRUE,NOT(COUNTIF('List of Values'!$F$2:$F$255,AD11)=0)),"") -> TRUE | AG11: V_20NET | AH11: =IF(NOT(ISBLANK($C11)),IF(NOT(ISBLANK(AG11)),TRUE,FALSE),"") -> TRUE | AI11: =IF(NOT(ISBLANK($C11)),AND(AH11=TRUE,NOT(COUNTIF('List of Values'!$N$2:$N$40,AG11)=0)),"") -> TRUE | AJ11: V_BANK | AK11: =IF(NOT(ISBLANK($C11)),IF(NOT(ISBLANK(AJ11)),TRUE,FALSE),"") -> TRUE | AL11: =IF(NOT(ISBLANK($C11)),AND(AK11=TRUE,NOT(COUNTIF('List of Values'!$O$2:$O$30,AJ11)=0)),"") -> TRUE | AM11: S-DOM | AN11: =IF(NOT(ISBLANK($C11)),IF(NOT(ISBLANK(AM11)),TRUE,FALSE),"") -> TRUE | AO11: =IF(NOT(ISBLANK($C11)),AND(AN11=TRUE,NOT(COUNTIF('List of Values'!$AF$2:$AF$20,AM11)=0)),"") -> TRUE | AQ11: =IF(NOT(ISBLANK($C11)),TRUE,"") -> TRUE | AR11: {=IF(NOT(ISBLANK($C11)),AND(AQ11=TRUE,LEN(AP11)<81,NOT(ISNUMBER(FIND('List of Values'!$C$2:$C$20,AP11)))),"")} -> TRUE | AS11: =D11 -> EKO MUSSLOR P.A.C AB | AT11: =IF(NOT(ISBLANK($C11)),IF(NOT(ISBLANK(AS11)),TRUE,FALSE),"") -> TRUE | AU11: {=IF(NOT(ISBLANK($C11)),AND(AT11=TRUE,LEN(AS11)<81,NOT(ISNUMBER(FIND('List of Values'!$C$2:$C$20,AS11)))),"")} -> TRUE | AV11: EKOMUSSLORP.A.CAB | AW11: =IF(NOT(ISBLANK($C11)),IF(NOT(ISBLANK(AV11)),TRUE,FALSE),"") -> TRUE | AX11: {=IF(NOT(ISBLANK($C11)),AND(AW11=TRUE,LEN(AV11)<21,NOT(ISNUMBER(FIND('List of Values'!$C$2:$C$20,AV11)))),"")} -> TRUE | AY11: 11667 | AZ11: =IF(NOT(ISBLANK($C11)),TRUE,"") -> TRUE | BA11: =IF(NOT(ISBLANK($C11)),AND(AZ11=TRUE,NOT(COUNTIF('List of Values'!$R$2:$R$400,AY11)=0)),"") -> TRUE | BC11: =IF(NOT(ISBLANK($C11)),TRUE,"") -> TRUE | BD11: {=IF(NOT(ISBLANK($C11)),OR(ISBLANK(BB11),AND(NOT(ISNUMBER(FIND('List of Values'!$C$2:$C$23,BB11))),ISNUMBER(DATEVALUE(BB11)))),"")} -> TRUE | BF11: =IF(NOT(ISBLANK($C11)),TRUE,"") -> TRUE | BG11: {=IF(NOT(ISBLANK($C11)),OR(ISBLANK(BE11),AND(NOT(ISNUMBER(FIND('List of Values'!$C$2:$C$23,BE11))),ISNUMBER(DATEVALUE(BE11)))),"")} -> TRUE | BI11: =IF(NOT(ISBLANK($C11)),TRUE,"") -> TRUE | BJ11: =IF(NOT(ISBLANK($C11)),OR(ISBLANK(BH11),AND(LEN(BH11)<14,ISNUMBER(BH11))),"") -> TRUE | BK11: Invoice | BL11: =IF(NOT(ISBLANK($C11)),IF(NOT(ISBLANK(BK11)),TRUE,FALSE),"") -> TRUE | BM11: =IF(NOT(ISBLANK($C11)),AND(BL11=TRUE,NOT(COUNTIF('List of Values'!$A$2:$A$20,BK11)=0)),"") -> TRUE | BN11: Active | BO11: =IF(NOT(ISBLANK($C11)),IF(NOT(ISBLANK(BN11)),TRUE,FALSE),"") -> TRUE | BP11: =IF(NOT(ISBLANK($C11)),OR(BN11="active",BN11="delisted"),"") -> TRUE | BR11: =IF(NOT(ISBLANK($C11)),OR(AND($E11="intercompany",NOT(ISBLANK(BQ11))),AND(NOT($E11="intercompany"),ISBLANK(BQ11))),"") -> TRUE | BS11: =IF(NOT(ISBLANK($C11)),OR(ISBLANK(BQ11),NOT(COUNTIF('List of Values'!$K$2:$K$30,BQ11)=0)),"") -> TRUE | BU11: =IF(NOT(ISBLANK($C11)),TRUE,"") -> TRUE | BV11: =IF(NOT(ISBLANK($C11)),OR(ISBLANK(BT11),BT11="duty paid",BT11="bond"),"") -> TRUE | BX11: =IF(NOT(ISBLANK($C11)),TRUE,"") -> TRUE | BY11: =IF(NOT(ISBLANK($C11)),OR(ISBLANK(BW11),BW11="duty paid",BW11="bond"),"") -> TRUE | BZ11: =_xlfn.XLOOKUP(C11,[1]Blad1!$A:$A,[1]Blad1!$D:$D,"") -> x
B12: =COUNTIF(C12:XFD12,"FALSE") -> 0 | C12: 218038 | D12: REMONDIS SWEDEN AB | E12: Indirect | F12: 5561142810 | G12: =IF(NOT(ISBLANK($C12)),IF(NOT(ISBLANK(F12)),TRUE,FALSE),"") -> TRUE | H12: {=IF(NOT(ISBLANK($C12)),AND(G12=TRUE,LEN(F12)<30,NOT(ISNUMBER(FIND('List of Values'!$C$2:$C$20,F12)))),"")} -> TRUE | I12: SE556114281001 | J12: =IF(NOT(ISBLANK($C12)),TRUE,"") -> TRUE | K12: {=IF(NOT(ISBLANK($C12)),AND(J12=TRUE,LEN(I12)<20,NOT(ISNUMBER(FIND('List of Values'!$C$2:$C$20,I12)))),"")} -> TRUE | L12: IMPORTGATAN 45 | M12: =IF(NOT(ISBLANK($C12)),IF(NOT(ISBLANK(L12)),TRUE,FALSE),"") -> TRUE | N12: {=IF(NOT(ISBLANK($C12)),AND(M12=TRUE,LEN(L12)<81,NOT(ISNUMBER(FIND('List of Values'!$C$2:$C$20,L12)))),"")} -> TRUE | P12: =IF(NOT(ISBLANK($C12)),TRUE,"") -> TRUE | Q12: {=IF(NOT(ISBLANK($C12)),AND(P12=TRUE,LEN(O12)<81,NOT(ISNUMBER(FIND('List of Values'!$C$2:$C$20,O12)))),"")} -> TRUE | R12: HISINGS BACKA | S12: =IF(NOT(ISBLANK($C12)),IF(NOT(ISBLANK(R12)),TRUE,FALSE),"") -> TRUE | T12: {=IF(NOT(ISBLANK($C12)),AND(S12=TRUE,LEN(R12)<61,NOT(ISNUMBER(FIND('List of Values'!$C$2:$C$23,R12)))),"")} -> TRUE | V12: =IF(NOT(ISBLANK($C12)),TRUE,"") -> TRUE | W12: {=IF(NOT(ISBLANK($C12)),AND(V12=TRUE,LEN(U12)<61,NOT(ISNUMBER(FIND('List of Values'!$C$2:$C$23,U12)))),"")} -> TRUE | X12: 422 46 | Y12: =IF(NOT(ISBLANK($C12)),IF(NOT(ISBLANK(X12)),TRUE,FALSE),"") -> TRUE | Z12: {=IF(NOT(ISBLANK($C12)),AND(Y12=TRUE,LEN(X12)<81,NOT(ISNUMBER(FIND('List of Values'!$C$2:$C$23,X12)))),"")} -> TRUE | AA12: SE | AB12: =IF(NOT(ISBLANK($C12)),IF(NOT(ISBLANK(AA12)),TRUE,FALSE),"") -> TRUE | AC12: =IF(NOT(ISBLANK($C12)),AND(AB12=TRUE,NOT(COUNTIF('List of Values'!$B$2:$B$255,AA12)=0)),"") -> TRUE | AD12: SEK | AE12: =IF(NOT(ISBLANK($C12)),IF(NOT(ISBLANK(AD12)),TRUE,FALSE),"") -> TRUE | AF12: =IF(NOT(ISBLANK($C12)),AND(AE12=TRUE,NOT(COUNTIF('List of Values'!$F$2:$F$255,AD12)=0)),"") -> TRUE | AG12: V_20NET | AH12: =IF(NOT(ISBLANK($C12)),IF(NOT(ISBLANK(AG12)),TRUE,FALSE),"") -> TRUE | AI12: =IF(NOT(ISBLANK($C12)),AND(AH12=TRUE,NOT(COUNTIF('List of Values'!$N$2:$N$40,AG12)=0)),"") -> TRUE | AJ12: V_BANK | AK12: =IF(NOT(ISBLANK($C12)),IF(NOT(ISBLANK(AJ12)),TRUE,FALSE),"") -> TRUE | AL12: =IF(NOT(ISBLANK($C12)),AND(AK12=TRUE,NOT(COUNTIF('List of Values'!$O$2:$O$30,AJ12)=0)),"") -> TRUE | AM12: S-DOM | AN12: =IF(NOT(ISBLANK($C12)),IF(NOT(ISBLANK(AM12)),TRUE,FALSE),"") -> TRUE | AO12: =IF(NOT(ISBLANK($C12)),AND(AN12=TRUE,NOT(COUNTIF('List of Values'!$AF$2:$AF$20,AM12)=0)),"") -> TRUE | AQ12: =IF(NOT(ISBLANK($C12)),TRUE,"") -> TRUE | AR12: {=IF(NOT(ISBLANK($C12)),AND(AQ12=TRUE,LEN(AP12)<81,NOT(ISNUMBER(FIND('List of Values'!$C$2:$C$20,AP12)))),"")} -> TRUE | AS12: =D12 -> REMONDIS SWEDEN AB | AT12: =IF(NOT(ISBLANK($C12)),IF(NOT(ISBLANK(AS12)),TRUE,FALSE),"") -> TRUE | AU12: {=IF(NOT(ISBLANK($C12)),AND(AT12=TRUE,LEN(AS12)<81,NOT(ISNUMBER(FIND('List of Values'!$C$2:$C$20,AS12)))),"")} -> TRUE | AV12: REMONDISSWEDENAB | AW12: =IF(NOT(ISBLANK($C12)),IF(NOT(ISBLANK(AV12)),TRUE,FALSE),"") -> TRUE | AX12: {=IF(NOT(ISBLANK($C12)),AND(AW12=TRUE,LEN(AV12)<21,NOT(ISNUMBER(FIND('List of Values'!$C$2:$C$20,AV12)))),"")} -> TRUE | AY12: 10001 | AZ12: =IF(NOT(ISBLANK($C12)),TRUE,"") -> TRUE | BA12: =IF(NOT(ISBLANK($C12)),AND(AZ12=TRUE,NOT(COUNTIF('List of Values'!$R$2:$R$400,AY12)=0)),"") -> TRUE | BC12: =IF(NOT(ISBLANK($C12)),TRUE,"") -> TRUE | BD12: {=IF(NOT(ISBLANK($C12)),OR(ISBLANK(BB12),AND(NOT(ISNUMBER(FIND('List of Values'!$C$2:$C$23,BB12))),ISNUMBER(DATEVALUE(BB12)))),"")} -> TRUE | BF12: =IF(NOT(ISBLANK($C12)),TRUE,"") -> TRUE | BG12: {=IF(NOT(ISBLANK($C12)),OR(ISBLANK(BE12),AND(NOT(ISNUMBER(FIND('List of Values'!$C$2:$C$23,BE12))),ISNUMBER(DATEVALUE(BE12)))),"")} -> TRUE | BI12: =IF(NOT(ISBLANK($C12)),TRUE,"") -> TRUE | BJ12: =IF(NOT(ISBLANK($C12)),OR(ISBLANK(BH12),AND(LEN(BH12)<14,ISNUMBER(BH12))),"") -> TRUE | BK12: Invoice | BL12: =IF(NOT(ISBLANK($C12)),IF(NOT(ISBLANK(BK12)),TRUE,FALSE),"") -> TRUE | BM12: =IF(NOT(ISBLANK($C12)),AND(BL12=TRUE,NOT(COUNTIF('List of Values'!$A$2:$A$20,BK12)=0)),"") -> TRUE | BN12: Active | BO12: =IF(NOT(ISBLANK($C12)),IF(NOT(ISBLANK(BN12)),TRUE,FALSE),"") -> TRUE | BP12: =IF(NOT(ISBLANK($C12)),OR(BN12="active",BN12="delisted"),"") -> TRUE | BR12: =IF(NOT(ISBLANK($C12)),OR(AND($E12="intercompany",NOT(ISBLANK(BQ12))),AND(NOT($E12="intercompany"),ISBLANK(BQ12))),"") -> TRUE | BS12: =IF(NOT(ISBLANK($C12)),OR(ISBLANK(BQ12),NOT(COUNTIF('List of Values'!$K$2:$K$30,BQ12)=0)),"") -> TRUE | BU12: =IF(NOT(ISBLANK($C12)),TRUE,"") -> TRUE | BV12: =IF(NOT(ISBLANK($C12)),OR(ISBLANK(BT12),BT12="duty paid",BT12="bond"),"") -> TRUE | BX12: =IF(NOT(ISBLANK($C12)),TRUE,"") -> TRUE | BY12: =IF(NOT(ISBLANK($C12)),OR(ISBLANK(BW12),BW12="duty paid",BW12="bond"),"") -> TRUE | BZ12: =_xlfn.XLOOKUP(C12,[1]Blad1!$A:$A,[1]Blad1!$D:$D,"")
B13: =COUNTIF(C13:XFD13,"FALSE") -> 0 | C13: 218053 | D13: FIRESAFE SVERIGE AB | E13: Indirect | F13: 5562629260 | G13: =IF(NOT(ISBLANK($C13)),IF(NOT(ISBLANK(F13)),TRUE,FALSE),"") -> TRUE | H13: {=IF(NOT(ISBLANK($C13)),AND(G13=TRUE,LEN(F13)<30,NOT(ISNUMBER(FIND('List of Values'!$C$2:$C$20,F13)))),"")} -> TRUE | I13: SE556262926001 | J13: =IF(NOT(ISBLANK($C13)),TRUE,"") -> TRUE | K13: {=IF(NOT(ISBLANK($C13)),AND(J13=TRUE,LEN(I13)<20,NOT(ISNUMBER(FIND('List of Values'!$C$2:$C$20,I13)))),"")} -> TRUE | L13: BOX 32050 | M13: =IF(NOT(ISBLANK($C13)),IF(NOT(ISBLANK(L13)),TRUE,FALSE),"") -> TRUE | N13: {=IF(NOT(ISBLANK($C13)),AND(M13=TRUE,LEN(L13)<81,NOT(ISNUMBER(FIND('List of Values'!$C$2:$C$20,L13)))),"")} -> TRUE | P13: =IF(NOT(ISBLANK($C13)),TRUE,"") -> TRUE | Q13: {=IF(NOT(ISBLANK($C13)),AND(P13=TRUE,LEN(O13)<81,NOT(ISNUMBER(FIND('List of Values'!$C$2:$C$20,O13)))),"")} -> TRUE | R13: STOCKHOLM | S13: =IF(NOT(ISBLANK($C13)),IF(NOT(ISBLANK(R13)),TRUE,FALSE),"") -> TRUE | T13: {=IF(NOT(ISBLANK($C13)),AND(S13=TRUE,LEN(R13)<61,NOT(ISNUMBER(FIND('List of Values'!$C$2:$C$23,R13)))),"")} -> TRUE | V13: =IF(NOT(ISBLANK($C13)),TRUE,"") -> TRUE | W13: {=IF(NOT(ISBLANK($C13)),AND(V13=TRUE,LEN(U13)<61,NOT(ISNUMBER(FIND('List of Values'!$C$2:$C$23,U13)))),"")} -> TRUE | X13: 126 11 | Y13: =IF(NOT(ISBLANK($C13)),IF(NOT(ISBLANK(X13)),TRUE,FALSE),"") -> TRUE | Z13: {=IF(NOT(ISBLANK($C13)),AND(Y13=TRUE,LEN(X13)<81,NOT(ISNUMBER(FIND('List of Values'!$C$2:$C$23,X13)))),"")} -> TRUE | AA13: SE | AB13: =IF(NOT(ISBLANK($C13)),IF(NOT(ISBLANK(AA13)),TRUE,FALSE),"") -> TRUE | AC13: =IF(NOT(ISBLANK($C13)),AND(AB13=TRUE,NOT(COUNTIF('List of Values'!$B$2:$B$255,AA13)=0)),"") -> TRUE | AD13: SEK | AE13: =IF(NOT(ISBLANK($C13)),IF(NOT(ISBLANK(AD13)),TRUE,FALSE),"") -> TRUE | AF13: =IF(NOT(ISBLANK($C13)),AND(AE13=TRUE,NOT(COUNTIF('List of Values'!$F$2:$F$255,AD13)=0)),"") -> TRUE | AG13: V_20NET | AH13: =IF(NOT(ISBLANK($C13)),IF(NOT(ISBLANK(AG13)),TRUE,FALSE),"") -> TRUE | AI13: =IF(NOT(ISBLANK($C13)),AND(AH13=TRUE,NOT(COUNTIF('List of Values'!$N$2:$N$40,AG13)=0)),"") -> TRUE | AJ13: V_BANK | AK13: =IF(NOT(ISBLANK($C13)),IF(NOT(ISBLANK(AJ13)),TRUE,FALSE),"") -> TRUE | AL13: =IF(NOT(ISBLANK($C13)),AND(AK13=TRUE,NOT(COUNTIF('List of Values'!$O$2:$O$30,AJ13)=0)),"") -> TRUE | AM13: S-DOM | AN13: =IF(NOT(ISBLANK($C13)),IF(NOT(ISBLANK(AM13)),TRUE,FALSE),"") -> TRUE | AO13: =IF(NOT(ISBLANK($C13)),AND(AN13=TRUE,NOT(COUNTIF('List of Values'!$AF$2:$AF$20,AM13)=0)),"") -> TRUE | AQ13: =IF(NOT(ISBLANK($C13)),TRUE,"") -> TRUE | AR13: {=IF(NOT(ISBLANK($C13)),AND(AQ13=TRUE,LEN(AP13)<81,NOT(ISNUMBER(FIND('List of Values'!$C$2:$C$20,AP13)))),"")} -> TRUE | AS13: =D13 -> FIRESAFE SVERIGE AB | AT13: =IF(NOT(ISBLANK($C13)),IF(NOT(ISBLANK(AS13)),TRUE,FALSE),"") -> TRUE | AU13: {=IF(NOT(ISBLANK($C13)),AND(AT13=TRUE,LEN(AS13)<81,NOT(ISNUMBER(FIND('List of Values'!$C$2:$C$20,AS13)))),"")} -> TRUE | AV13: KIDDESWEDEN | AW13: =IF(NOT(ISBLANK($C13)),IF(NOT(ISBLANK(AV13)),TRUE,FALSE),"") -> TRUE | AX13: {=IF(NOT(ISBLANK($C13)),AND(AW13=TRUE,LEN(AV13)<21,NOT(ISNUMBER(FIND('List of Values'!$C$2:$C$20,AV13)))),"")} -> TRUE | AY13: 10001 | AZ13: =IF(NOT(ISBLANK($C13)),TRUE,"") -> TRUE | BA13: =IF(NOT(ISBLANK($C13)),AND(AZ13=TRUE,NOT(COUNTIF('List of Values'!$R$2:$R$400,AY13)=0)),"") -> TRUE | BC13: =IF(NOT(ISBLANK($C13)),TRUE,"") -> TRUE | BD13: {=IF(NOT(ISBLANK($C13)),OR(ISBLANK(BB13),AND(NOT(ISNUMBER(FIND('List of Values'!$C$2:$C$23,BB13))),ISNUMBER(DATEVALUE(BB13)))),"")} -> TRUE | BF13: =IF(NOT(ISBLANK($C13)),TRUE,"") -> TRUE | BG13: {=IF(NOT(ISBLANK($C13)),OR(ISBLANK(BE13),AND(NOT(ISNUMBER(FIND('List of Values'!$C$2:$C$23,BE13))),ISNUMBER(DATEVALUE(BE13)))),"")} -> TRUE | BI13: =IF(NOT(ISBLANK($C13)),TRUE,"") -> TRUE | BJ13: =IF(NOT(ISBLANK($C13)),OR(ISBLANK(BH13),AND(LEN(BH13)<14,ISNUMBER(BH13))),"") -> TRUE | BK13: Invoice | BL13: =IF(NOT(ISBLANK($C13)),IF(NOT(ISBLANK(BK13)),TRUE,FALSE),"") -> TRUE | BM13: =IF(NOT(ISBLANK($C13)),AND(BL13=TRUE,NOT(COUNTIF('List of Values'!$A$2:$A$20,BK13)=0)),"") -> TRUE | BN13: Active | BO13: =IF(NOT(ISBLANK($C13)),IF(NOT(ISBLANK(BN13)),TRUE,FALSE),"") -> TRUE | BP13: =IF(NOT(ISBLANK($C13)),OR(BN13="active",BN13="delisted"),"") -> TRUE | BR13: =IF(NOT(ISBLANK($C13)),OR(AND($E13="intercompany",NOT(ISBLANK(BQ13))),AND(NOT($E13="intercompany"),ISBLANK(BQ13))),"") -> TRUE | BS13: =IF(NOT(ISBLANK($C13)),OR(ISBLANK(BQ13),NOT(COUNTIF('List of Values'!$K$2:$K$30,BQ13)=0)),"") -> TRUE | BU13: =IF(NOT(ISBLANK($C13)),TRUE,"") -> TRUE | BV13: =IF(NOT(ISBLANK($C13)),OR(ISBLANK(BT13),BT13="duty paid",BT13="bond"),"") -> TRUE | BX13: =IF(NOT(ISBLANK($C13)),TRUE,"") -> TRUE | BY13: =IF(NOT(ISBLANK($C13)),OR(ISBLANK(BW13),BW13="duty paid",BW13="bond"),"") -> TRUE | BZ13: =_xlfn.XLOOKUP(C13,[1]Blad1!$A:$A,[1]Blad1!$D:$D,"")
B14: =COUNTIF(C14:XFD14,"FALSE") -> 0 | C14: 217966 | D14: HOKKAI SUISAN SWEDEN AB | E14: Trade | F14: 5567159867 | G14: =IF(NOT(ISBLANK($C14)),IF(NOT(ISBLANK(F14)),TRUE,FALSE),"") -> TRUE | H14: {=IF(NOT(ISBLANK($C14)),AND(G14=TRUE,LEN(F14)<30,NOT(ISNUMBER(FIND('List of Values'!$C$2:$C$20,F14)))),"")} -> TRUE | I14: SE556715986701 | J14: =IF(NOT(ISBLANK($C14)),TRUE,"") -> TRUE | K14: {=IF(NOT(ISBLANK($C14)),AND(J14=TRUE,LEN(I14)<20,NOT(ISNUMBER(FIND('List of Values'!$C$2:$C$20,I14)))),"")} -> TRUE | L14: FISKHALLSVÄGEN 16 | M14: =IF(NOT(ISBLANK($C14)),IF(NOT(ISBLANK(L14)),TRUE,FALSE),"") -> TRUE | N14: {=IF(NOT(ISBLANK($C14)),AND(M14=TRUE,LEN(L14)<81,NOT(ISNUMBER(FIND('List of Values'!$C$2:$C$20,L14)))),"")} -> TRUE | P14: =IF(NOT(ISBLANK($C14)),TRUE,"") -> TRUE | Q14: {=IF(NOT(ISBLANK($C14)),AND(P14=TRUE,LEN(O14)<81,NOT(ISNUMBER(FIND('List of Values'!$C$2:$C$20,O14)))),"")} -> TRUE | R14: ÅRSTA | S14: =IF(NOT(ISBLANK($C14)),IF(NOT(ISBLANK(R14)),TRUE,FALSE),"") -> TRUE | T14: {=IF(NOT(ISBLANK($C14)),AND(S14=TRUE,LEN(R14)<61,NOT(ISNUMBER(FIND('List of Values'!$C$2:$C$23,R14)))),"")} -> TRUE | V14: =IF(NOT(ISBLANK($C14)),TRUE,"") -> TRUE | W14: {=IF(NOT(ISBLANK($C14)),AND(V14=TRUE,LEN(U14)<61,NOT(ISNUMBER(FIND('List of Values'!$C$2:$C$23,U14)))),"")} -> TRUE | X14: 120 44 | Y14: =IF(NOT(ISBLANK($C14)),IF(NOT(ISBLANK(X14)),TRUE,FALSE),"") -> TRUE | Z14: {=IF(NOT(ISBLANK($C14)),AND(Y14=TRUE,LEN(X14)<81,NOT(ISNUMBER(FIND('List of Values'!$C$2:$C$23,X14)))),"")} -> TRUE | AA14: SE | AB14: =IF(NOT(ISBLANK($C14)),IF(NOT(ISBLANK(AA14)),TRUE,FALSE),"") -> TRUE | AC14: =IF(NOT(ISBLANK($C14)),AND(AB14=TRUE,NOT(COUNTIF('List of Values'!$B$2:$B$255,AA14)=0)),"") -> TRUE | AD14: SEK | AE14: =IF(NOT(ISBLANK($C14)),IF(NOT(ISBLANK(AD14)),TRUE,FALSE),"") -> TRUE | AF14: =IF(NOT(ISBLANK($C14)),AND(AE14=TRUE,NOT(COUNTIF('List of Values'!$F$2:$F$255,AD14)=0)),"") -> TRUE | AG14: V_10EOM | AH14: =IF(NOT(ISBLANK($C14)),IF(NOT(ISBLANK(AG14)),TRUE,FALSE),"") -> TRUE | AI14: =IF(NOT(ISBLANK($C14)),AND(AH14=TRUE,NOT(COUNTIF('List of Values'!$N$2:$N$40,AG14)=0)),"") -> TRUE | AJ14: V_BANK | AK14: =IF(NOT(ISBLANK($C14)),IF(NOT(ISBLANK(AJ14)),TRUE,FALSE),"") -> TRUE | AL14: =IF(NOT(ISBLANK($C14)),AND(AK14=TRUE,NOT(COUNTIF('List of Values'!$O$2:$O$30,AJ14)=0)),"") -> TRUE | AM14: S-DOM | AN14: =IF(NOT(ISBLANK($C14)),IF(NOT(ISBLANK(AM14)),TRUE,FALSE),"") -> TRUE | AO14: =IF(NOT(ISBLANK($C14)),AND(AN14=TRUE,NOT(COUNTIF('List of Values'!$AF$2:$AF$20,AM14)=0)),"") -> TRUE | AQ14: =IF(NOT(ISBLANK($C14)),TRUE,"") -> TRUE | AR14: {=IF(NOT(ISBLANK($C14)),AND(AQ14=TRUE,LEN(AP14)<81,NOT(ISNUMBER(FIND('List of Values'!$C$2:$C$20,AP14)))),"")} -> TRUE | AS14: =D14 -> HOKKAI SUISAN SWEDEN AB | AT14: =IF(NOT(ISBLANK($C14)),IF(NOT(ISBLANK(AS14)),TRUE,FALSE),"") -> TRUE | AU14: {=IF(NOT(ISBLANK($C14)),AND(AT14=TRUE,LEN(AS14)<81,NOT(ISNUMBER(FIND('List of Values'!$C$2:$C$20,AS14)))),"")} -> TRUE | AV14: HOKKAISUISANSWEDENAB | AW14: =IF(NOT(ISBLANK($C14)),IF(NOT(ISBLANK(AV14)),TRUE,FALSE),"") -> TRUE | AX14: {=IF(NOT(ISBLANK($C14)),AND(AW14=TRUE,LEN(AV14)<21,NOT(ISNUMBER(FIND('List of Values'!$C$2:$C$20,AV14)))),"")} -> TRUE | AY14: 12492 | AZ14: =IF(NOT(ISBLANK($C14)),TRUE,"") -> TRUE | BA14: =IF(NOT(ISBLANK($C14)),AND(AZ14=TRUE,NOT(COUNTIF('List of Values'!$R$2:$R$400,AY14)=0)),"") -> TRUE | BC14: =IF(NOT(ISBLANK($C14)),TRUE,"") -> TRUE | BD14: {=IF(NOT(ISBLANK($C14)),OR(ISBLANK(BB14),AND(NOT(ISNUMBER(FIND('List of Values'!$C$2:$C$23,BB14))),ISNUMBER(DATEVALUE(BB14)))),"")} -> TRUE | BF14: =IF(NOT(ISBLANK($C14)),TRUE,"") -> TRUE | BG14: {=IF(NOT(ISBLANK($C14)),OR(ISBLANK(BE14),AND(NOT(ISNUMBER(FIND('List of Values'!$C$2:$C$23,BE14))),ISNUMBER(DATEVALUE(BE14)))),"")} -> TRUE | BI14: =IF(NOT(ISBLANK($C14)),TRUE,"") -> TRUE | BJ14: =IF(NOT(ISBLANK($C14)),OR(ISBLANK(BH14),AND(LEN(BH14)<14,ISNUMBER(BH14))),"") -> TRUE | BK14: Invoice | BL14: =IF(NOT(ISBLANK($C14)),IF(NOT(ISBLANK(BK14)),TRUE,FALSE),"") -> TRUE | BM14: =IF(NOT(ISBLANK($C14)),AND(BL14=TRUE,NOT(COUNTIF('List of Values'!$A$2:$A$20,BK14)=0)),"") -> TRUE | BN14: Active | BO14: =IF(NOT(ISBLANK($C14)),IF(NOT(ISBLANK(BN14)),TRUE,FALSE),"") -> TRUE | BP14: =IF(NOT(ISBLANK($C14)),OR(BN14="active",BN14="delisted"),"") -> TRUE | BR14: =IF(NOT(ISBLANK($C14)),OR(AND($E14="intercompany",NOT(ISBLANK(BQ14))),AND(NOT($E14="intercompany"),ISBLANK(BQ14))),"") -> TRUE | BS14: =IF(NOT(ISBLANK($C14)),OR(ISBLANK(BQ14),NOT(COUNTIF('List of Values'!$K$2:$K$30,BQ14)=0)),"") -> TRUE | BU14: =IF(NOT(ISBLANK($C14)),TRUE,"") -> TRUE | BV14: =IF(NOT(ISBLANK($C14)),OR(ISBLANK(BT14),BT14="duty paid",BT14="bond"),"") -> TRUE | BX14: =IF(NOT(ISBLANK($C14)),TRUE,"") -> TRUE | BY14: =IF(NOT(ISBLANK($C14)),OR(ISBLANK(BW14),BW14="duty paid",BW14="bond"),"") -> TRUE | BZ14: =_xlfn.XLOOKUP(C14,[1]Blad1!$A:$A,[1]Blad1!$D:$D,"")
B15: =COUNTIF(C15:XFD15,"FALSE") -> 0 | C15: 217988 | D15: JUST SEAFOOD DK | E15: Trade | F15: DK42785342 | G15: =IF(NOT(ISBLANK($C15)),IF(NOT(ISBLANK(F15)),TRUE,FALSE),"") -> TRUE | H15: {=IF(NOT(ISBLANK($C15)),AND(G15=TRUE,LEN(F15)<30,NOT(ISNUMBER(FIND('List of Values'!$C$2:$C$20,F15)))),"")} -> TRUE | I15: DK42785342 | J15: =IF(NOT(ISBLANK($C15)),TRUE,"") -> TRUE | K15: {=IF(NOT(ISBLANK($C15)),AND(J15=TRUE,LEN(I15)<20,NOT(ISNUMBER(FIND('List of Values'!$C$2:$C$20,I15)))),"")} -> TRUE | L15: KAI LINDBERGS GADE 41 | M15: =IF(NOT(ISBLANK($C15)),IF(NOT(ISBLANK(L15)),TRUE,FALSE),"") -> TRUE | N15: {=IF(NOT(ISBLANK($C15)),AND(M15=TRUE,LEN(L15)<81,NOT(ISNUMBER(FIND('List of Values'!$C$2:$C$20,L15)))),"")} -> TRUE | P15: =IF(NOT(ISBLANK($C15)),TRUE,"") -> TRUE | Q15: {=IF(NOT(ISBLANK($C15)),AND(P15=TRUE,LEN(O15)<81,NOT(ISNUMBER(FIND('List of Values'!$C$2:$C$20,O15)))),"")} -> TRUE | R15: HANSTHOLM | S15: =IF(NOT(ISBLANK($C15)),IF(NOT(ISBLANK(R15)),TRUE,FALSE),"") -> TRUE | T15: {=IF(NOT(ISBLANK($C15)),AND(S15=TRUE,LEN(R15)<61,NOT(ISNUMBER(FIND('List of Values'!$C$2:$C$23,R15)))),"")} -> TRUE | V15: =IF(NOT(ISBLANK($C15)),TRUE,"") -> TRUE | W15: {=IF(NOT(ISBLANK($C15)),AND(V15=TRUE,LEN(U15)<61,NOT(ISNUMBER(FIND('List of Values'!$C$2:$C$23,U15)))),"")} -> TRUE | X15: DK-7730 | Y15: =IF(NOT(ISBLANK($C15)),IF(NOT(ISBLANK(X15)),TRUE,FALSE),"") -> TRUE | Z15: {=IF(NOT(ISBLANK($C15)),AND(Y15=TRUE,LEN(X15)<81,NOT(ISNUMBER(FIND('List of Values'!$C$2:$C$23,X15)))),"")} -> TRUE | AA15: DK | AB15: =IF(NOT(ISBLANK($C15)),IF(NOT(ISBLANK(AA15)),TRUE,FALSE),"") -> TRUE | AC15: =IF(NOT(ISBLANK($C15)),AND(AB15=TRUE,NOT(COUNTIF('List of Values'!$B$2:$B$255,AA15)=0)),"") -> TRUE | AD15: SEK | AE15: =IF(NOT(ISBLANK($C15)),IF(NOT(ISBLANK(AD15)),TRUE,FALSE),"") -> TRUE | AF15: =IF(NOT(ISBLANK($C15)),AND(AE15=TRUE,NOT(COUNTIF('List of Values'!$F$2:$F$255,AD15)=0)),"") -> TRUE | AG15: V_10EOM | AH15: =IF(NOT(ISBLANK($C15)),IF(NOT(ISBLANK(AG15)),TRUE,FALSE),"") -> TRUE | AI15: =IF(NOT(ISBLANK($C15)),AND(AH15=TRUE,NOT(COUNTIF('List of Values'!$N$2:$N$40,AG15)=0)),"") -> TRUE | AJ15: V_BANK | AK15: =IF(NOT(ISBLANK($C15)),IF(NOT(ISBLANK(AJ15)),TRUE,FALSE),"") -> TRUE | AL15: =IF(NOT(ISBLANK($C15)),AND(AK15=TRUE,NOT(COUNTIF('List of Values'!$O$2:$O$30,AJ15)=0)),"") -> TRUE | AM15: S-EU | AN15: =IF(NOT(ISBLANK($C15)),IF(NOT(ISBLANK(AM15)),TRUE,FALSE),"") -> TRUE | AO15: =IF(NOT(ISBLANK($C15)),AND(AN15=TRUE,NOT(COUNTIF('List of Values'!$AF$2:$AF$20,AM15)=0)),"") -> TRUE | AQ15: =IF(NOT(ISBLANK($C15)),TRUE,"") -> TRUE | AR15: {=IF(NOT(ISBLANK($C15)),AND(AQ15=TRUE,LEN(AP15)<81,NOT(ISNUMBER(FIND('List of Values'!$C$2:$C$20,AP15)))),"")} -> TRUE | AS15: =D15 -> JUST SEAFOOD DK | AT15: =IF(NOT(ISBLANK($C15)),IF(NOT(ISBLANK(AS15)),TRUE,FALSE),"") -> TRUE | AU15: {=IF(NOT(ISBLANK($C15)),AND(AT15=TRUE,LEN(AS15)<81,NOT(ISNUMBER(FIND('List of Values'!$C$2:$C$20,AS15)))),"")} -> TRUE | AV15: JUSTSEAFOODDK | AW15: =IF(NOT(ISBLANK($C15)),IF(NOT(ISBLANK(AV15)),TRUE,FALSE),"") -> TRUE | AX15: {=IF(NOT(ISBLANK($C15)),AND(AW15=TRUE,LEN(AV15)<21,NOT(ISNUMBER(FIND('List of Values'!$C$2:$C$20,AV15)))),"")} -> TRUE | AY15: 12783 | AZ15: =IF(NOT(ISBLANK($C15)),TRUE,"") -> TRUE | BA15: =IF(NOT(ISBLANK($C15)),AND(AZ15=TRUE,NOT(COUNTIF('List of Values'!$R$2:$R$400,AY15)=0)),"") -> TRUE | BC15: =IF(NOT(ISBLANK($C15)),TRUE,"") -> TRUE | BD15: {=IF(NOT(ISBLANK($C15)),OR(ISBLANK(BB15),AND(NOT(ISNUMBER(FIND('List of Values'!$C$2:$C$23,BB15))),ISNUMBER(DATEVALUE(BB15)))),"")} -> TRUE | BF15: =IF(NOT(ISBLANK($C15)),TRUE,"") -> TRUE | BG15: {=IF(NOT(ISBLANK($C15)),OR(ISBLANK(BE15),AND(NOT(ISNUMBER(FIND('List of Values'!$C$2:$C$23,BE15))),ISNUMBER(DATEVALUE(BE15)))),"")} -> TRUE | BI15: =IF(NOT(ISBLANK($C15)),TRUE,"") -> TRUE | BJ15: =IF(NOT(ISBLANK($C15)),OR(ISBLANK(BH15),AND(LEN(BH15)<14,ISNUMBER(BH15))),"") -> TRUE | BK15: Invoice | BL15: =IF(NOT(ISBLANK($C15)),IF(NOT(ISBLANK(BK15)),TRUE,FALSE),"") -> TRUE | BM15: =IF(NOT(ISBLANK($C15)),AND(BL15=TRUE,NOT(COUNTIF('List of Values'!$A$2:$A$20,BK15)=0)),"") -> TRUE | BN15: Active | BO15: =IF(NOT(ISBLANK($C15)),IF(NOT(ISBLANK(BN15)),TRUE,FALSE),"") -> TRUE | BP15: =IF(NOT(ISBLANK($C15)),OR(BN15="active",BN15="delisted"),"") -> TRUE | BR15: =IF(NOT(ISBLANK($C15)),OR(AND($E15="intercompany",NOT(ISBLANK(BQ15))),AND(NOT($E15="intercompany"),ISBLANK(BQ15))),"") -> TRUE | BS15: =IF(NOT(ISBLANK($C15)),OR(ISBLANK(BQ15),NOT(COUNTIF('List of Values'!$K$2:$K$30,BQ15)=0)),"") -> TRUE | BU15: =IF(NOT(ISBLANK($C15)),TRUE,"") -> TRUE | BV15: =IF(NOT(ISBLANK($C15)),OR(ISBLANK(BT15),BT15="duty paid",BT15="bond"),"") -> TRUE | BX15: =IF(NOT(ISBLANK($C15)),TRUE,"") -> TRUE | BY15: =IF(NOT(ISBLANK($C15)),OR(ISBLANK(BW15),BW15="duty paid",BW15="bond"),"") -> TRUE | BZ15: =_xlfn.XLOOKUP(C15,[1]Blad1!$A:$A,[1]Blad1!$D:$D,"")
B16: =COUNTIF(C16:XFD16,"FALSE") -> 0 | C16: 218002 | D16: MAREA ALTRA BV | E16: Trade | F16: NL805410491B01 | G16: =IF(NOT(ISBLANK($C16)),IF(NOT(ISBLANK(F16)),TRUE,FALSE),"") -> TRUE | H16: {=IF(NOT(ISBLANK($C16)),AND(G16=TRUE,LEN(F16)<30,NOT(ISNUMBER(FIND('List of Values'!$C$2:$C$20,F16)))),"")} -> TRUE | I16: NL805410491B01 | J16: =IF(NOT(ISBLANK($C16)),TRUE,"") -> TRUE | K16: {=IF(NOT(ISBLANK($C16)),AND(J16=TRUE,LEN(I16)<20,NOT(ISNUMBER(FIND('List of Values'!$C$2:$C$20,I16)))),"")} -> TRUE | L16: BOX 12 | M16: =IF(NOT(ISBLANK($C16)),IF(NOT(ISBLANK(L16)),TRUE,FALSE),"") -> TRUE | N16: {=IF(NOT(ISBLANK($C16)),AND(M16=TRUE,LEN(L16)<81,NOT(ISNUMBER(FIND('List of Values'!$C$2:$C$20,L16)))),"")} -> TRUE | P16: =IF(NOT(ISBLANK($C16)),TRUE,"") -> TRUE | Q16: {=IF(NOT(ISBLANK($C16)),AND(P16=TRUE,LEN(O16)<81,NOT(ISNUMBER(FIND('List of Values'!$C$2:$C$20,O16)))),"")} -> TRUE | R16: URK | S16: =IF(NOT(ISBLANK($C16)),IF(NOT(ISBLANK(R16)),TRUE,FALSE),"") -> TRUE | T16: {=IF(NOT(ISBLANK($C16)),AND(S16=TRUE,LEN(R16)<61,NOT(ISNUMBER(FIND('List of Values'!$C$2:$C$23,R16)))),"")} -> TRUE | V16: =IF(NOT(ISBLANK($C16)),TRUE,"") -> TRUE | W16: {=IF(NOT(ISBLANK($C16)),AND(V16=TRUE,LEN(U16)<61,NOT(ISNUMBER(FIND('List of Values'!$C$2:$C$23,U16)))),"")} -> TRUE | X16: NL-8320 AA | Y16: =IF(NOT(ISBLANK($C16)),IF(NOT(ISBLANK(X16)),TRUE,FALSE),"") -> TRUE | Z16: {=IF(NOT(ISBLANK($C16)),AND(Y16=TRUE,LEN(X16)<81,NOT(ISNUMBER(FIND('List of Values'!$C$2:$C$23,X16)))),"")} -> TRUE | AA16: NL | AB16: =IF(NOT(ISBLANK($C16)),IF(NOT(ISBLANK(AA16)),TRUE,FALSE),"") -> TRUE | AC16: =IF(NOT(ISBLANK($C16)),AND(AB16=TRUE,NOT(COUNTIF('List of Values'!$B$2:$B$255,AA16)=0)),"") -> TRUE | AD16: EUR | AE16: =IF(NOT(ISBLANK($C16)),IF(NOT(ISBLANK(AD16)),TRUE,FALSE),"") -> TRUE | AF16: =IF(NOT(ISBLANK($C16)),AND(AE16=TRUE,NOT(COUNTIF('List of Values'!$F$2:$F$255,AD16)=0)),"") -> TRUE | AG16: V_30NET | AH16: =IF(NOT(ISBLANK($C16)),IF(NOT(ISBLANK(AG16)),TRUE,FALSE),"") -> TRUE | AI16: =IF(NOT(ISBLANK($C16)),AND(AH16=TRUE,NOT(COUNTIF('List of Values'!$N$2:$N$40,AG16)=0)),"") -> TRUE | AJ16: V_BANK | AK16: =IF(NOT(ISBLANK($C16)),IF(NOT(ISBLANK(AJ16)),TRUE,FALSE),"") -> TRUE | AL16: =IF(NOT(ISBLANK($C16)),AND(AK16=TRUE,NOT(COUNTIF('List of Values'!$O$2:$O$30,AJ16)=0)),"") -> TRUE | AM16: S-EU | AN16: =IF(NOT(ISBLANK($C16)),IF(NOT(ISBLANK(AM16)),TRUE,FALSE),"") -> TRUE | AO16: =IF(NOT(ISBLANK($C16)),AND(AN16=TRUE,NOT(COUNTIF('List of Values'!$AF$2:$AF$20,AM16)=0)),"") -> TRUE | AQ16: =IF(NOT(ISBLANK($C16)),TRUE,"") -> TRUE | AR16: {=IF(NOT(ISBLANK($C16)),AND(AQ16=TRUE,LEN(AP16)<81,NOT(ISNUMBER(FIND('List of Values'!$C$2:$C$20,AP16)))),"")} -> TRUE | AS16: =D16 -> MAREA ALTRA BV | AT16: =IF(NOT(ISBLANK($C16)),IF(NOT(ISBLANK(AS16)),TRUE,FALSE),"") -> TRUE | AU16: {=IF(NOT(ISBLANK($C16)),AND(AT16=TRUE,LEN(AS16)<81,NOT(ISNUMBER(FIND('List of Values'!$C$2:$C$20,AS16)))),"")} -> TRUE | AV16: MAREAALTRA | AW16: =IF(NOT(ISBLANK($C16)),IF(NOT(ISBLANK(AV16)),TRUE,FALSE),"") -> TRUE | AX16: {=IF(NOT(ISBLANK($C16)),AND(AW16=TRUE,LEN(AV16)<21,NOT(ISNUMBER(FIND('List of Values'!$C$2:$C$20,AV16)))),"")} -> TRUE | AY16: 13292 | AZ16: =IF(NOT(ISBLANK($C16)),TRUE,"") -> TRUE | BA16: =IF(NOT(ISBLANK($C16)),AND(AZ16=TRUE,NOT(COUNTIF('List of Values'!$R$2:$R$400,AY16)=0)),"") -> TRUE | BC16: =IF(NOT(ISBLANK($C16)),TRUE,"") -> TRUE | BD16: {=IF(NOT(ISBLANK($C16)),OR(ISBLANK(BB16),AND(NOT(ISNUMBER(FIND('List of Values'!$C$2:$C$23,BB16))),ISNUMBER(DATEVALUE(BB16)))),"")} -> TRUE | BF16: =IF(NOT(ISBLANK($C16)),TRUE,"") -> TRUE | BG16: {=IF(NOT(ISBLANK($C16)),OR(ISBLANK(BE16),AND(NOT(ISNUMBER(FIND('List of Values'!$C$2:$C$23,BE16))),ISNUMBER(DATEVALUE(BE16)))),"")} -> TRUE | BI16: =IF(NOT(ISBLANK($C16)),TRUE,"") -> TRUE | BJ16: =IF(NOT(ISBLANK($C16)),OR(ISBLANK(BH16),AND(LEN(BH16)<14,ISNUMBER(BH16))),"") -> TRUE | BK16: Invoice | BL16: =IF(NOT(ISBLANK($C16)),IF(NOT(ISBLANK(BK16)),TRUE,FALSE),"") -> TRUE | BM16: =IF(NOT(ISBLANK($C16)),AND(BL16=TRUE,NOT(COUNTIF('List of Values'!$A$2:$A$20,BK16)=0)),"") -> TRUE | BN16: Active | BO16: =IF(NOT(ISBLANK($C16)),IF(NOT(ISBLANK(BN16)),TRUE,FALSE),"") -> TRUE | BP16: =IF(NOT(ISBLANK($C16)),OR(BN16="active",BN16="delisted"),"") -> TRUE | BR16: =IF(NOT(ISBLANK($C16)),OR(AND($E16="intercompany",NOT(ISBLANK(BQ16))),AND(NOT($E16="intercompany"),ISBLANK(BQ16))),"") -> TRUE | BS16: =IF(NOT(ISBLANK($C16)),OR(ISBLANK(BQ16),NOT(COUNTIF('List of Values'!$K$2:$K$30,BQ16)=0)),"") -> TRUE | BU16: =IF(NOT(ISBLANK($C16)),TRUE,"") -> TRUE | BV16: =IF(NOT(ISBLANK($C16)),OR(ISBLANK(BT16),BT16="duty paid",BT16="bond"),"") -> TRUE | BX16: =IF(NOT(ISBLANK($C16)),TRUE,"") -> TRUE | BY16: =IF(NOT(ISBLANK($C16)),OR(ISBLANK(BW16),BW16="duty paid",BW16="bond"),"") -> TRUE | BZ16: =_xlfn.XLOOKUP(C16,[1]Blad1!$A:$A,[1]Blad1!$D:$D,"") -> x
B17: =COUNTIF(C17:XFD17,"FALSE") -> 0 | C17: 218039 | D17: AKTIEBOLAGET SYSTEMSTÖD SVERIGE | E17: Indirect | F17: 5561220798 | G17: =IF(NOT(ISBLANK($C17)),IF(NOT(ISBLANK(F17)),TRUE,FALSE),"") -> TRUE | H17: {=IF(NOT(ISBLANK($C17)),AND(G17=TRUE,LEN(F17)<30,NOT(ISNUMBER(FIND('List of Values'!$C$2:$C$20,F17)))),"")} -> TRUE | I17: SE556122079801 | J17: =IF(NOT(ISBLANK($C17)),TRUE,"") -> TRUE | K17: {=IF(NOT(ISBLANK($C17)),AND(J17=TRUE,LEN(I17)<20,NOT(ISNUMBER(FIND('List of Values'!$C$2:$C$20,I17)))),"")} -> TRUE | L17: TORSHAMNSGATAN 28 A | M17: =IF(NOT(ISBLANK($C17)),IF(NOT(ISBLANK(L17)),TRUE,FALSE),"") -> TRUE | N17: {=IF(NOT(ISBLANK($C17)),AND(M17=TRUE,LEN(L17)<81,NOT(ISNUMBER(FIND('List of Values'!$C$2:$C$20,L17)))),"")} -> TRUE | P17: =IF(NOT(ISBLANK($C17)),TRUE,"") -> TRUE | Q17: {=IF(NOT(ISBLANK($C17)),AND(P17=TRUE,LEN(O17)<81,NOT(ISNUMBER(FIND('List of Values'!$C$2:$C$20,O17)))),"")} -> TRUE | R17: KISTA | S17: =IF(NOT(ISBLANK($C17)),IF(NOT(ISBLANK(R17)),TRUE,FALSE),"") -> TRUE | T17: {=IF(NOT(ISBLANK($C17)),AND(S17=TRUE,LEN(R17)<61,NOT(ISNUMBER(FIND('List of Values'!$C$2:$C$23,R17)))),"")} -> TRUE | V17: =IF(NOT(ISBLANK($C17)),TRUE,"") -> TRUE | W17: {=IF(NOT(ISBLANK($C17)),AND(V17=TRUE,LEN(U17)<61,NOT(ISNUMBER(FIND('List of Values'!$C$2:$C$23,U17)))),"")} -> TRUE | X17: 164 40 | Y17: =IF(NOT(ISBLANK($C17)),IF(NOT(ISBLANK(X17)),TRUE,FALSE),"") -> TRUE | Z17: {=IF(NOT(ISBLANK($C17)),AND(Y17=TRUE,LEN(X17)<81,NOT(ISNUMBER(FIND('List of Values'!$C$2:$C$23,X17)))),"")} -> TRUE | AA17: SE | AB17: =IF(NOT(ISBLANK($C17)),IF(NOT(ISBLANK(AA17)),TRUE,FALSE),"") -> TRUE | AC17: =IF(NOT(ISBLANK($C17)),AND(AB17=TRUE,NOT(COUNTIF('List of Values'!$B$2:$B$255,AA17)=0)),"") -> TRUE | AD17: SEK | AE17: =IF(NOT(ISBLANK($C17)),IF(NOT(ISBLANK(AD17)),TRUE,FALSE),"") -> TRUE | AF17: =IF(NOT(ISBLANK($C17)),AND(AE17=TRUE,NOT(COUNTIF('List of Values'!$F$2:$F$255,AD17)=0)),"") -> TRUE | AG17: V_20NET | AH17: =IF(NOT(ISBLANK($C17)),IF(NOT(ISBLANK(AG17)),TRUE,FALSE),"") -> TRUE | AI17: =IF(NOT(ISBLANK($C17)),AND(AH17=TRUE,NOT(COUNTIF('List of Values'!$N$2:$N$40,AG17)=0)),"") -> TRUE | AJ17: V_BANK | AK17: =IF(NOT(ISBLANK($C17)),IF(NOT(ISBLANK(AJ17)),TRUE,FALSE),"") -> TRUE | AL17: =IF(NOT(ISBLANK($C17)),AND(AK17=TRUE,NOT(COUNTIF('List of Values'!$O$2:$O$30,AJ17)=0)),"") -> TRUE | AM17: S-DOM | AN17: =IF(NOT(ISBLANK($C17)),IF(NOT(ISBLANK(AM17)),TRUE,FALSE),"") -> TRUE | AO17: =IF(NOT(ISBLANK($C17)),AND(AN17=TRUE,NOT(COUNTIF('List of Values'!$AF$2:$AF$20,AM17)=0)),"") -> TRUE | AQ17: =IF(NOT(ISBLANK($C17)),TRUE,"") -> TRUE | AR17: {=IF(NOT(ISBLANK($C17)),AND(AQ17=TRUE,LEN(AP17)<81,NOT(ISNUMBER(FIND('List of Values'!$C$2:$C$20,AP17)))),"")} -> TRUE | AS17: =D17 -> AKTIEBOLAGET SYSTEMSTÖD SVERIGE | AT17: =IF(NOT(ISBLANK($C17)),IF(NOT(ISBLANK(AS17)),TRUE,FALSE),"") -> TRUE | AU17: {=IF(NOT(ISBLANK($C17)),AND(AT17=TRUE,LEN(AS17)<81,NOT(ISNUMBER(FIND('List of Values'!$C$2:$C$20,AS17)))),"")} -> TRUE | AV17: AKTIEBOLAGETSYSTEMST | AW17: =IF(NOT(ISBLANK($C17)),IF(NOT(ISBLANK(AV17)),TRUE,FALSE),"") -> TRUE | AX17: {=IF(NOT(ISBLANK($C17)),AND(AW17=TRUE,LEN(AV17)<21,NOT(ISNUMBER(FIND('List of Values'!$C$2:$C$20,AV17)))),"")} -> TRUE | AY17: 10001 | AZ17: =IF(NOT(ISBLANK($C17)),TRUE,"") -> TRUE | BA17: =IF(NOT(ISBLANK($C17)),AND(AZ17=TRUE,NOT(COUNTIF('List of Values'!$R$2:$R$400,AY17)=0)),"") -> TRUE | BC17: =IF(NOT(ISBLANK($C17)),TRUE,"") -> TRUE | BD17: {=IF(NOT(ISBLANK($C17)),OR(ISBLANK(BB17),AND(NOT(ISNUMBER(FIND('List of Values'!$C$2:$C$23,BB17))),ISNUMBER(DATEVALUE(BB17)))),"")} -> TRUE | BF17: =IF(NOT(ISBLANK($C17)),TRUE,"") -> TRUE | BG17: {=IF(NOT(ISBLANK($C17)),OR(ISBLANK(BE17),AND(NOT(ISNUMBER(FIND('List of Values'!$C$2:$C$23,BE17))),ISNUMBER(DATEVALUE(BE17)))),"")} -> TRUE | BI17: =IF(NOT(ISBLANK($C17)),TRUE,"") -> TRUE | BJ17: =IF(NOT(ISBLANK($C17)),OR(ISBLANK(BH17),AND(LEN(BH17)<14,ISNUMBER(BH17))),"") -> TRUE | BK17: Invoice | BL17: =IF(NOT(ISBLANK($C17)),IF(NOT(ISBLANK(BK17)),TRUE,FALSE),"") -> TRUE | BM17: =IF(NOT(ISBLANK($C17)),AND(BL17=TRUE,NOT(COUNTIF('List of Values'!$A$2:$A$20,BK17)=0)),"") -> TRUE | BN17: Active | BO17: =IF(NOT(ISBLANK($C17)),IF(NOT(ISBLANK(BN17)),TRUE,FALSE),"") -> TRUE | BP17: =IF(NOT(ISBLANK($C17)),OR(BN17="active",BN17="delisted"),"") -> TRUE | BR17: =IF(NOT(ISBLANK($C17)),OR(AND($E17="intercompany",NOT(ISBLANK(BQ17))),AND(NOT($E17="intercompany"),ISBLANK(BQ17))),"") -> TRUE | BS17: =IF(NOT(ISBLANK($C17)),OR(ISBLANK(BQ17),NOT(COUNTIF('List of Values'!$K$2:$K$30,BQ17)=0)),"") -> TRUE | BU17: =IF(NOT(ISBLANK($C17)),TRUE,"") -> TRUE | BV17: =IF(NOT(ISBLANK($C17)),OR(ISBLANK(BT17),BT17="duty paid",BT17="bond"),"") -> TRUE | BX17: =IF(NOT(ISBLANK($C17)),TRUE,"") -> TRUE | BY17: =IF(NOT(ISBLANK($C17)),OR(ISBLANK(BW17),BW17="duty paid",BW17="bond"),"") -> TRUE | BZ17: =_xlfn.XLOOKUP(C17,[1]Blad1!$A:$A,[1]Blad1!$D:$D,"")
B18: =COUNTIF(C18:XFD18,"FALSE") -> 0 | C18: 218287 | D18: GULDHAVEN PELAGISKA AB | E18: Trade | F18: 5567041560 | G18: =IF(NOT(ISBLANK($C18)),IF(NOT(ISBLANK(F18)),TRUE,FALSE),"") -> TRUE | H18: {=IF(NOT(ISBLANK($C18)),AND(G18=TRUE,LEN(F18)<30,NOT(ISNUMBER(FIND('List of Values'!$C$2:$C$20,F18)))),"")} -> TRUE | I18: SE556704156001 | J18: =IF(NOT(ISBLANK($C18)),TRUE,"") -> TRUE | K18: {=IF(NOT(ISBLANK($C18)),AND(J18=TRUE,LEN(I18)<20,NOT(ISNUMBER(FIND('List of Values'!$C$2:$C$20,I18)))),"")} -> TRUE | L18: BOX 43 | M18: =IF(NOT(ISBLANK($C18)),IF(NOT(ISBLANK(L18)),TRUE,FALSE),"") -> TRUE | N18: {=IF(NOT(ISBLANK($C18)),AND(M18=TRUE,LEN(L18)<81,NOT(ISNUMBER(FIND('List of Values'!$C$2:$C$20,L18)))),"")} -> TRUE | P18: =IF(NOT(ISBLANK($C18)),TRUE,"") -> TRUE | Q18: {=IF(NOT(ISBLANK($C18)),AND(P18=TRUE,LEN(O18)<81,NOT(ISNUMBER(FIND('List of Values'!$C$2:$C$20,O18)))),"")} -> TRUE | R18: KALIX | S18: =IF(NOT(ISBLANK($C18)),IF(NOT(ISBLANK(R18)),TRUE,FALSE),"") -> TRUE | T18: {=IF(NOT(ISBLANK($C18)),AND(S18=TRUE,LEN(R18)<61,NOT(ISNUMBER(FIND('List of Values'!$C$2:$C$23,R18)))),"")} -> TRUE | V18: =IF(NOT(ISBLANK($C18)),TRUE,"") -> TRUE | W18: {=IF(NOT(ISBLANK($C18)),AND(V18=TRUE,LEN(U18)<61,NOT(ISNUMBER(FIND('List of Values'!$C$2:$C$23,U18)))),"")} -> TRUE | X18: 952 21 | Y18: =IF(NOT(ISBLANK($C18)),IF(NOT(ISBLANK(X18)),TRUE,FALSE),"") -> TRUE | Z18: {=IF(NOT(ISBLANK($C18)),AND(Y18=TRUE,LEN(X18)<81,NOT(ISNUMBER(FIND('List of Values'!$C$2:$C$23,X18)))),"")} -> TRUE | AA18: SE | AB18: =IF(NOT(ISBLANK($C18)),IF(NOT(ISBLANK(AA18)),TRUE,FALSE),"") -> TRUE | AC18: =IF(NOT(ISBLANK($C18)),AND(AB18=TRUE,NOT(COUNTIF('List of Values'!$B$2:$B$255,AA18)=0)),"") -> TRUE | AD18: SEK | AE18: =IF(NOT(ISBLANK($C18)),IF(NOT(ISBLANK(AD18)),TRUE,FALSE),"") -> TRUE | AF18: =IF(NOT(ISBLANK($C18)),AND(AE18=TRUE,NOT(COUNTIF('List of Values'!$F$2:$F$255,AD18)=0)),"") -> TRUE | AG18: V_20NET | AH18: =IF(NOT(ISBLANK($C18)),IF(NOT(ISBLANK(AG18)),TRUE,FALSE),"") -> TRUE | AI18: =IF(NOT(ISBLANK($C18)),AND(AH18=TRUE,NOT(COUNTIF('List of Values'!$N$2:$N$40,AG18)=0)),"") -> TRUE | AJ18: V_BANK | AK18: =IF(NOT(ISBLANK($C18)),IF(NOT(ISBLANK(AJ18)),TRUE,FALSE),"") -> TRUE | AL18: =IF(NOT(ISBLANK($C18)),AND(AK18=TRUE,NOT(COUNTIF('List of Values'!$O$2:$O$30,AJ18)=0)),"") -> TRUE | AM18: S-DOM | AN18: =IF(NOT(ISBLANK($C18)),IF(NOT(ISBLANK(AM18)),TRUE,FALSE),"") -> TRUE | AO18: =IF(NOT(ISBLANK($C18)),AND(AN18=TRUE,NOT(COUNTIF('List of Values'!$AF$2:$AF$20,AM18)=0)),"") -> TRUE | AQ18: =IF(NOT(ISBLANK($C18)),TRUE,"") -> TRUE | AR18: {=IF(NOT(ISBLANK($C18)),AND(AQ18=TRUE,LEN(AP18)<81,NOT(ISNUMBER(FIND('List of Values'!$C$2:$C$20,AP18)))),"")} -> TRUE | AS18: =D18 -> GULDHAVEN PELAGISKA AB | AT18: =IF(NOT(ISBLANK($C18)),IF(NOT(ISBLANK(AS18)),TRUE,FALSE),"") -> TRUE | AU18: {=IF(NOT(ISBLANK($C18)),AND(AT18=TRUE,LEN(AS18)<81,NOT(ISNUMBER(FIND('List of Values'!$C$2:$C$20,AS18)))),"")} -> TRUE | AV18: GULDHAVENPELAGISKAAB | AW18: =IF(NOT(ISBLANK($C18)),IF(NOT(ISBLANK(AV18)),TRUE,FALSE),"") -> TRUE | AX18: {=IF(NOT(ISBLANK($C18)),AND(AW18=TRUE,LEN(AV18)<21,NOT(ISNUMBER(FIND('List of Values'!$C$2:$C$20,AV18)))),"")} -> TRUE | AY18: 12344 | AZ18: =IF(NOT(ISBLANK($C18)),TRUE,"") -> TRUE | BA18: =IF(NOT(ISBLANK($C18)),AND(AZ18=TRUE,NOT(COUNTIF('List of Values'!$R$2:$R$400,AY18)=0)),"") -> TRUE | BC18: =IF(NOT(ISBLANK($C18)),TRUE,"") -> TRUE | BD18: {=IF(NOT(ISBLANK($C18)),OR(ISBLANK(BB18),AND(NOT(ISNUMBER(FIND('List of Values'!$C$2:$C$23,BB18))),ISNUMBER(DATEVALUE(BB18)))),"")} -> TRUE | BF18: =IF(NOT(ISBLANK($C18)),TRUE,"") -> TRUE | BG18: {=IF(NOT(ISBLANK($C18)),OR(ISBLANK(BE18),AND(NOT(ISNUMBER(FIND('List of Values'!$C$2:$C$23,BE18))),ISNUMBER(DATEVALUE(BE18)))),"")} -> TRUE | BH18: 7350036610005 | BI18: =IF(NOT(ISBLANK($C18)),TRUE,"") -> TRUE | BJ18: =IF(NOT(ISBLANK($C18)),OR(ISBLANK(BH18),AND(LEN(BH18)<14,ISNUMBER(BH18))),"") -> TRUE | BK18: Invoice | BL18: =IF(NOT(ISBLANK($C18)),IF(NOT(ISBLANK(BK18)),TRUE,FALSE),"") -> TRUE | BM18: =IF(NOT(ISBLANK($C18)),AND(BL18=TRUE,NOT(COUNTIF('List of Values'!$A$2:$A$20,BK18)=0)),"") -> TRUE | BN18: Active | BO18: =IF(NOT(ISBLANK($C18)),IF(NOT(ISBLANK(BN18)),TRUE,FALSE),"") -> TRUE | BP18: =IF(NOT(ISBLANK($C18)),OR(BN18="active",BN18="delisted"),"") -> TRUE | BR18: =IF(NOT(ISBLANK($C18)),OR(AND($E18="intercompany",NOT(ISBLANK(BQ18))),AND(NOT($E18="intercompany"),ISBLANK(BQ18))),"") -> TRUE | BS18: =IF(NOT(ISBLANK($C18)),OR(ISBLANK(BQ18),NOT(COUNTIF('List of Values'!$K$2:$K$30,BQ18)=0)),"") -> TRUE | BU18: =IF(NOT(ISBLANK($C18)),TRUE,"") -> TRUE | BV18: =IF(NOT(ISBLANK($C18)),OR(ISBLANK(BT18),BT18="duty paid",BT18="bond"),"") -> TRUE | BX18: =IF(NOT(ISBLANK($C18)),TRUE,"") -> TRUE | BY18: =IF(NOT(ISBLANK($C18)),OR(ISBLANK(BW18),BW18="duty paid",BW18="bond"),"") -> TRUE | BZ18: =_xlfn.XLOOKUP(C18,[1]Blad1!$A:$A,[1]Blad1!$D:$D,"")
B19: =COUNTIF(C19:XFD19,"FALSE") -> 0 | C19: 218071 | D19: STADSBUD I STORSTOCKHOLM AB | E19: Indirect | F19: 5564993573 | G19: =IF(NOT(ISBLANK($C19)),IF(NOT(ISBLANK(F19)),TRUE,FALSE),"") -> TRUE | H19: {=IF(NOT(ISBLANK($C19)),AND(G19=TRUE,LEN(F19)<30,NOT(ISNUMBER(FIND('List of Values'!$C$2:$C$20,F19)))),"")} -> TRUE | I19: SE556499357301 | J19: =IF(NOT(ISBLANK($C19)),TRUE,"") -> TRUE | K19: {=IF(NOT(ISBLANK($C19)),AND(J19=TRUE,LEN(I19)<20,NOT(ISNUMBER(FIND('List of Values'!$C$2:$C$20,I19)))),"")} -> TRUE | L19: BOX 5125 | M19: =IF(NOT(ISBLANK($C19)),IF(NOT(ISBLANK(L19)),TRUE,FALSE),"") -> TRUE | N19: {=IF(NOT(ISBLANK($C19)),AND(M19=TRUE,LEN(L19)<81,NOT(ISNUMBER(FIND('List of Values'!$C$2:$C$20,L19)))),"")} -> TRUE | P19: =IF(NOT(ISBLANK($C19)),TRUE,"") -> TRUE | Q19: {=IF(NOT(ISBLANK($C19)),AND(P19=TRUE,LEN(O19)<81,NOT(ISNUMBER(FIND('List of Values'!$C$2:$C$20,O19)))),"")} -> TRUE | R19: JOHANNESHOV | S19: =IF(NOT(ISBLANK($C19)),IF(NOT(ISBLANK(R19)),TRUE,FALSE),"") -> TRUE | T19: {=IF(NOT(ISBLANK($C19)),AND(S19=TRUE,LEN(R19)<61,NOT(ISNUMBER(FIND('List of Values'!$C$2:$C$23,R19)))),"")} -> TRUE | V19: =IF(NOT(ISBLANK($C19)),TRUE,"") -> TRUE | W19: {=IF(NOT(ISBLANK($C19)),AND(V19=TRUE,LEN(U19)<61,NOT(ISNUMBER(FIND('List of Values'!$C$2:$C$23,U19)))),"")} -> TRUE | X19: 121 17 | Y19: =IF(NOT(ISBLANK($C19)),IF(NOT(ISBLANK(X19)),TRUE,FALSE),"") -> TRUE | Z19: {=IF(NOT(ISBLANK($C19)),AND(Y19=TRUE,LEN(X19)<81,NOT(ISNUMBER(FIND('List of Values'!$C$2:$C$23,X19)))),"")} -> TRUE | AA19: SE | AB19: =IF(NOT(ISBLANK($C19)),IF(NOT(ISBLANK(AA19)),TRUE,FALSE),"") -> TRUE | AC19: =IF(NOT(ISBLANK($C19)),AND(AB19=TRUE,NOT(COUNTIF('List of Values'!$B$2:$B$255,AA19)=0)),"") -> TRUE | AD19: SEK | AE19: =IF(NOT(ISBLANK($C19)),IF(NOT(ISBLANK(AD19)),TRUE,FALSE),"") -> TRUE | AF19: =IF(NOT(ISBLANK($C19)),AND(AE19=TRUE,NOT(COUNTIF('List of Values'!$F$2:$F$255,AD19)=0)),"") -> TRUE | AG19: V_10EOM | AH19: =IF(NOT(ISBLANK($C19)),IF(NOT(ISBLANK(AG19)),TRUE,FALSE),"") -> TRUE | AI19: =IF(NOT(ISBLANK($C19)),AND(AH19=TRUE,NOT(COUNTIF('List of Values'!$N$2:$N$40,AG19)=0)),"") -> TRUE | AJ19: V_BANK | AK19: =IF(NOT(ISBLANK($C19)),IF(NOT(ISBLANK(AJ19)),TRUE,FALSE),"") -> TRUE | AL19: =IF(NOT(ISBLANK($C19)),AND(AK19=TRUE,NOT(COUNTIF('List of Values'!$O$2:$O$30,AJ19)=0)),"") -> TRUE | AM19: S-DOM | AN19: =IF(NOT(ISBLANK($C19)),IF(NOT(ISBLANK(AM19)),TRUE,FALSE),"") -> TRUE | AO19: =IF(NOT(ISBLANK($C19)),AND(AN19=TRUE,NOT(COUNTIF('List of Values'!$AF$2:$AF$20,AM19)=0)),"") -> TRUE | AQ19: =IF(NOT(ISBLANK($C19)),TRUE,"") -> TRUE | AR19: {=IF(NOT(ISBLANK($C19)),AND(AQ19=TRUE,LEN(AP19)<81,NOT(ISNUMBER(FIND('List of Values'!$C$2:$C$20,AP19)))),"")} -> TRUE | AS19: =D19 -> STADSBUD I STORSTOCKHOLM AB | AT19: =IF(NOT(ISBLANK($C19)),IF(NOT(ISBLANK(AS19)),TRUE,FALSE),"") -> TRUE | AU19: {=IF(NOT(ISBLANK($C19)),AND(AT19=TRUE,LEN(AS19)<81,NOT(ISNUMBER(FIND('List of Values'!$C$2:$C$20,AS19)))),"")} -> TRUE | AV19: STADSBUDISTORSTOCKHO | AW19: =IF(NOT(ISBLANK($C19)),IF(NOT(ISBLANK(AV19)),TRUE,FALSE),"") -> TRUE | AX19: {=IF(NOT(ISBLANK($C19)),AND(AW19=TRUE,LEN(AV19)<21,NOT(ISNUMBER(FIND('List of Values'!$C$2:$C$20,AV19)))),"")} -> TRUE | AY19: 10001 | AZ19: =IF(NOT(ISBLANK($C19)),TRUE,"") -> TRUE | BA19: =IF(NOT(ISBLANK($C19)),AND(AZ19=TRUE,NOT(COUNTIF('List of Values'!$R$2:$R$400,AY19)=0)),"") -> TRUE | BC19: =IF(NOT(ISBLANK($C19)),TRUE,"") -> TRUE | BD19: {=IF(NOT(ISBLANK($C19)),OR(ISBLANK(BB19),AND(NOT(ISNUMBER(FIND('List of Values'!$C$2:$C$23,BB19))),ISNUMBER(DATEVALUE(BB19)))),"")} -> TRUE | BF19: =IF(NOT(ISBLANK($C19)),TRUE,"") -> TRUE | BG19: {=IF(NOT(ISBLANK($C19)),OR(ISBLANK(BE19),AND(NOT(ISNUMBER(FIND('List of Values'!$C$2:$C$23,BE19))),ISNUMBER(DATEVALUE(BE19)))),"")} -> TRUE | BI19: =IF(NOT(ISBLANK($C19)),TRUE,"") -> TRUE | BJ19: =IF(NOT(ISBLANK($C19)),OR(ISBLANK(BH19),AND(LEN(BH19)<14,ISNUMBER(BH19))),"") -> TRUE | BK19: Invoice | BL19: =IF(NOT(ISBLANK($C19)),IF(NOT(ISBLANK(BK19)),TRUE,FALSE),"") -> TRUE | BM19: =IF(NOT(ISBLANK($C19)),AND(BL19=TRUE,NOT(COUNTIF('List of Values'!$A$2:$A$20,BK19)=0)),"") -> TRUE | BN19: Delisted | BO19: =IF(NOT(ISBLANK($C19)),IF(NOT(ISBLANK(BN19)),TRUE,FALSE),"") -> TRUE | BP19: =IF(NOT(ISBLANK($C19)),OR(BN19="active",BN19="delisted"),"") -> TRUE | BR19: =IF(NOT(ISBLANK($C19)),OR(AND($E19="intercompany",NOT(ISBLANK(BQ19))),AND(NOT($E19="intercompany"),ISBLANK(BQ19))),"") -> TRUE | BS19: =IF(NOT(ISBLANK($C19)),OR(ISBLANK(BQ19),NOT(COUNTIF('List of Values'!$K$2:$K$30,BQ19)=0)),"") -> TRUE | BU19: =IF(NOT(ISBLANK($C19)),TRUE,"") -> TRUE | BV19: =IF(NOT(ISBLANK($C19)),OR(ISBLANK(BT19),BT19="duty paid",BT19="bond"),"") -> TRUE | BX19: =IF(NOT(ISBLANK($C19)),TRUE,"") -> TRUE | BY19: =IF(NOT(ISBLANK($C19)),OR(ISBLANK(BW19),BW19="duty paid",BW19="bond"),"") -> TRUE | BZ19: =_xlfn.XLOOKUP(C19,[1]Blad1!$A:$A,[1]Blad1!$D:$D,"")
B20: =COUNTIF(C20:XFD20,"FALSE") -> 0 | C20: 217989 | D20: GEFION SEAFOOD APS | E20: Trade | F20: DK32775527 | G20: =IF(NOT(ISBLANK($C20)),IF(NOT(ISBLANK(F20)),TRUE,FALSE),"") -> TRUE | H20: {=IF(NOT(ISBLANK($C20)),AND(G20=TRUE,LEN(F20)<30,NOT(ISNUMBER(FIND('List of Values'!$C$2:$C$20,F20)))),"")} -> TRUE | I20: DK32775527 | J20: =IF(NOT(ISBLANK($C20)),TRUE,"") -> TRUE | K20: {=IF(NOT(ISBLANK($C20)),AND(J20=TRUE,LEN(I20)<20,NOT(ISNUMBER(FIND('List of Values'!$C$2:$C$20,I20)))),"")} -> TRUE | L20: VOGNMAGERVEJ 14 | M20: =IF(NOT(ISBLANK($C20)),IF(NOT(ISBLANK(L20)),TRUE,FALSE),"") -> TRUE | N20: {=IF(NOT(ISBLANK($C20)),AND(M20=TRUE,LEN(L20)<81,NOT(ISNUMBER(FIND('List of Values'!$C$2:$C$20,L20)))),"")} -> TRUE | P20: =IF(NOT(ISBLANK($C20)),TRUE,"") -> TRUE | Q20: {=IF(NOT(ISBLANK($C20)),AND(P20=TRUE,LEN(O20)<81,NOT(ISNUMBER(FIND('List of Values'!$C$2:$C$20,O20)))),"")} -> TRUE | R20: VIBORG | S20: =IF(NOT(ISBLANK($C20)),IF(NOT(ISBLANK(R20)),TRUE,FALSE),"") -> TRUE | T20: {=IF(NOT(ISBLANK($C20)),AND(S20=TRUE,LEN(R20)<61,NOT(ISNUMBER(FIND('List of Values'!$C$2:$C$23,R20)))),"")} -> TRUE | V20: =IF(NOT(ISBLANK($C20)),TRUE,"") -> TRUE | W20: {=IF(NOT(ISBLANK($C20)),AND(V20=TRUE,LEN(U20)<61,NOT(ISNUMBER(FIND('List of Values'!$C$2:$C$23,U20)))),"")} -> TRUE | X20: DK-8800 | Y20: =IF(NOT(ISBLANK($C20)),IF(NOT(ISBLANK(X20)),TRUE,FALSE),"") -> TRUE | Z20: {=IF(NOT(ISBLANK($C20)),AND(Y20=TRUE,LEN(X20)<81,NOT(ISNUMBER(FIND('List of Values'!$C$2:$C$23,X20)))),"")} -> TRUE | AA20: DK | AB20: =IF(NOT(ISBLANK($C20)),IF(NOT(ISBLANK(AA20)),TRUE,FALSE),"") -> TRUE | AC20: =IF(NOT(ISBLANK($C20)),AND(AB20=TRUE,NOT(COUNTIF('List of Values'!$B$2:$B$255,AA20)=0)),"") -> TRUE | AD20: SEK | AE20: =IF(NOT(ISBLANK($C20)),IF(NOT(ISBLANK(AD20)),TRUE,FALSE),"") -> TRUE | AF20: =IF(NOT(ISBLANK($C20)),AND(AE20=TRUE,NOT(COUNTIF('List of Values'!$F$2:$F$255,AD20)=0)),"") -> TRUE | AG20: V_10EOM | AH20: =IF(NOT(ISBLANK($C20)),IF(NOT(ISBLANK(AG20)),TRUE,FALSE),"") -> TRUE | AI20: =IF(NOT(ISBLANK($C20)),AND(AH20=TRUE,NOT(COUNTIF('List of Values'!$N$2:$N$40,AG20)=0)),"") -> TRUE | AJ20: V_BANK | AK20: =IF(NOT(ISBLANK($C20)),IF(NOT(ISBLANK(AJ20)),TRUE,FALSE),"") -> TRUE | AL20: =IF(NOT(ISBLANK($C20)),AND(AK20=TRUE,NOT(COUNTIF('List of Values'!$O$2:$O$30,AJ20)=0)),"") -> TRUE | AM20: S-EU | AN20: =IF(NOT(ISBLANK($C20)),IF(NOT(ISBLANK(AM20)),TRUE,FALSE),"") -> TRUE | AO20: =IF(NOT(ISBLANK($C20)),AND(AN20=TRUE,NOT(COUNTIF('List of Values'!$AF$2:$AF$20,AM20)=0)),"") -> TRUE | AQ20: =IF(NOT(ISBLANK($C20)),TRUE,"") -> TRUE | AR20: {=IF(NOT(ISBLANK($C20)),AND(AQ20=TRUE,LEN(AP20)<81,NOT(ISNUMBER(FIND('List of Values'!$C$2:$C$20,AP20)))),"")} -> TRUE | AS20: =D20 -> GEFION SEAFOOD APS | AT20: =IF(NOT(ISBLANK($C20)),IF(NOT(ISBLANK(AS20)),TRUE,FALSE),"") -> TRUE | AU20: {=IF(NOT(ISBLANK($C20)),AND(AT20=TRUE,LEN(AS20)<81,NOT(ISNUMBER(FIND('List of Values'!$C$2:$C$20,AS20)))),"")} -> TRUE | AV20: GEFIONSEAFOODAPS | AW20: =IF(NOT(ISBLANK($C20)),IF(NOT(ISBLANK(AV20)),TRUE,FALSE),"") -> TRUE | AX20: {=IF(NOT(ISBLANK($C20)),AND(AW20=TRUE,LEN(AV20)<21,NOT(ISNUMBER(FIND('List of Values'!$C$2:$C$20,AV20)))),"")} -> TRUE | AY20: 12134 | AZ20: =IF(NOT(ISBLANK($C20)),TRUE,"") -> TRUE | BA20: =IF(NOT(ISBLANK($C20)),AND(AZ20=TRUE,NOT(COUNTIF('List of Values'!$R$2:$R$400,AY20)=0)),"") -> TRUE | BC20: =IF(NOT(ISBLANK($C20)),TRUE,"") -> TRUE | BD20: {=IF(NOT(ISBLANK($C20)),OR(ISBLANK(BB20),AND(NOT(ISNUMBER(FIND('List of Values'!$C$2:$C$23,BB20))),ISNUMBER(DATEVALUE(BB20)))),"")} -> TRUE | BF20: =IF(NOT(ISBLANK($C20)),TRUE,"") -> TRUE | BG20: {=IF(NOT(ISBLANK($C20)),OR(ISBLANK(BE20),AND(NOT(ISNUMBER(FIND('List of Values'!$C$2:$C$23,BE20))),ISNUMBER(DATEVALUE(BE20)))),"")} -> TRUE | BI20: =IF(NOT(ISBLANK($C20)),TRUE,"") -> TRUE | BJ20: =IF(NOT(ISBLANK($C20)),OR(ISBLANK(BH20),AND(LEN(BH20)<14,ISNUMBER(BH20))),"") -> TRUE | BK20: Invoice | BL20: =IF(NOT(ISBLANK($C20)),IF(NOT(ISBLANK(BK20)),TRUE,FALSE),"") -> TRUE | BM20: =IF(NOT(ISBLANK($C20)),AND(BL20=TRUE,NOT(COUNTIF('List of Values'!$A$2:$A$20,BK20)=0)),"") -> TRUE | BN20: Active | BO20: =IF(NOT(ISBLANK($C20)),IF(NOT(ISBLANK(BN20)),TRUE,FALSE),"") -> TRUE | BP20: =IF(NOT(ISBLANK($C20)),OR(BN20="active",BN20="delisted"),"") -> TRUE | BR20: =IF(NOT(ISBLANK($C20)),OR(AND($E20="intercompany",NOT(ISBLANK(BQ20))),AND(NOT($E20="intercompany"),ISBLANK(BQ20))),"") -> TRUE | BS20: =IF(NOT(ISBLANK($C20)),OR(ISBLANK(BQ20),NOT(COUNTIF('List of Values'!$K$2:$K$30,BQ20)=0)),"") -> TRUE | BU20: =IF(NOT(ISBLANK($C20)),TRUE,"") -> TRUE | BV20: =IF(NOT(ISBLANK($C20)),OR(ISBLANK(BT20),BT20="duty paid",BT20="bond"),"") -> TRUE | BX20: =IF(NOT(ISBLANK($C20)),TRUE,"") -> TRUE | BY20: =IF(NOT(ISBLANK($C20)),OR(ISBLANK(BW20),BW20="duty paid",BW20="bond"),"") -> TRUE | BZ20: =_xlfn.XLOOKUP(C20,[1]Blad1!$A:$A,[1]Blad1!$D:$D,"")
B21: =COUNTIF(C21:XFD21,"FALSE") -> 0 | C21: 217940 | D21: GOURMET FOOD F SVANBERG AB | E21: Trade | F21: 5562322411 | G21: =IF(NOT(ISBLANK($C21)),IF(NOT(ISBLANK(F21)),TRUE,FALSE),"") -> TRUE | H21: {=IF(NOT(ISBLANK($C21)),AND(G21=TRUE,LEN(F21)<30,NOT(ISNUMBER(FIND('List of Values'!$C$2:$C$20,F21)))),"")} -> TRUE | I21: SE556232241101 | J21: =IF(NOT(ISBLANK($C21)),TRUE,"") -> TRUE | K21: {=IF(NOT(ISBLANK($C21)),AND(J21=TRUE,LEN(I21)<20,NOT(ISNUMBER(FIND('List of Values'!$C$2:$C$20,I21)))),"")} -> TRUE | L21: BOX 5114 | M21: =IF(NOT(ISBLANK($C21)),IF(NOT(ISBLANK(L21)),TRUE,FALSE),"") -> TRUE | N21: {=IF(NOT(ISBLANK($C21)),AND(M21=TRUE,LEN(L21)<81,NOT(ISNUMBER(FIND('List of Values'!$C$2:$C$20,L21)))),"")} -> TRUE | P21: =IF(NOT(ISBLANK($C21)),TRUE,"") -> TRUE | Q21: {=IF(NOT(ISBLANK($C21)),AND(P21=TRUE,LEN(O21)<81,NOT(ISNUMBER(FIND('List of Values'!$C$2:$C$20,O21)))),"")} -> TRUE | R21: JOHANNESHOV | S21: =IF(NOT(ISBLANK($C21)),IF(NOT(ISBLANK(R21)),TRUE,FALSE),"") -> TRUE | T21: {=IF(NOT(ISBLANK($C21)),AND(S21=TRUE,LEN(R21)<61,NOT(ISNUMBER(FIND('List of Values'!$C$2:$C$23,R21)))),"")} -> TRUE | V21: =IF(NOT(ISBLANK($C21)),TRUE,"") -> TRUE | W21: {=IF(NOT(ISBLANK($C21)),AND(V21=TRUE,LEN(U21)<61,NOT(ISNUMBER(FIND('List of Values'!$C$2:$C$23,U21)))),"")} -> TRUE | X21: 121 17 | Y21: =IF(NOT(ISBLANK($C21)),IF(NOT(ISBLANK(X21)),TRUE,FALSE),"") -> TRUE | Z21: {=IF(NOT(ISBLANK($C21)),AND(Y21=TRUE,LEN(X21)<81,NOT(ISNUMBER(FIND('List of Values'!$C$2:$C$23,X21)))),"")} -> TRUE | AA21: SE | AB21: =IF(NOT(ISBLANK($C21)),IF(NOT(ISBLANK(AA21)),TRUE,FALSE),"") -> TRUE | AC21: =IF(NOT(ISBLANK($C21)),AND(AB21=TRUE,NOT(COUNTIF('List of Values'!$B$2:$B$255,AA21)=0)),"") -> TRUE | AD21: SEK | AE21: =IF(NOT(ISBLANK($C21)),IF(NOT(ISBLANK(AD21)),TRUE,FALSE),"") -> TRUE | AF21: =IF(NOT(ISBLANK($C21)),AND(AE21=TRUE,NOT(COUNTIF('List of Values'!$F$2:$F$255,AD21)=0)),"") -> TRUE | AG21: V_20NET | AH21: =IF(NOT(ISBLANK($C21)),IF(NOT(ISBLANK(AG21)),TRUE,FALSE),"") -> TRUE | AI21: =IF(NOT(ISBLANK($C21)),AND(AH21=TRUE,NOT(COUNTIF('List of Values'!$N$2:$N$40,AG21)=0)),"") -> TRUE | AJ21: V_BANK | AK21: =IF(NOT(ISBLANK($C21)),IF(NOT(ISBLANK(AJ21)),TRUE,FALSE),"") -> TRUE | AL21: =IF(NOT(ISBLANK($C21)),AND(AK21=TRUE,NOT(COUNTIF('List of Values'!$O$2:$O$30,AJ21)=0)),"") -> TRUE | AM21: S-DOM | AN21: =IF(NOT(ISBLANK($C21)),IF(NOT(ISBLANK(AM21)),TRUE,FALSE),"") -> TRUE | AO21: =IF(NOT(ISBLANK($C21)),AND(AN21=TRUE,NOT(COUNTIF('List of Values'!$AF$2:$AF$20,AM21)=0)),"") -> TRUE | AQ21: =IF(NOT(ISBLANK($C21)),TRUE,"") -> TRUE | AR21: {=IF(NOT(ISBLANK($C21)),AND(AQ21=TRUE,LEN(AP21)<81,NOT(ISNUMBER(FIND('List of Values'!$C$2:$C$20,AP21)))),"")} -> TRUE | AS21: =D21 -> GOURMET FOOD F SVANBERG AB | AT21: =IF(NOT(ISBLANK($C21)),IF(NOT(ISBLANK(AS21)),TRUE,FALSE),"") -> TRUE | AU21: {=IF(NOT(ISBLANK($C21)),AND(AT21=TRUE,LEN(AS21)<81,NOT(ISNUMBER(FIND('List of Values'!$C$2:$C$20,AS21)))),"")} -> TRUE | AV21: GOURMETFOODFSVANBERG | AW21: =IF(NOT(ISBLANK($C21)),IF(NOT(ISBLANK(AV21)),TRUE,FALSE),"") -> TRUE | AX21: {=IF(NOT(ISBLANK($C21)),AND(AW21=TRUE,LEN(AV21)<21,NOT(ISNUMBER(FIND('List of Values'!$C$2:$C$20,AV21)))),"")} -> TRUE | AY21: 12241 | AZ21: =IF(NOT(ISBLANK($C21)),TRUE,"") -> TRUE | BA21: =IF(NOT(ISBLANK($C21)),AND(AZ21=TRUE,NOT(COUNTIF('List of Values'!$R$2:$R$400,AY21)=0)),"") -> TRUE | BC21: =IF(NOT(ISBLANK($C21)),TRUE,"") -> TRUE | BD21: {=IF(NOT(ISBLANK($C21)),OR(ISBLANK(BB21),AND(NOT(ISNUMBER(FIND('List of Values'!$C$2:$C$23,BB21))),ISNUMBER(DATEVALUE(BB21)))),"")} -> TRUE | BF21: =IF(NOT(ISBLANK($C21)),TRUE,"") -> TRUE | BG21: {=IF(NOT(ISBLANK($C21)),OR(ISBLANK(BE21),AND(NOT(ISNUMBER(FIND('List of Values'!$C$2:$C$23,BE21))),ISNUMBER(DATEVALUE(BE21)))),"")} -> TRUE | BH21: 7350007470003 | BI21: =IF(NOT(ISBLANK($C21)),TRUE,"") -> TRUE | BJ21: =IF(NOT(ISBLANK($C21)),OR(ISBLANK(BH21),AND(LEN(BH21)<14,ISNUMBER(BH21))),"") -> TRUE | BK21: Invoice | BL21: =IF(NOT(ISBLANK($C21)),IF(NOT(ISBLANK(BK21)),TRUE,FALSE),"") -> TRUE | BM21: =IF(NOT(ISBLANK($C21)),AND(BL21=TRUE,NOT(COUNTIF('List of Values'!$A$2:$A$20,BK21)=0)),"") -> TRUE | BN21: Active | BO21: =IF(NOT(ISBLANK($C21)),IF(NOT(ISBLANK(BN21)),TRUE,FALSE),"") -> TRUE | BP21: =IF(NOT(ISBLANK($C21)),OR(BN21="active",BN21="delisted"),"") -> TRUE | BR21: =IF(NOT(ISBLANK($C21)),OR(AND($E21="intercompany",NOT(ISBLANK(BQ21))),AND(NOT($E21="intercompany"),ISBLANK(BQ21))),"") -> TRUE | BS21: =IF(NOT(ISBLANK($C21)),OR(ISBLANK(BQ21),NOT(COUNTIF('List of Values'!$K$2:$K$30,BQ21)=0)),"") -> TRUE | BU21: =IF(NOT(ISBLANK($C21)),TRUE,"") -> TRUE | BV21: =IF(NOT(ISBLANK($C21)),OR(ISBLANK(BT21),BT21="duty paid",BT21="bond"),"") -> TRUE | BX21: =IF(NOT(ISBLANK($C21)),TRUE,"") -> TRUE | BY21: =IF(NOT(ISBLANK($C21)),OR(ISBLANK(BW21),BW21="duty paid",BW21="bond"),"") -> TRUE | BZ21: =_xlfn.XLOOKUP(C21,[1]Blad1!$A:$A,[1]Blad1!$D:$D,"")
B22: =COUNTIF(C22:XFD22,"FALSE") -> 0 | C22: 218060 | D22: TRUCKREPERATÖRENS FÖRSÄLJNINGS AB | E22: Indirect | F22: 5563364602 | G22: =IF(NOT(ISBLANK($C22)),IF(NOT(ISBLANK(F22)),TRUE,FALSE),"") -> TRUE | H22: {=IF(NOT(ISBLANK($C22)),AND(G22=TRUE,LEN(F22)<30,NOT(ISNUMBER(FIND('List of Values'!$C$2:$C$20,F22)))),"")} -> TRUE | I22: SE556336460201 | J22: =IF(NOT(ISBLANK($C22)),TRUE,"") -> TRUE | K22: {=IF(NOT(ISBLANK($C22)),AND(J22=TRUE,LEN(I22)<20,NOT(ISNUMBER(FIND('List of Values'!$C$2:$C$20,I22)))),"")} -> TRUE | L22: BOX 2074 | M22: =IF(NOT(ISBLANK($C22)),IF(NOT(ISBLANK(L22)),TRUE,FALSE),"") -> TRUE | N22: {=IF(NOT(ISBLANK($C22)),AND(M22=TRUE,LEN(L22)<81,NOT(ISNUMBER(FIND('List of Values'!$C$2:$C$20,L22)))),"")} -> TRUE | P22: =IF(NOT(ISBLANK($C22)),TRUE,"") -> TRUE | Q22: {=IF(NOT(ISBLANK($C22)),AND(P22=TRUE,LEN(O22)<81,NOT(ISNUMBER(FIND('List of Values'!$C$2:$C$20,O22)))),"")} -> TRUE | R22: TYRESÖ | S22: =IF(NOT(ISBLANK($C22)),IF(NOT(ISBLANK(R22)),TRUE,FALSE),"") -> TRUE | T22: {=IF(NOT(ISBLANK($C22)),AND(S22=TRUE,LEN(R22)<61,NOT(ISNUMBER(FIND('List of Values'!$C$2:$C$23,R22)))),"")} -> TRUE | V22: =IF(NOT(ISBLANK($C22)),TRUE,"") -> TRUE | W22: {=IF(NOT(ISBLANK($C22)),AND(V22=TRUE,LEN(U22)<61,NOT(ISNUMBER(FIND('List of Values'!$C$2:$C$23,U22)))),"")} -> TRUE | X22: 135 02 | Y22: =IF(NOT(ISBLANK($C22)),IF(NOT(ISBLANK(X22)),TRUE,FALSE),"") -> TRUE | Z22: {=IF(NOT(ISBLANK($C22)),AND(Y22=TRUE,LEN(X22)<81,NOT(ISNUMBER(FIND('List of Values'!$C$2:$C$23,X22)))),"")} -> TRUE | AA22: SE | AB22: =IF(NOT(ISBLANK($C22)),IF(NOT(ISBLANK(AA22)),TRUE,FALSE),"") -> TRUE | AC22: =IF(NOT(ISBLANK($C22)),AND(AB22=TRUE,NOT(COUNTIF('List of Values'!$B$2:$B$255,AA22)=0)),"") -> TRUE | AD22: SEK | AE22: =IF(NOT(ISBLANK($C22)),IF(NOT(ISBLANK(AD22)),TRUE,FALSE),"") -> TRUE | AF22: =IF(NOT(ISBLANK($C22)),AND(AE22=TRUE,NOT(COUNTIF('List of Values'!$F$2:$F$255,AD22)=0)),"") -> TRUE | AG22: V_10EOM | AH22: =IF(NOT(ISBLANK($C22)),IF(NOT(ISBLANK(AG22)),TRUE,FALSE),"") -> TRUE | AI22: =IF(NOT(ISBLANK($C22)),AND(AH22=TRUE,NOT(COUNTIF('List of Values'!$N$2:$N$40,AG22)=0)),"") -> TRUE | AJ22: V_BANK | AK22: =IF(NOT(ISBLANK($C22)),IF(NOT(ISBLANK(AJ22)),TRUE,FALSE),"") -> TRUE | AL22: =IF(NOT(ISBLANK($C22)),AND(AK22=TRUE,NOT(COUNTIF('List of Values'!$O$2:$O$30,AJ22)=0)),"") -> TRUE | AM22: S-DOM | AN22: =IF(NOT(ISBLANK($C22)),IF(NOT(ISBLANK(AM22)),TRUE,FALSE),"") -> TRUE | AO22: =IF(NOT(ISBLANK($C22)),AND(AN22=TRUE,NOT(COUNTIF('List of Values'!$AF$2:$AF$20,AM22)=0)),"") -> TRUE | AQ22: =IF(NOT(ISBLANK($C22)),TRUE,"") -> TRUE | AR22: {=IF(NOT(ISBLANK($C22)),AND(AQ22=TRUE,LEN(AP22)<81,NOT(ISNUMBER(FIND('List of Values'!$C$2:$C$20,AP22)))),"")} -> TRUE | AS22: =D22 -> TRUCKREPERATÖRENS FÖRSÄLJNINGS AB | AT22: =IF(NOT(ISBLANK($C22)),IF(NOT(ISBLANK(AS22)),TRUE,FALSE),"") -> TRUE | AU22: {=IF(NOT(ISBLANK($C22)),AND(AT22=TRUE,LEN(AS22)<81,NOT(ISNUMBER(FIND('List of Values'!$C$2:$C$20,AS22)))),"")} -> TRUE | AV22: TRUCKREPERATÖRENSFÖR | AW22: =IF(NOT(ISBLANK($C22)),IF(NOT(ISBLANK(AV22)),TRUE,FALSE),"") -> TRUE | AX22: {=IF(NOT(ISBLANK($C22)),AND(AW22=TRUE,LEN(AV22)<21,NOT(ISNUMBER(FIND('List of Values'!$C$2:$C$20,AV22)))),"")} -> TRUE | AY22: 10001 | AZ22: =IF(NOT(ISBLANK($C22)),TRUE,"") -> TRUE | BA22: =IF(NOT(ISBLANK($C22)),AND(AZ22=TRUE,NOT(COUNTIF('List of Values'!$R$2:$R$400,AY22)=0)),"") -> TRUE | BC22: =IF(NOT(ISBLANK($C22)),TRUE,"") -> TRUE | BD22: {=IF(NOT(ISBLANK($C22)),OR(ISBLANK(BB22),AND(NOT(ISNUMBER(FIND('List of Values'!$C$2:$C$23,BB22))),ISNUMBER(DATEVALUE(BB22)))),"")} -> TRUE | BF22: =IF(NOT(ISBLANK($C22)),TRUE,"") -> TRUE | BG22: {=IF(NOT(ISBLANK($C22)),OR(ISBLANK(BE22),AND(NOT(ISNUMBER(FIND('List of Values'!$C$2:$C$23,BE22))),ISNUMBER(DATEVALUE(BE22)))),"")} -> TRUE | BI22: =IF(NOT(ISBLANK($C22)),TRUE,"") -> TRUE | BJ22: =IF(NOT(ISBLANK($C22)),OR(ISBLANK(BH22),AND(LEN(BH22)<14,ISNUMBER(BH22))),"") -> TRUE | BK22: Invoice | BL22: =IF(NOT(ISBLANK($C22)),IF(NOT(ISBLANK(BK22)),TRUE,FALSE),"") -> TRUE | BM22: =IF(NOT(ISBLANK($C22)),AND(BL22=TRUE,NOT(COUNTIF('List of Values'!$A$2:$A$20,BK22)=0)),"") -> TRUE | BN22: Active | BO22: =IF(NOT(ISBLANK($C22)),IF(NOT(ISBLANK(BN22)),TRUE,FALSE),"") -> TRUE | BP22: =IF(NOT(ISBLANK($C22)),OR(BN22="active",BN22="delisted"),"") -> TRUE | BR22: =IF(NOT(ISBLANK($C22)),OR(AND($E22="intercompany",NOT(ISBLANK(BQ22))),AND(NOT($E22="intercompany"),ISBLANK(BQ22))),"") -> TRUE | BS22: =IF(NOT(ISBLANK($C22)),OR(ISBLANK(BQ22),NOT(COUNTIF('List of Values'!$K$2:$K$30,BQ22)=0)),"") -> TRUE | BU22: =IF(NOT(ISBLANK($C22)),TRUE,"") -> TRUE | BV22: =IF(NOT(ISBLANK($C22)),OR(ISBLANK(BT22),BT22="duty paid",BT22="bond"),"") -> TRUE | BX22: =IF(NOT(ISBLANK($C22)),TRUE,"") -> TRUE | BY22: =IF(NOT(ISBLANK($C22)),OR(ISBLANK(BW22),BW22="duty paid",BW22="bond"),"") -> TRUE | BZ22: =_xlfn.XLOOKUP(C22,[1]Blad1!$A:$A,[1]Blad1!$D:$D,"")
B23: =COUNTIF(C23:XFD23,"FALSE") -> 0 | C23: 218014 | D23: STOCKHOLMS MILJÖFÖRVALTNING | E23: Indirect | F23: 2120000142 | G23: =IF(NOT(ISBLANK($C23)),IF(NOT(ISBLANK(F23)),TRUE,FALSE),"") -> TRUE | H23: {=IF(NOT(ISBLANK($C23)),AND(G23=TRUE,LEN(F23)<30,NOT(ISNUMBER(FIND('List of Values'!$C$2:$C$20,F23)))),"")} -> TRUE | I23: SE212000014201 | J23: =IF(NOT(ISBLANK($C23)),TRUE,"") -> TRUE | K23: {=IF(NOT(ISBLANK($C23)),AND(J23=TRUE,LEN(I23)<20,NOT(ISNUMBER(FIND('List of Values'!$C$2:$C$20,I23)))),"")} -> TRUE | L23: BOX 38024 | M23: =IF(NOT(ISBLANK($C23)),IF(NOT(ISBLANK(L23)),TRUE,FALSE),"") -> TRUE | N23: {=IF(NOT(ISBLANK($C23)),AND(M23=TRUE,LEN(L23)<81,NOT(ISNUMBER(FIND('List of Values'!$C$2:$C$20,L23)))),"")} -> TRUE | P23: =IF(NOT(ISBLANK($C23)),TRUE,"") -> TRUE | Q23: {=IF(NOT(ISBLANK($C23)),AND(P23=TRUE,LEN(O23)<81,NOT(ISNUMBER(FIND('List of Values'!$C$2:$C$20,O23)))),"")} -> TRUE | R23: STOCKHOLM | S23: =IF(NOT(ISBLANK($C23)),IF(NOT(ISBLANK(R23)),TRUE,FALSE),"") -> TRUE | T23: {=IF(NOT(ISBLANK($C23)),AND(S23=TRUE,LEN(R23)<61,NOT(ISNUMBER(FIND('List of Values'!$C$2:$C$23,R23)))),"")} -> TRUE | V23: =IF(NOT(ISBLANK($C23)),TRUE,"") -> TRUE | W23: {=IF(NOT(ISBLANK($C23)),AND(V23=TRUE,LEN(U23)<61,NOT(ISNUMBER(FIND('List of Values'!$C$2:$C$23,U23)))),"")} -> TRUE | X23: 100 64 | Y23: =IF(NOT(ISBLANK($C23)),IF(NOT(ISBLANK(X23)),TRUE,FALSE),"") -> TRUE | Z23: {=IF(NOT(ISBLANK($C23)),AND(Y23=TRUE,LEN(X23)<81,NOT(ISNUMBER(FIND('List of Values'!$C$2:$C$23,X23)))),"")} -> TRUE | AA23: SE | AB23: =IF(NOT(ISBLANK($C23)),IF(NOT(ISBLANK(AA23)),TRUE,FALSE),"") -> TRUE | AC23: =IF(NOT(ISBLANK($C23)),AND(AB23=TRUE,NOT(COUNTIF('List of Values'!$B$2:$B$255,AA23)=0)),"") -> TRUE | AD23: SEK | AE23: =IF(NOT(ISBLANK($C23)),IF(NOT(ISBLANK(AD23)),TRUE,FALSE),"") -> TRUE | AF23: =IF(NOT(ISBLANK($C23)),AND(AE23=TRUE,NOT(COUNTIF('List of Values'!$F$2:$F$255,AD23)=0)),"") -> TRUE | AG23: V_30NET | AH23: =IF(NOT(ISBLANK($C23)),IF(NOT(ISBLANK(AG23)),TRUE,FALSE),"") -> TRUE | AI23: =IF(NOT(ISBLANK($C23)),AND(AH23=TRUE,NOT(COUNTIF('List of Values'!$N$2:$N$40,AG23)=0)),"") -> TRUE | AJ23: V_BANK | AK23: =IF(NOT(ISBLANK($C23)),IF(NOT(ISBLANK(AJ23)),TRUE,FALSE),"") -> TRUE | AL23: =IF(NOT(ISBLANK($C23)),AND(AK23=TRUE,NOT(COUNTIF('List of Values'!$O$2:$O$30,AJ23)=0)),"") -> TRUE | AM23: S-DOM | AN23: =IF(NOT(ISBLANK($C23)),IF(NOT(ISBLANK(AM23)),TRUE,FALSE),"") -> TRUE | AO23: =IF(NOT(ISBLANK($C23)),AND(AN23=TRUE,NOT(COUNTIF('List of Values'!$AF$2:$AF$20,AM23)=0)),"") -> TRUE | AQ23: =IF(NOT(ISBLANK($C23)),TRUE,"") -> TRUE | AR23: {=IF(NOT(ISBLANK($C23)),AND(AQ23=TRUE,LEN(AP23)<81,NOT(ISNUMBER(FIND('List of Values'!$C$2:$C$20,AP23)))),"")} -> TRUE | AS23: =D23 -> STOCKHOLMS MILJÖFÖRVALTNING | AT23: =IF(NOT(ISBLANK($C23)),IF(NOT(ISBLANK(AS23)),TRUE,FALSE),"") -> TRUE | AU23: {=IF(NOT(ISBLANK($C23)),AND(AT23=TRUE,LEN(AS23)<81,NOT(ISNUMBER(FIND('List of Values'!$C$2:$C$20,AS23)))),"")} -> TRUE | AV23: STOCKHOLMSMILJÖFÖRVA | AW23: =IF(NOT(ISBLANK($C23)),IF(NOT(ISBLANK(AV23)),TRUE,FALSE),"") -> TRUE | AX23: {=IF(NOT(ISBLANK($C23)),AND(AW23=TRUE,LEN(AV23)<21,NOT(ISNUMBER(FIND('List of Values'!$C$2:$C$20,AV23)))),"")} -> TRUE | AY23: 10001 | AZ23: =IF(NOT(ISBLANK($C23)),TRUE,"") -> TRUE | BA23: =IF(NOT(ISBLANK($C23)),AND(AZ23=TRUE,NOT(COUNTIF('List of Values'!$R$2:$R$400,AY23)=0)),"") -> TRUE | BC23: =IF(NOT(ISBLANK($C23)),TRUE,"") -> TRUE | BD23: {=IF(NOT(ISBLANK($C23)),OR(ISBLANK(BB23),AND(NOT(ISNUMBER(FIND('List of Values'!$C$2:$C$23,BB23))),ISNUMBER(DATEVALUE(BB23)))),"")} -> TRUE | BF23: =IF(NOT(ISBLANK($C23)),TRUE,"") -> TRUE | BG23: {=IF(NOT(ISBLANK($C23)),OR(ISBLANK(BE23),AND(NOT(ISNUMBER(FIND('List of Values'!$C$2:$C$23,BE23))),ISNUMBER(DATEVALUE(BE23)))),"")} -> TRUE | BI23: =IF(NOT(ISBLANK($C23)),TRUE,"") -> TRUE | BJ23: =IF(NOT(ISBLANK($C23)),OR(ISBLANK(BH23),AND(LEN(BH23)<14,ISNUMBER(BH23))),"") -> TRUE | BK23: Invoice | BL23: =IF(NOT(ISBLANK($C23)),IF(NOT(ISBLANK(BK23)),TRUE,FALSE),"") -> TRUE | BM23: =IF(NOT(ISBLANK($C23)),AND(BL23=TRUE,NOT(COUNTIF('List of Values'!$A$2:$A$20,BK23)=0)),"") -> TRUE | BN23: Active | BO23: =IF(NOT(ISBLANK($C23)),IF(NOT(ISBLANK(BN23)),TRUE,FALSE),"") -> TRUE | BP23: =IF(NOT(ISBLANK($C23)),OR(BN23="active",BN23="delisted"),"") -> TRUE | BR23: =IF(NOT(ISBLANK($C23)),OR(AND($E23="intercompany",NOT(ISBLANK(BQ23))),AND(NOT($E23="intercompany"),ISBLANK(BQ23))),"") -> TRUE | BS23: =IF(NOT(ISBLANK($C23)),OR(ISBLANK(BQ23),NOT(COUNTIF('List of Values'!$K$2:$K$30,BQ23)=0)),"") -> TRUE | BU23: =IF(NOT(ISBLANK($C23)),TRUE,"") -> TRUE | BV23: =IF(NOT(ISBLANK($C23)),OR(ISBLANK(BT23),BT23="duty paid",BT23="bond"),"") -> TRUE | BX23: =IF(NOT(ISBLANK($C23)),TRUE,"") -> TRUE | BY23: =IF(NOT(ISBLANK($C23)),OR(ISBLANK(BW23),BW23="duty paid",BW23="bond"),"") -> TRUE | BZ23: =_xlfn.XLOOKUP(C23,[1]Blad1!$A:$A,[1]Blad1!$D:$D,"")
B24: =COUNTIF(C24:XFD24,"FALSE") -> 0 | C24: 218082 | D24: ADSTRINGO AB | E24: Indirect | F24: 5566238936 | G24: =IF(NOT(ISBLANK($C24)),IF(NOT(ISBLANK(F24)),TRUE,FALSE),"") -> TRUE | H24: {=IF(NOT(ISBLANK($C24)),AND(G24=TRUE,LEN(F24)<30,NOT(ISNUMBER(FIND('List of Values'!$C$2:$C$20,F24)))),"")} -> TRUE | I24: SE556623893601 | J24: =IF(NOT(ISBLANK($C24)),TRUE,"") -> TRUE | K24: {=IF(NOT(ISBLANK($C24)),AND(J24=TRUE,LEN(I24)<20,NOT(ISNUMBER(FIND('List of Values'!$C$2:$C$20,I24)))),"")} -> TRUE | L24: BOX 70 | M24: =IF(NOT(ISBLANK($C24)),IF(NOT(ISBLANK(L24)),TRUE,FALSE),"") -> TRUE | N24: {=IF(NOT(ISBLANK($C24)),AND(M24=TRUE,LEN(L24)<81,NOT(ISNUMBER(FIND('List of Values'!$C$2:$C$20,L24)))),"")} -> TRUE | P24: =IF(NOT(ISBLANK($C24)),TRUE,"") -> TRUE | Q24: {=IF(NOT(ISBLANK($C24)),AND(P24=TRUE,LEN(O24)<81,NOT(ISNUMBER(FIND('List of Values'!$C$2:$C$20,O24)))),"")} -> TRUE | R24: GUSTAVSBERG | S24: =IF(NOT(ISBLANK($C24)),IF(NOT(ISBLANK(R24)),TRUE,FALSE),"") -> TRUE | T24: {=IF(NOT(ISBLANK($C24)),AND(S24=TRUE,LEN(R24)<61,NOT(ISNUMBER(FIND('List of Values'!$C$2:$C$23,R24)))),"")} -> TRUE | V24: =IF(NOT(ISBLANK($C24)),TRUE,"") -> TRUE | W24: {=IF(NOT(ISBLANK($C24)),AND(V24=TRUE,LEN(U24)<61,NOT(ISNUMBER(FIND('List of Values'!$C$2:$C$23,U24)))),"")} -> TRUE | X24: 134 22 | Y24: =IF(NOT(ISBLANK($C24)),IF(NOT(ISBLANK(X24)),TRUE,FALSE),"") -> TRUE | Z24: {=IF(NOT(ISBLANK($C24)),AND(Y24=TRUE,LEN(X24)<81,NOT(ISNUMBER(FIND('List of Values'!$C$2:$C$23,X24)))),"")} -> TRUE | AA24: SE | AB24: =IF(NOT(ISBLANK($C24)),IF(NOT(ISBLANK(AA24)),TRUE,FALSE),"") -> TRUE | AC24: =IF(NOT(ISBLANK($C24)),AND(AB24=TRUE,NOT(COUNTIF('List of Values'!$B$2:$B$255,AA24)=0)),"") -> TRUE | AD24: SEK | AE24: =IF(NOT(ISBLANK($C24)),IF(NOT(ISBLANK(AD24)),TRUE,FALSE),"") -> TRUE | AF24: =IF(NOT(ISBLANK($C24)),AND(AE24=TRUE,NOT(COUNTIF('List of Values'!$F$2:$F$255,AD24)=0)),"") -> TRUE | AG24: V_30NET | AH24: =IF(NOT(ISBLANK($C24)),IF(NOT(ISBLANK(AG24)),TRUE,FALSE),"") -> TRUE | AI24: =IF(NOT(ISBLANK($C24)),AND(AH24=TRUE,NOT(COUNTIF('List of Values'!$N$2:$N$40,AG24)=0)),"") -> TRUE | AJ24: V_BANK | AK24: =IF(NOT(ISBLANK($C24)),IF(NOT(ISBLANK(AJ24)),TRUE,FALSE),"") -> TRUE | AL24: =IF(NOT(ISBLANK($C24)),AND(AK24=TRUE,NOT(COUNTIF('List of Values'!$O$2:$O$30,AJ24)=0)),"") -> TRUE | AM24: S-DOM | AN24: =IF(NOT(ISBLANK($C24)),IF(NOT(ISBLANK(AM24)),TRUE,FALSE),"") -> TRUE | AO24: =IF(NOT(ISBLANK($C24)),AND(AN24=TRUE,NOT(COUNTIF('List of Values'!$AF$2:$AF$20,AM24)=0)),"") -> TRUE | AQ24: =IF(NOT(ISBLANK($C24)),TRUE,"") -> TRUE | AR24: {=IF(NOT(ISBLANK($C24)),AND(AQ24=TRUE,LEN(AP24)<81,NOT(ISNUMBER(FIND('List of Values'!$C$2:$C$20,AP24)))),"")} -> TRUE | AS24: =D24 -> ADSTRINGO AB | AT24: =IF(NOT(ISBLANK($C24)),IF(NOT(ISBLANK(AS24)),TRUE,FALSE),"") -> TRUE | AU24: {=IF(NOT(ISBLANK($C24)),AND(AT24=TRUE,LEN(AS24)<81,NOT(ISNUMBER(FIND('List of Values'!$C$2:$C$20,AS24)))),"")} -> TRUE | AV24: ADSTRINGOAB | AW24: =IF(NOT(ISBLANK($C24)),IF(NOT(ISBLANK(AV24)),TRUE,FALSE),"") -> TRUE | AX24: {=IF(NOT(ISBLANK($C24)),AND(AW24=TRUE,LEN(AV24)<21,NOT(ISNUMBER(FIND('List of Values'!$C$2:$C$20,AV24)))),"")} -> TRUE | AY24: 10001 | AZ24: =IF(NOT(ISBLANK($C24)),TRUE,"") -> TRUE | BA24: =IF(NOT(ISBLANK($C24)),AND(AZ24=TRUE,NOT(COUNTIF('List of Values'!$R$2:$R$400,AY24)=0)),"") -> TRUE | BC24: =IF(NOT(ISBLANK($C24)),TRUE,"") -> TRUE | BD24: {=IF(NOT(ISBLANK($C24)),OR(ISBLANK(BB24),AND(NOT(ISNUMBER(FIND('List of Values'!$C$2:$C$23,BB24))),ISNUMBER(DATEVALUE(BB24)))),"")} -> TRUE | BF24: =IF(NOT(ISBLANK($C24)),TRUE,"") -> TRUE | BG24: {=IF(NOT(ISBLANK($C24)),OR(ISBLANK(BE24),AND(NOT(ISNUMBER(FIND('List of Values'!$C$2:$C$23,BE24))),ISNUMBER(DATEVALUE(BE24)))),"")} -> TRUE | BI24: =IF(NOT(ISBLANK($C24)),TRUE,"") -> TRUE | BJ24: =IF(NOT(ISBLANK($C24)),OR(ISBLANK(BH24),AND(LEN(BH24)<14,ISNUMBER(BH24))),"") -> TRUE | BK24: Invoice | BL24: =IF(NOT(ISBLANK($C24)),IF(NOT(ISBLANK(BK24)),TRUE,FALSE),"") -> TRUE | BM24: =IF(NOT(ISBLANK($C24)),AND(BL24=TRUE,NOT(COUNTIF('List of Values'!$A$2:$A$20,BK24)=0)),"") -> TRUE | BN24: Active | BO24: =IF(NOT(ISBLANK($C24)),IF(NOT(ISBLANK(BN24)),TRUE,FALSE),"") -> TRUE | BP24: =IF(NOT(ISBLANK($C24)),OR(BN24="active",BN24="delisted"),"") -> TRUE | BR24: =IF(NOT(ISBLANK($C24)),OR(AND($E24="intercompany",NOT(ISBLANK(BQ24))),AND(NOT($E24="intercompany"),ISBLANK(BQ24))),"") -> TRUE | BS24: =IF(NOT(ISBLANK($C24)),OR(ISBLANK(BQ24),NOT(COUNTIF('List of Values'!$K$2:$K$30,BQ24)=0)),"") -> TRUE | BU24: =IF(NOT(ISBLANK($C24)),TRUE,"") -> TRUE | BV24: =IF(NOT(ISBLANK($C24)),OR(ISBLANK(BT24),BT24="duty paid",BT24="bond"),"") -> TRUE | BX24: =IF(NOT(ISBLANK($C24)),TRUE,"") -> TRUE | BY24: =IF(NOT(ISBLANK($C24)),OR(ISBLANK(BW24),BW24="duty paid",BW24="bond"),"") -> TRUE | BZ24: =_xlfn.XLOOKUP(C24,[1]Blad1!$A:$A,[1]Blad1!$D:$D,"")
B25: =COUNTIF(C25:XFD25,"FALSE") -> 0 | C25: 218004 | D25: NORWEGIAN SEAFOOD COMPANY | E25: Trade | F25: NO967791377 | G25: =IF(NOT(ISBLANK($C25)),IF(NOT(ISBLANK(F25)),TRUE,FALSE),"") -> TRUE | H25: {=IF(NOT(ISBLANK($C25)),AND(G25=TRUE,LEN(F25)<30,NOT(ISNUMBER(FIND('List of Values'!$C$2:$C$20,F25)))),"")} -> TRUE | I25: NO967791377 | J25: =IF(NOT(ISBLANK($C25)),TRUE,"") -> TRUE | K25: {=IF(NOT(ISBLANK($C25)),AND(J25=TRUE,LEN(I25)<20,NOT(ISNUMBER(FIND('List of Values'!$C$2:$C$20,I25)))),"")} -> TRUE | L25: BRUNHOLMGT 1 C | M25: =IF(NOT(ISBLANK($C25)),IF(NOT(ISBLANK(L25)),TRUE,FALSE),"") -> TRUE | N25: {=IF(NOT(ISBLANK($C25)),AND(M25=TRUE,LEN(L25)<81,NOT(ISNUMBER(FIND('List of Values'!$C$2:$C$20,L25)))),"")} -> TRUE | P25: =IF(NOT(ISBLANK($C25)),TRUE,"") -> TRUE | Q25: {=IF(NOT(ISBLANK($C25)),AND(P25=TRUE,LEN(O25)<81,NOT(ISNUMBER(FIND('List of Values'!$C$2:$C$20,O25)))),"")} -> TRUE | R25: ÅLESUND | S25: =IF(NOT(ISBLANK($C25)),IF(NOT(ISBLANK(R25)),TRUE,FALSE),"") -> TRUE | T25: {=IF(NOT(ISBLANK($C25)),AND(S25=TRUE,LEN(R25)<61,NOT(ISNUMBER(FIND('List of Values'!$C$2:$C$23,R25)))),"")} -> TRUE | V25: =IF(NOT(ISBLANK($C25)),TRUE,"") -> TRUE | W25: {=IF(NOT(ISBLANK($C25)),AND(V25=TRUE,LEN(U25)<61,NOT(ISNUMBER(FIND('List of Values'!$C$2:$C$23,U25)))),"")} -> TRUE | X25: NO-6001 | Y25: =IF(NOT(ISBLANK($C25)),IF(NOT(ISBLANK(X25)),TRUE,FALSE),"") -> TRUE | Z25: {=IF(NOT(ISBLANK($C25)),AND(Y25=TRUE,LEN(X25)<81,NOT(ISNUMBER(FIND('List of Values'!$C$2:$C$23,X25)))),"")} -> TRUE | AA25: NO | AB25: =IF(NOT(ISBLANK($C25)),IF(NOT(ISBLANK(AA25)),TRUE,FALSE),"") -> TRUE | AC25: =IF(NOT(ISBLANK($C25)),AND(AB25=TRUE,NOT(COUNTIF('List of Values'!$B$2:$B$255,AA25)=0)),"") -> TRUE | AD25: NOK | AE25: =IF(NOT(ISBLANK($C25)),IF(NOT(ISBLANK(AD25)),TRUE,FALSE),"") -> TRUE | AF25: =IF(NOT(ISBLANK($C25)),AND(AE25=TRUE,NOT(COUNTIF('List of Values'!$F$2:$F$255,AD25)=0)),"") -> TRUE | AG25: V_20NET | AH25: =IF(NOT(ISBLANK($C25)),IF(NOT(ISBLANK(AG25)),TRUE,FALSE),"") -> TRUE | AI25: =IF(NOT(ISBLANK($C25)),AND(AH25=TRUE,NOT(COUNTIF('List of Values'!$N$2:$N$40,AG25)=0)),"") -> TRUE | AJ25: V_BANK | AK25: =IF(NOT(ISBLANK($C25)),IF(NOT(ISBLANK(AJ25)),TRUE,FALSE),"") -> TRUE | AL25: =IF(NOT(ISBLANK($C25)),AND(AK25=TRUE,NOT(COUNTIF('List of Values'!$O$2:$O$30,AJ25)=0)),"") -> TRUE | AM25: S-INT | AN25: =IF(NOT(ISBLANK($C25)),IF(NOT(ISBLANK(AM25)),TRUE,FALSE),"") -> TRUE | AO25: =IF(NOT(ISBLANK($C25)),AND(AN25=TRUE,NOT(COUNTIF('List of Values'!$AF$2:$AF$20,AM25)=0)),"") -> TRUE | AQ25: =IF(NOT(ISBLANK($C25)),TRUE,"") -> TRUE | AR25: {=IF(NOT(ISBLANK($C25)),AND(AQ25=TRUE,LEN(AP25)<81,NOT(ISNUMBER(FIND('List of Values'!$C$2:$C$20,AP25)))),"")} -> TRUE | AS25: =D25 -> NORWEGIAN SEAFOOD COMPANY | AT25: =IF(NOT(ISBLANK($C25)),IF(NOT(ISBLANK(AS25)),TRUE,FALSE),"") -> TRUE | AU25: {=IF(NOT(ISBLANK($C25)),AND(AT25=TRUE,LEN(AS25)<81,NOT(ISNUMBER(FIND('List of Values'!$C$2:$C$20,AS25)))),"")} -> TRUE | AV25: NORWEGIANSEAFOODCOMP | AW25: =IF(NOT(ISBLANK($C25)),IF(NOT(ISBLANK(AV25)),TRUE,FALSE),"") -> TRUE | AX25: {=IF(NOT(ISBLANK($C25)),AND(AW25=TRUE,LEN(AV25)<21,NOT(ISNUMBER(FIND('List of Values'!$C$2:$C$20,AV25)))),"")} -> TRUE | AY25: 13697 | AZ25: =IF(NOT(ISBLANK($C25)),TRUE,"") -> TRUE | BA25: =IF(NOT(ISBLANK($C25)),AND(AZ25=TRUE,NOT(COUNTIF('List of Values'!$R$2:$R$400,AY25)=0)),"") -> TRUE | BC25: =IF(NOT(ISBLANK($C25)),TRUE,"") -> TRUE | BD25: {=IF(NOT(ISBLANK($C25)),OR(ISBLANK(BB25),AND(NOT(ISNUMBER(FIND('List of Values'!$C$2:$C$23,BB25))),ISNUMBER(DATEVALUE(BB25)))),"")} -> TRUE | BF25: =IF(NOT(ISBLANK($C25)),TRUE,"") -> TRUE | BG25: {=IF(NOT(ISBLANK($C25)),OR(ISBLANK(BE25),AND(NOT(ISNUMBER(FIND('List of Values'!$C$2:$C$23,BE25))),ISNUMBER(DATEVALUE(BE25)))),"")} -> TRUE | BI25: =IF(NOT(ISBLANK($C25)),TRUE,"") -> TRUE | BJ25: =IF(NOT(ISBLANK($C25)),OR(ISBLANK(BH25),AND(LEN(BH25)<14,ISNUMBER(BH25))),"") -> TRUE | BK25: Invoice | BL25: =IF(NOT(ISBLANK($C25)),IF(NOT(ISBLANK(BK25)),TRUE,FALSE),"") -> TRUE | BM25: =IF(NOT(ISBLANK($C25)),AND(BL25=TRUE,NOT(COUNTIF('List of Values'!$A$2:$A$20,BK25)=0)),"") -> TRUE | BN25: Active | BO25: =IF(NOT(ISBLANK($C25)),IF(NOT(ISBLANK(BN25)),TRUE,FALSE),"") -> TRUE | BP25: =IF(NOT(ISBLANK($C25)),OR(BN25="active",BN25="delisted"),"") -> TRUE | BR25: =IF(NOT(ISBLANK($C25)),OR(AND($E25="intercompany",NOT(ISBLANK(BQ25))),AND(NOT($E25="intercompany"),ISBLANK(BQ25))),"") -> TRUE | BS25: =IF(NOT(ISBLANK($C25)),OR(ISBLANK(BQ25),NOT(COUNTIF('List of Values'!$K$2:$K$30,BQ25)=0)),"") -> TRUE | BU25: =IF(NOT(ISBLANK($C25)),TRUE,"") -> TRUE | BV25: =IF(NOT(ISBLANK($C25)),OR(ISBLANK(BT25),BT25="duty paid",BT25="bond"),"") -> TRUE | BX25: =IF(NOT(ISBLANK($C25)),TRUE,"") -> TRUE | BY25: =IF(NOT(ISBLANK($C25)),OR(ISBLANK(BW25),BW25="duty paid",BW25="bond"),"") -> TRUE | BZ25: =_xlfn.XLOOKUP(C25,[1]Blad1!$A:$A,[1]Blad1!$D:$D,"")
B26: =COUNTIF(C26:XFD26,"FALSE") -> 0 | C26: 218050 | D26: LAGERSTEDTS BILSERVICE AB | E26: Indirect | F26: 5562507581 | G26: =IF(NOT(ISBLANK($C26)),IF(NOT(ISBLANK(F26)),TRUE,FALSE),"") -> TRUE | H26: {=IF(NOT(ISBLANK($C26)),AND(G26=TRUE,LEN(F26)<30,NOT(ISNUMBER(FIND('List of Values'!$C$2:$C$20,F26)))),"")} -> TRUE | I26: SE556250758101 | J26: =IF(NOT(ISBLANK($C26)),TRUE,"") -> TRUE | K26: {=IF(NOT(ISBLANK($C26)),AND(J26=TRUE,LEN(I26)<20,NOT(ISNUMBER(FIND('List of Values'!$C$2:$C$20,I26)))),"")} -> TRUE | L26: BOX 2136 | M26: =IF(NOT(ISBLANK($C26)),IF(NOT(ISBLANK(L26)),TRUE,FALSE),"") -> TRUE | N26: {=IF(NOT(ISBLANK($C26)),AND(M26=TRUE,LEN(L26)<81,NOT(ISNUMBER(FIND('List of Values'!$C$2:$C$20,L26)))),"")} -> TRUE | P26: =IF(NOT(ISBLANK($C26)),TRUE,"") -> TRUE | Q26: {=IF(NOT(ISBLANK($C26)),AND(P26=TRUE,LEN(O26)<81,NOT(ISNUMBER(FIND('List of Values'!$C$2:$C$20,O26)))),"")} -> TRUE | R26: SKARPNÄCK | S26: =IF(NOT(ISBLANK($C26)),IF(NOT(ISBLANK(R26)),TRUE,FALSE),"") -> TRUE | T26: {=IF(NOT(ISBLANK($C26)),AND(S26=TRUE,LEN(R26)<61,NOT(ISNUMBER(FIND('List of Values'!$C$2:$C$23,R26)))),"")} -> TRUE | V26: =IF(NOT(ISBLANK($C26)),TRUE,"") -> TRUE | W26: {=IF(NOT(ISBLANK($C26)),AND(V26=TRUE,LEN(U26)<61,NOT(ISNUMBER(FIND('List of Values'!$C$2:$C$23,U26)))),"")} -> TRUE | X26: 128 23 | Y26: =IF(NOT(ISBLANK($C26)),IF(NOT(ISBLANK(X26)),TRUE,FALSE),"") -> TRUE | Z26: {=IF(NOT(ISBLANK($C26)),AND(Y26=TRUE,LEN(X26)<81,NOT(ISNUMBER(FIND('List of Values'!$C$2:$C$23,X26)))),"")} -> TRUE | AA26: SE | AB26: =IF(NOT(ISBLANK($C26)),IF(NOT(ISBLANK(AA26)),TRUE,FALSE),"") -> TRUE | AC26: =IF(NOT(ISBLANK($C26)),AND(AB26=TRUE,NOT(COUNTIF('List of Values'!$B$2:$B$255,AA26)=0)),"") -> TRUE | AD26: SEK | AE26: =IF(NOT(ISBLANK($C26)),IF(NOT(ISBLANK(AD26)),TRUE,FALSE),"") -> TRUE | AF26: =IF(NOT(ISBLANK($C26)),AND(AE26=TRUE,NOT(COUNTIF('List of Values'!$F$2:$F$255,AD26)=0)),"") -> TRUE | AG26: V_20NET | AH26: =IF(NOT(ISBLANK($C26)),IF(NOT(ISBLANK(AG26)),TRUE,FALSE),"") -> TRUE | AI26: =IF(NOT(ISBLANK($C26)),AND(AH26=TRUE,NOT(COUNTIF('List of Values'!$N$2:$N$40,AG26)=0)),"") -> TRUE | AJ26: V_BANK | AK26: =IF(NOT(ISBLANK($C26)),IF(NOT(ISBLANK(AJ26)),TRUE,FALSE),"") -> TRUE | AL26: =IF(NOT(ISBLANK($C26)),AND(AK26=TRUE,NOT(COUNTIF('List of Values'!$O$2:$O$30,AJ26)=0)),"") -> TRUE | AM26: S-DOM | AN26: =IF(NOT(ISBLANK($C26)),IF(NOT(ISBLANK(AM26)),TRUE,FALSE),"") -> TRUE | AO26: =IF(NOT(ISBLANK($C26)),AND(AN26=TRUE,NOT(COUNTIF('List of Values'!$AF$2:$AF$20,AM26)=0)),"") -> TRUE | AQ26: =IF(NOT(ISBLANK($C26)),TRUE,"") -> TRUE | AR26: {=IF(NOT(ISBLANK($C26)),AND(AQ26=TRUE,LEN(AP26)<81,NOT(ISNUMBER(FIND('List of Values'!$C$2:$C$20,AP26)))),"")} -> TRUE | AS26: =D26 -> LAGERSTEDTS BILSERVICE AB | AT26: =IF(NOT(ISBLANK($C26)),IF(NOT(ISBLANK(AS26)),TRUE,FALSE),"") -> TRUE | AU26: {=IF(NOT(ISBLANK($C26)),AND(AT26=TRUE,LEN(AS26)<81,NOT(ISNUMBER(FIND('List of Values'!$C$2:$C$20,AS26)))),"")} -> TRUE | AV26: LAGERSTEDTSBILSERVIC | AW26: =IF(NOT(ISBLANK($C26)),IF(NOT(ISBLANK(AV26)),TRUE,FALSE),"") -> TRUE | AX26: {=IF(NOT(ISBLANK($C26)),AND(AW26=TRUE,LEN(AV26)<21,NOT(ISNUMBER(FIND('List of Values'!$C$2:$C$20,AV26)))),"")} -> TRUE | AY26: 10001 | AZ26: =IF(NOT(ISBLANK($C26)),TRUE,"") -> TRUE | BA26: =IF(NOT(ISBLANK($C26)),AND(AZ26=TRUE,NOT(COUNTIF('List of Values'!$R$2:$R$400,AY26)=0)),"") -> TRUE | BC26: =IF(NOT(ISBLANK($C26)),TRUE,"") -> TRUE | BD26: {=IF(NOT(ISBLANK($C26)),OR(ISBLANK(BB26),AND(NOT(ISNUMBER(FIND('List of Values'!$C$2:$C$23,BB26))),ISNUMBER(DATEVALUE(BB26)))),"")} -> TRUE | BF26: =IF(NOT(ISBLANK($C26)),TRUE,"") -> TRUE | BG26: {=IF(NOT(ISBLANK($C26)),OR(ISBLANK(BE26),AND(NOT(ISNUMBER(FIND('List of Values'!$C$2:$C$23,BE26))),ISNUMBER(DATEVALUE(BE26)))),"")} -> TRUE | BI26: =IF(NOT(ISBLANK($C26)),TRUE,"") -> TRUE | BJ26: =IF(NOT(ISBLANK($C26)),OR(ISBLANK(BH26),AND(LEN(BH26)<14,ISNUMBER(BH26))),"") -> TRUE | BK26: Invoice | BL26: =IF(NOT(ISBLANK($C26)),IF(NOT(ISBLANK(BK26)),TRUE,FALSE),"") -> TRUE | BM26: =IF(NOT(ISBLANK($C26)),AND(BL26=TRUE,NOT(COUNTIF('List of Values'!$A$2:$A$20,BK26)=0)),"") -> TRUE | BN26: Active | BO26: =IF(NOT(ISBLANK($C26)),IF(NOT(ISBLANK(BN26)),TRUE,FALSE),"") -> TRUE | BP26: =IF(NOT(ISBLANK($C26)),OR(BN26="active",BN26="delisted"),"") -> TRUE | BR26: =IF(NOT(ISBLANK($C26)),OR(AND($E26="intercompany",NOT(ISBLANK(BQ26))),AND(NOT($E26="intercompany"),ISBLANK(BQ26))),"") -> TRUE | BS26: =IF(NOT(ISBLANK($C26)),OR(ISBLANK(BQ26),NOT(COUNTIF('List of Values'!$K$2:$K$30,BQ26)=0)),"") -> TRUE | BU26: =IF(NOT(ISBLANK($C26)),TRUE,"") -> TRUE | BV26: =IF(NOT(ISBLANK($C26)),OR(ISBLANK(BT26),BT26="duty paid",BT26="bond"),"") -> TRUE | BX26: =IF(NOT(ISBLANK($C26)),TRUE,"") -> TRUE | BY26: =IF(NOT(ISBLANK($C26)),OR(ISBLANK(BW26),BW26="duty paid",BW26="bond"),"") -> TRUE | BZ26: =_xlfn.XLOOKUP(C26,[1]Blad1!$A:$A,[1]Blad1!$D:$D,"")
B27: =COUNTIF(C27:XFD27,"FALSE") -> 0 | C27: 218026 | D27: SEB TRYGG-LIV | E27: Indirect | F27: 5164018243 | G27: =IF(NOT(ISBLANK($C27)),IF(NOT(ISBLANK(F27)),TRUE,FALSE),"") -> TRUE | H27: {=IF(NOT(ISBLANK($C27)),AND(G27=TRUE,LEN(F27)<30,NOT(ISNUMBER(FIND('List of Values'!$C$2:$C$20,F27)))),"")} -> TRUE | I27: SE516401824301 | J27: =IF(NOT(ISBLANK($C27)),TRUE,"") -> TRUE | K27: {=IF(NOT(ISBLANK($C27)),AND(J27=TRUE,LEN(I27)<20,NOT(ISNUMBER(FIND('List of Values'!$C$2:$C$20,I27)))),"")} -> TRUE | L27: UNAVAILABLE | M27: =IF(NOT(ISBLANK($C27)),IF(NOT(ISBLANK(L27)),TRUE,FALSE),"") -> TRUE | N27: {=IF(NOT(ISBLANK($C27)),AND(M27=TRUE,LEN(L27)<81,NOT(ISNUMBER(FIND('List of Values'!$C$2:$C$20,L27)))),"")} -> TRUE | P27: =IF(NOT(ISBLANK($C27)),TRUE,"") -> TRUE | Q27: {=IF(NOT(ISBLANK($C27)),AND(P27=TRUE,LEN(O27)<81,NOT(ISNUMBER(FIND('List of Values'!$C$2:$C$20,O27)))),"")} -> TRUE | R27: STOCKHOLM | S27: =IF(NOT(ISBLANK($C27)),IF(NOT(ISBLANK(R27)),TRUE,FALSE),"") -> TRUE | T27: {=IF(NOT(ISBLANK($C27)),AND(S27=TRUE,LEN(R27)<61,NOT(ISNUMBER(FIND('List of Values'!$C$2:$C$23,R27)))),"")} -> TRUE | V27: =IF(NOT(ISBLANK($C27)),TRUE,"") -> TRUE | W27: {=IF(NOT(ISBLANK($C27)),AND(V27=TRUE,LEN(U27)<61,NOT(ISNUMBER(FIND('List of Values'!$C$2:$C$23,U27)))),"")} -> TRUE | X27: 106 40 | Y27: =IF(NOT(ISBLANK($C27)),IF(NOT(ISBLANK(X27)),TRUE,FALSE),"") -> TRUE | Z27: {=IF(NOT(ISBLANK($C27)),AND(Y27=TRUE,LEN(X27)<81,NOT(ISNUMBER(FIND('List of Values'!$C$2:$C$23,X27)))),"")} -> TRUE | AA27: SE | AB27: =IF(NOT(ISBLANK($C27)),IF(NOT(ISBLANK(AA27)),TRUE,FALSE),"") -> TRUE | AC27: =IF(NOT(ISBLANK($C27)),AND(AB27=TRUE,NOT(COUNTIF('List of Values'!$B$2:$B$255,AA27)=0)),"") -> TRUE | AD27: SEK | AE27: =IF(NOT(ISBLANK($C27)),IF(NOT(ISBLANK(AD27)),TRUE,FALSE),"") -> TRUE | AF27: =IF(NOT(ISBLANK($C27)),AND(AE27=TRUE,NOT(COUNTIF('List of Values'!$F$2:$F$255,AD27)=0)),"") -> TRUE | AG27: V_30NET | AH27: =IF(NOT(ISBLANK($C27)),IF(NOT(ISBLANK(AG27)),TRUE,FALSE),"") -> TRUE | AI27: =IF(NOT(ISBLANK($C27)),AND(AH27=TRUE,NOT(COUNTIF('List of Values'!$N$2:$N$40,AG27)=0)),"") -> TRUE | AJ27: V_BANK | AK27: =IF(NOT(ISBLANK($C27)),IF(NOT(ISBLANK(AJ27)),TRUE,FALSE),"") -> TRUE | AL27: =IF(NOT(ISBLANK($C27)),AND(AK27=TRUE,NOT(COUNTIF('List of Values'!$O$2:$O$30,AJ27)=0)),"") -> TRUE | AM27: S-DOM | AN27: =IF(NOT(ISBLANK($C27)),IF(NOT(ISBLANK(AM27)),TRUE,FALSE),"") -> TRUE | AO27: =IF(NOT(ISBLANK($C27)),AND(AN27=TRUE,NOT(COUNTIF('List of Values'!$AF$2:$AF$20,AM27)=0)),"") -> TRUE | AQ27: =IF(NOT(ISBLANK($C27)),TRUE,"") -> TRUE | AR27: {=IF(NOT(ISBLANK($C27)),AND(AQ27=TRUE,LEN(AP27)<81,NOT(ISNUMBER(FIND('List of Values'!$C$2:$C$20,AP27)))),"")} -> TRUE | AS27: =D27 -> SEB TRYGG-LIV | AT27: =IF(NOT(ISBLANK($C27)),IF(NOT(ISBLANK(AS27)),TRUE,FALSE),"") -> TRUE | AU27: {=IF(NOT(ISBLANK($C27)),AND(AT27=TRUE,LEN(AS27)<81,NOT(ISNUMBER(FIND('List of Values'!$C$2:$C$20,AS27)))),"")} -> TRUE | AV27: SEBTRYGG-LIV | AW27: =IF(NOT(ISBLANK($C27)),IF(NOT(ISBLANK(AV27)),TRUE,FALSE),"") -> TRUE | AX27: {=IF(NOT(ISBLANK($C27)),AND(AW27=TRUE,LEN(AV27)<21,NOT(ISNUMBER(FIND('List of Values'!$C$2:$C$20,AV27)))),"")} -> TRUE | AY27: 10001 | AZ27: =IF(NOT(ISBLANK($C27)),TRUE,"") -> TRUE | BA27: =IF(NOT(ISBLANK($C27)),AND(AZ27=TRUE,NOT(COUNTIF('List of Values'!$R$2:$R$400,AY27)=0)),"") -> TRUE | BC27: =IF(NOT(ISBLANK($C27)),TRUE,"") -> TRUE | BD27: {=IF(NOT(ISBLANK($C27)),OR(ISBLANK(BB27),AND(NOT(ISNUMBER(FIND('List of Values'!$C$2:$C$23,BB27))),ISNUMBER(DATEVALUE(BB27)))),"")} -> TRUE | BF27: =IF(NOT(ISBLANK($C27)),TRUE,"") -> TRUE | BG27: {=IF(NOT(ISBLANK($C27)),OR(ISBLANK(BE27),AND(NOT(ISNUMBER(FIND('List of Values'!$C$2:$C$23,BE27))),ISNUMBER(DATEVALUE(BE27)))),"")} -> TRUE | BI27: =IF(NOT(ISBLANK($C27)),TRUE,"") -> TRUE | BJ27: =IF(NOT(ISBLANK($C27)),OR(ISBLANK(BH27),AND(LEN(BH27)<14,ISNUMBER(BH27))),"") -> TRUE | BK27: Invoice | BL27: =IF(NOT(ISBLANK($C27)),IF(NOT(ISBLANK(BK27)),TRUE,FALSE),"") -> TRUE | BM27: =IF(NOT(ISBLANK($C27)),AND(BL27=TRUE,NOT(COUNTIF('List of Values'!$A$2:$A$20,BK27)=0)),"") -> TRUE | BN27: Active | BO27: =IF(NOT(ISBLANK($C27)),IF(NOT(ISBLANK(BN27)),TRUE,FALSE),"") -> TRUE | BP27: =IF(NOT(ISBLANK($C27)),OR(BN27="active",BN27="delisted"),"") -> TRUE | BR27: =IF(NOT(ISBLANK($C27)),OR(AND($E27="intercompany",NOT(ISBLANK(BQ27))),AND(NOT($E27="intercompany"),ISBLANK(BQ27))),"") -> TRUE | BS27: =IF(NOT(ISBLANK($C27)),OR(ISBLANK(BQ27),NOT(COUNTIF('List of Values'!$K$2:$K$30,BQ27)=0)),"") -> TRUE | BU27: =IF(NOT(ISBLANK($C27)),TRUE,"") -> TRUE | BV27: =IF(NOT(ISBLANK($C27)),OR(ISBLANK(BT27),BT27="duty paid",BT27="bond"),"") -> TRUE | BX27: =IF(NOT(ISBLANK($C27)),TRUE,"") -> TRUE | BY27: =IF(NOT(ISBLANK($C27)),OR(ISBLANK(BW27),BW27="duty paid",BW27="bond"),"") -> TRUE | BZ27: =_xlfn.XLOOKUP(C27,[1]Blad1!$A:$A,[1]Blad1!$D:$D,"")
B28: =COUNTIF(C28:XFD28,"FALSE") -> 0 | C28: 218056 | D28: TELE2 SVERIGE AB | E28: Indirect | F28: 5562675164 | G28: =IF(NOT(ISBLANK($C28)),IF(NOT(ISBLANK(F28)),TRUE,FALSE),"") -> TRUE | H28: {=IF(NOT(ISBLANK($C28)),AND(G28=TRUE,LEN(F28)<30,NOT(ISNUMBER(FIND('List of Values'!$C$2:$C$20,F28)))),"")} -> TRUE | I28: SE556267516401 | J28: =IF(NOT(ISBLANK($C28)),TRUE,"") -> TRUE | K28: {=IF(NOT(ISBLANK($C28)),AND(J28=TRUE,LEN(I28)<20,NOT(ISNUMBER(FIND('List of Values'!$C$2:$C$20,I28)))),"")} -> TRUE | L28: PLÅTVÄGEN 14 | M28: =IF(NOT(ISBLANK($C28)),IF(NOT(ISBLANK(L28)),TRUE,FALSE),"") -> TRUE | N28: {=IF(NOT(ISBLANK($C28)),AND(M28=TRUE,LEN(L28)<81,NOT(ISNUMBER(FIND('List of Values'!$C$2:$C$20,L28)))),"")} -> TRUE | P28: =IF(NOT(ISBLANK($C28)),TRUE,"") -> TRUE | Q28: {=IF(NOT(ISBLANK($C28)),AND(P28=TRUE,LEN(O28)<81,NOT(ISNUMBER(FIND('List of Values'!$C$2:$C$20,O28)))),"")} -> TRUE | R28: KARLSKOGA | S28: =IF(NOT(ISBLANK($C28)),IF(NOT(ISBLANK(R28)),TRUE,FALSE),"") -> TRUE | T28: {=IF(NOT(ISBLANK($C28)),AND(S28=TRUE,LEN(R28)<61,NOT(ISNUMBER(FIND('List of Values'!$C$2:$C$23,R28)))),"")} -> TRUE | V28: =IF(NOT(ISBLANK($C28)),TRUE,"") -> TRUE | W28: {=IF(NOT(ISBLANK($C28)),AND(V28=TRUE,LEN(U28)<61,NOT(ISNUMBER(FIND('List of Values'!$C$2:$C$23,U28)))),"")} -> TRUE | X28: 691 50 | Y28: =IF(NOT(ISBLANK($C28)),IF(NOT(ISBLANK(X28)),TRUE,FALSE),"") -> TRUE | Z28: {=IF(NOT(ISBLANK($C28)),AND(Y28=TRUE,LEN(X28)<81,NOT(ISNUMBER(FIND('List of Values'!$C$2:$C$23,X28)))),"")} -> TRUE | AA28: SE | AB28: =IF(NOT(ISBLANK($C28)),IF(NOT(ISBLANK(AA28)),TRUE,FALSE),"") -> TRUE | AC28: =IF(NOT(ISBLANK($C28)),AND(AB28=TRUE,NOT(COUNTIF('List of Values'!$B$2:$B$255,AA28)=0)),"") -> TRUE | AD28: SEK | AE28: =IF(NOT(ISBLANK($C28)),IF(NOT(ISBLANK(AD28)),TRUE,FALSE),"") -> TRUE | AF28: =IF(NOT(ISBLANK($C28)),AND(AE28=TRUE,NOT(COUNTIF('List of Values'!$F$2:$F$255,AD28)=0)),"") -> TRUE | AG28: V_10EOM | AH28: =IF(NOT(ISBLANK($C28)),IF(NOT(ISBLANK(AG28)),TRUE,FALSE),"") -> TRUE | AI28: =IF(NOT(ISBLANK($C28)),AND(AH28=TRUE,NOT(COUNTIF('List of Values'!$N$2:$N$40,AG28)=0)),"") -> TRUE | AJ28: V_BANK | AK28: =IF(NOT(ISBLANK($C28)),IF(NOT(ISBLANK(AJ28)),TRUE,FALSE),"") -> TRUE | AL28: =IF(NOT(ISBLANK($C28)),AND(AK28=TRUE,NOT(COUNTIF('List of Values'!$O$2:$O$30,AJ28)=0)),"") -> TRUE | AM28: S-DOM | AN28: =IF(NOT(ISBLANK($C28)),IF(NOT(ISBLANK(AM28)),TRUE,FALSE),"") -> TRUE | AO28: =IF(NOT(ISBLANK($C28)),AND(AN28=TRUE,NOT(COUNTIF('List of Values'!$AF$2:$AF$20,AM28)=0)),"") -> TRUE | AQ28: =IF(NOT(ISBLANK($C28)),TRUE,"") -> TRUE | AR28: {=IF(NOT(ISBLANK($C28)),AND(AQ28=TRUE,LEN(AP28)<81,NOT(ISNUMBER(FIND('List of Values'!$C$2:$C$20,AP28)))),"")} -> TRUE | AS28: =D28 -> TELE2 SVERIGE AB | AT28: =IF(NOT(ISBLANK($C28)),IF(NOT(ISBLANK(AS28)),TRUE,FALSE),"") -> TRUE | AU28: {=IF(NOT(ISBLANK($C28)),AND(AT28=TRUE,LEN(AS28)<81,NOT(ISNUMBER(FIND('List of Values'!$C$2:$C$20,AS28)))),"")} -> TRUE | AV28: TELE2 | AW28: =IF(NOT(ISBLANK($C28)),IF(NOT(ISBLANK(AV28)),TRUE,FALSE),"") -> TRUE | AX28: {=IF(NOT(ISBLANK($C28)),AND(AW28=TRUE,LEN(AV28)<21,NOT(ISNUMBER(FIND('List of Values'!$C$2:$C$20,AV28)))),"")} -> TRUE | AY28: 10001 | AZ28: =IF(NOT(ISBLANK($C28)),TRUE,"") -> TRUE | BA28: =IF(NOT(ISBLANK($C28)),AND(AZ28=TRUE,NOT(COUNTIF('List of Values'!$R$2:$R$400,AY28)=0)),"") -> TRUE | BC28: =IF(NOT(ISBLANK($C28)),TRUE,"") -> TRUE | BD28: {=IF(NOT(ISBLANK($C28)),OR(ISBLANK(BB28),AND(NOT(ISNUMBER(FIND('List of Values'!$C$2:$C$23,BB28))),ISNUMBER(DATEVALUE(BB28)))),"")} -> TRUE | BF28: =IF(NOT(ISBLANK($C28)),TRUE,"") -> TRUE | BG28: {=IF(NOT(ISBLANK($C28)),OR(ISBLANK(BE28),AND(NOT(ISNUMBER(FIND('List of Values'!$C$2:$C$23,BE28))),ISNUMBER(DATEVALUE(BE28)))),"")} -> TRUE | BI28: =IF(NOT(ISBLANK($C28)),TRUE,"") -> TRUE | BJ28: =IF(NOT(ISBLANK($C28)),OR(ISBLANK(BH28),AND(LEN(BH28)<14,ISNUMBER(BH28))),"") -> TRUE | BK28: Invoice | BL28: =IF(NOT(ISBLANK($C28)),IF(NOT(ISBLANK(BK28)),TRUE,FALSE),"") -> TRUE | BM28: =IF(NOT(ISBLANK($C28)),AND(BL28=TRUE,NOT(COUNTIF('List of Values'!$A$2:$A$20,BK28)=0)),"") -> TRUE | BN28: Delisted | BO28: =IF(NOT(ISBLANK($C28)),IF(NOT(ISBLANK(BN28)),TRUE,FALSE),"") -> TRUE | BP28: =IF(NOT(ISBLANK($C28)),OR(BN28="active",BN28="delisted"),"") -> TRUE | BR28: =IF(NOT(ISBLANK($C28)),OR(AND($E28="intercompany",NOT(ISBLANK(BQ28))),AND(NOT($E28="intercompany"),ISBLANK(BQ28))),"") -> TRUE | BS28: =IF(NOT(ISBLANK($C28)),OR(ISBLANK(BQ28),NOT(COUNTIF('List of Values'!$K$2:$K$30,BQ28)=0)),"") -> TRUE | BU28: =IF(NOT(ISBLANK($C28)),TRUE,"") -> TRUE | BV28: =IF(NOT(ISBLANK($C28)),OR(ISBLANK(BT28),BT28="duty paid",BT28="bond"),"") -> TRUE | BX28: =IF(NOT(ISBLANK($C28)),TRUE,"") -> TRUE | BY28: =IF(NOT(ISBLANK($C28)),OR(ISBLANK(BW28),BW28="duty paid",BW28="bond"),"") -> TRUE | BZ28: =_xlfn.XLOOKUP(C28,[1]Blad1!$A:$A,[1]Blad1!$D:$D,"")
B29: =COUNTIF(C29:XFD29,"FALSE") -> 0 | C29: 217975 | D29: STOCKHOLMS FISKAUKTION | E29: Trade | F29: 5590192737 | G29: =IF(NOT(ISBLANK($C29)),IF(NOT(ISBLANK(F29)),TRUE,FALSE),"") -> TRUE | H29: {=IF(NOT(ISBLANK($C29)),AND(G29=TRUE,LEN(F29)<30,NOT(ISNUMBER(FIND('List of Values'!$C$2:$C$20,F29)))),"")} -> TRUE | I29: SE559019273701 | J29: =IF(NOT(ISBLANK($C29)),TRUE,"") -> TRUE | K29: {=IF(NOT(ISBLANK($C29)),AND(J29=TRUE,LEN(I29)<20,NOT(ISNUMBER(FIND('List of Values'!$C$2:$C$20,I29)))),"")} -> TRUE | L29: FISKHALLSVÄGEN 4 | M29: =IF(NOT(ISBLANK($C29)),IF(NOT(ISBLANK(L29)),TRUE,FALSE),"") -> TRUE | N29: {=IF(NOT(ISBLANK($C29)),AND(M29=TRUE,LEN(L29)<81,NOT(ISNUMBER(FIND('List of Values'!$C$2:$C$20,L29)))),"")} -> TRUE | P29: =IF(NOT(ISBLANK($C29)),TRUE,"") -> TRUE | Q29: {=IF(NOT(ISBLANK($C29)),AND(P29=TRUE,LEN(O29)<81,NOT(ISNUMBER(FIND('List of Values'!$C$2:$C$20,O29)))),"")} -> TRUE | R29: ÅRSTA | S29: =IF(NOT(ISBLANK($C29)),IF(NOT(ISBLANK(R29)),TRUE,FALSE),"") -> TRUE | T29: {=IF(NOT(ISBLANK($C29)),AND(S29=TRUE,LEN(R29)<61,NOT(ISNUMBER(FIND('List of Values'!$C$2:$C$23,R29)))),"")} -> TRUE | V29: =IF(NOT(ISBLANK($C29)),TRUE,"") -> TRUE | W29: {=IF(NOT(ISBLANK($C29)),AND(V29=TRUE,LEN(U29)<61,NOT(ISNUMBER(FIND('List of Values'!$C$2:$C$23,U29)))),"")} -> TRUE | X29: 120 44 | Y29: =IF(NOT(ISBLANK($C29)),IF(NOT(ISBLANK(X29)),TRUE,FALSE),"") -> TRUE | Z29: {=IF(NOT(ISBLANK($C29)),AND(Y29=TRUE,LEN(X29)<81,NOT(ISNUMBER(FIND('List of Values'!$C$2:$C$23,X29)))),"")} -> TRUE | AA29: SE | AB29: =IF(NOT(ISBLANK($C29)),IF(NOT(ISBLANK(AA29)),TRUE,FALSE),"") -> TRUE | AC29: =IF(NOT(ISBLANK($C29)),AND(AB29=TRUE,NOT(COUNTIF('List of Values'!$B$2:$B$255,AA29)=0)),"") -> TRUE | AD29: SEK | AE29: =IF(NOT(ISBLANK($C29)),IF(NOT(ISBLANK(AD29)),TRUE,FALSE),"") -> TRUE | AF29: =IF(NOT(ISBLANK($C29)),AND(AE29=TRUE,NOT(COUNTIF('List of Values'!$F$2:$F$255,AD29)=0)),"") -> TRUE | AG29: V_30NET | AH29: =IF(NOT(ISBLANK($C29)),IF(NOT(ISBLANK(AG29)),TRUE,FALSE),"") -> TRUE | AI29: =IF(NOT(ISBLANK($C29)),AND(AH29=TRUE,NOT(COUNTIF('List of Values'!$N$2:$N$40,AG29)=0)),"") -> TRUE | AJ29: V_BANK | AK29: =IF(NOT(ISBLANK($C29)),IF(NOT(ISBLANK(AJ29)),TRUE,FALSE),"") -> TRUE | AL29: =IF(NOT(ISBLANK($C29)),AND(AK29=TRUE,NOT(COUNTIF('List of Values'!$O$2:$O$30,AJ29)=0)),"") -> TRUE | AM29: S-DOM | AN29: =IF(NOT(ISBLANK($C29)),IF(NOT(ISBLANK(AM29)),TRUE,FALSE),"") -> TRUE | AO29: =IF(NOT(ISBLANK($C29)),AND(AN29=TRUE,NOT(COUNTIF('List of Values'!$AF$2:$AF$20,AM29)=0)),"") -> TRUE | AQ29: =IF(NOT(ISBLANK($C29)),TRUE,"") -> TRUE | AR29: {=IF(NOT(ISBLANK($C29)),AND(AQ29=TRUE,LEN(AP29)<81,NOT(ISNUMBER(FIND('List of Values'!$C$2:$C$20,AP29)))),"")} -> TRUE | AS29: =D29 -> STOCKHOLMS FISKAUKTION | AT29: =IF(NOT(ISBLANK($C29)),IF(NOT(ISBLANK(AS29)),TRUE,FALSE),"") -> TRUE | AU29: {=IF(NOT(ISBLANK($C29)),AND(AT29=TRUE,LEN(AS29)<81,NOT(ISNUMBER(FIND('List of Values'!$C$2:$C$20,AS29)))),"")} -> TRUE | AV29: STOCKHOLMSFISKAUKTIO | AW29: =IF(NOT(ISBLANK($C29)),IF(NOT(ISBLANK(AV29)),TRUE,FALSE),"") -> TRUE | AX29: {=IF(NOT(ISBLANK($C29)),AND(AW29=TRUE,LEN(AV29)<21,NOT(ISNUMBER(FIND('List of Values'!$C$2:$C$20,AV29)))),"")} -> TRUE | AY29: 14804 | AZ29: =IF(NOT(ISBLANK($C29)),TRUE,"") -> TRUE | BA29: =IF(NOT(ISBLANK($C29)),AND(AZ29=TRUE,NOT(COUNTIF('List of Values'!$R$2:$R$400,AY29)=0)),"") -> TRUE | BC29: =IF(NOT(ISBLANK($C29)),TRUE,"") -> TRUE | BD29: {=IF(NOT(ISBLANK($C29)),OR(ISBLANK(BB29),AND(NOT(ISNUMBER(FIND('List of Values'!$C$2:$C$23,BB29))),ISNUMBER(DATEVALUE(BB29)))),"")} -> TRUE | BF29: =IF(NOT(ISBLANK($C29)),TRUE,"") -> TRUE | BG29: {=IF(NOT(ISBLANK($C29)),OR(ISBLANK(BE29),AND(NOT(ISNUMBER(FIND('List of Values'!$C$2:$C$23,BE29))),ISNUMBER(DATEVALUE(BE29)))),"")} -> TRUE | BI29: =IF(NOT(ISBLANK($C29)),TRUE,"") -> TRUE | BJ29: =IF(NOT(ISBLANK($C29)),OR(ISBLANK(BH29),AND(LEN(BH29)<14,ISNUMBER(BH29))),"") -> TRUE | BK29: Invoice | BL29: =IF(NOT(ISBLANK($C29)),IF(NOT(ISBLANK(BK29)),TRUE,FALSE),"") -> TRUE | BM29: =IF(NOT(ISBLANK($C29)),AND(BL29=TRUE,NOT(COUNTIF('List of Values'!$A$2:$A$20,BK29)=0)),"") -> TRUE | BN29: Active | BO29: =IF(NOT(ISBLANK($C29)),IF(NOT(ISBLANK(BN29)),TRUE,FALSE),"") -> TRUE | BP29: =IF(NOT(ISBLANK($C29)),OR(BN29="active",BN29="delisted"),"") -> TRUE | BR29: =IF(NOT(ISBLANK($C29)),OR(AND($E29="intercompany",NOT(ISBLANK(BQ29))),AND(NOT($E29="intercompany"),ISBLANK(BQ29))),"") -> TRUE | BS29: =IF(NOT(ISBLANK($C29)),OR(ISBLANK(BQ29),NOT(COUNTIF('List of Values'!$K$2:$K$30,BQ29)=0)),"") -> TRUE | BU29: =IF(NOT(ISBLANK($C29)),TRUE,"") -> TRUE | BV29: =IF(NOT(ISBLANK($C29)),OR(ISBLANK(BT29),BT29="duty paid",BT29="bond"),"") -> TRUE | BX29: =IF(NOT(ISBLANK($C29)),TRUE,"") -> TRUE | BY29: =IF(NOT(ISBLANK($C29)),OR(ISBLANK(BW29),BW29="duty paid",BW29="bond"),"") -> TRUE | BZ29: =_xlfn.XLOOKUP(C29,[1]Blad1!$A:$A,[1]Blad1!$D:$D,"") -> x
B30: =COUNTIF(C30:XFD30,"FALSE") -> 0 | C30: 217967 | D30: SERVICESTYCKARNA AB | E30: Trade | F30: 5567233514 | G30: =IF(NOT(ISBLANK($C30)),IF(NOT(ISBLANK(F30)),TRUE,FALSE),"") -> TRUE | H30: {=IF(NOT(ISBLANK($C30)),AND(G30=TRUE,LEN(F30)<30,NOT(ISNUMBER(FIND('List of Values'!$C$2:$C$20,F30)))),"")} -> TRUE | I30: SE556723351401 | J30: =IF(NOT(ISBLANK($C30)),TRUE,"") -> TRUE | K30: {=IF(NOT(ISBLANK($C30)),AND(J30=TRUE,LEN(I30)<20,NOT(ISNUMBER(FIND('List of Values'!$C$2:$C$20,I30)))),"")} -> TRUE | L30: BOSKAPSVÄGEN 24-26 | M30: =IF(NOT(ISBLANK($C30)),IF(NOT(ISBLANK(L30)),TRUE,FALSE),"") -> TRUE | N30: {=IF(NOT(ISBLANK($C30)),AND(M30=TRUE,LEN(L30)<81,NOT(ISNUMBER(FIND('List of Values'!$C$2:$C$20,L30)))),"")} -> TRUE | P30: =IF(NOT(ISBLANK($C30)),TRUE,"") -> TRUE | Q30: {=IF(NOT(ISBLANK($C30)),AND(P30=TRUE,LEN(O30)<81,NOT(ISNUMBER(FIND('List of Values'!$C$2:$C$20,O30)))),"")} -> TRUE | R30: JOHANNESHOV | S30: =IF(NOT(ISBLANK($C30)),IF(NOT(ISBLANK(R30)),TRUE,FALSE),"") -> TRUE | T30: {=IF(NOT(ISBLANK($C30)),AND(S30=TRUE,LEN(R30)<61,NOT(ISNUMBER(FIND('List of Values'!$C$2:$C$23,R30)))),"")} -> TRUE | V30: =IF(NOT(ISBLANK($C30)),TRUE,"") -> TRUE | W30: {=IF(NOT(ISBLANK($C30)),AND(V30=TRUE,LEN(U30)<61,NOT(ISNUMBER(FIND('List of Values'!$C$2:$C$23,U30)))),"")} -> TRUE | X30: 121 62 | Y30: =IF(NOT(ISBLANK($C30)),IF(NOT(ISBLANK(X30)),TRUE,FALSE),"") -> TRUE | Z30: {=IF(NOT(ISBLANK($C30)),AND(Y30=TRUE,LEN(X30)<81,NOT(ISNUMBER(FIND('List of Values'!$C$2:$C$23,X30)))),"")} -> TRUE | AA30: SE | AB30: =IF(NOT(ISBLANK($C30)),IF(NOT(ISBLANK(AA30)),TRUE,FALSE),"") -> TRUE | AC30: =IF(NOT(ISBLANK($C30)),AND(AB30=TRUE,NOT(COUNTIF('List of Values'!$B$2:$B$255,AA30)=0)),"") -> TRUE | AD30: SEK | AE30: =IF(NOT(ISBLANK($C30)),IF(NOT(ISBLANK(AD30)),TRUE,FALSE),"") -> TRUE | AF30: =IF(NOT(ISBLANK($C30)),AND(AE30=TRUE,NOT(COUNTIF('List of Values'!$F$2:$F$255,AD30)=0)),"") -> TRUE | AG30: V_10EOM | AH30: =IF(NOT(ISBLANK($C30)),IF(NOT(ISBLANK(AG30)),TRUE,FALSE),"") -> TRUE | AI30: =IF(NOT(ISBLANK($C30)),AND(AH30=TRUE,NOT(COUNTIF('List of Values'!$N$2:$N$40,AG30)=0)),"") -> TRUE | AJ30: V_BANK | AK30: =IF(NOT(ISBLANK($C30)),IF(NOT(ISBLANK(AJ30)),TRUE,FALSE),"") -> TRUE | AL30: =IF(NOT(ISBLANK($C30)),AND(AK30=TRUE,NOT(COUNTIF('List of Values'!$O$2:$O$30,AJ30)=0)),"") -> TRUE | AM30: S-DOM | AN30: =IF(NOT(ISBLANK($C30)),IF(NOT(ISBLANK(AM30)),TRUE,FALSE),"") -> TRUE | AO30: =IF(NOT(ISBLANK($C30)),AND(AN30=TRUE,NOT(COUNTIF('List of Values'!$AF$2:$AF$20,AM30)=0)),"") -> TRUE | AQ30: =IF(NOT(ISBLANK($C30)),TRUE,"") -> TRUE | AR30: {=IF(NOT(ISBLANK($C30)),AND(AQ30=TRUE,LEN(AP30)<81,NOT(ISNUMBER(FIND('List of Values'!$C$2:$C$20,AP30)))),"")} -> TRUE | AS30: =D30 -> SERVICESTYCKARNA AB | AT30: =IF(NOT(ISBLANK($C30)),IF(NOT(ISBLANK(AS30)),TRUE,FALSE),"") -> TRUE | AU30: {=IF(NOT(ISBLANK($C30)),AND(AT30=TRUE,LEN(AS30)<81,NOT(ISNUMBER(FIND('List of Values'!$C$2:$C$20,AS30)))),"")} -> TRUE | AV30: SERVICESTYCKARNAAB | AW30: =IF(NOT(ISBLANK($C30)),IF(NOT(ISBLANK(AV30)),TRUE,FALSE),"") -> TRUE | AX30: {=IF(NOT(ISBLANK($C30)),AND(AW30=TRUE,LEN(AV30)<21,NOT(ISNUMBER(FIND('List of Values'!$C$2:$C$20,AV30)))),"")} -> TRUE | AY30: 14538 | AZ30: =IF(NOT(ISBLANK($C30)),TRUE,"") -> TRUE | BA30: =IF(NOT(ISBLANK($C30)),AND(AZ30=TRUE,NOT(COUNTIF('List of Values'!$R$2:$R$400,AY30)=0)),"") -> TRUE | BC30: =IF(NOT(ISBLANK($C30)),TRUE,"") -> TRUE | BD30: {=IF(NOT(ISBLANK($C30)),OR(ISBLANK(BB30),AND(NOT(ISNUMBER(FIND('List of Values'!$C$2:$C$23,BB30))),ISNUMBER(DATEVALUE(BB30)))),"")} -> TRUE | BF30: =IF(NOT(ISBLANK($C30)),TRUE,"") -> TRUE | BG30: {=IF(NOT(ISBLANK($C30)),OR(ISBLANK(BE30),AND(NOT(ISNUMBER(FIND('List of Values'!$C$2:$C$23,BE30))),ISNUMBER(DATEVALUE(BE30)))),"")} -> TRUE | BI30: =IF(NOT(ISBLANK($C30)),TRUE,"") -> TRUE | BJ30: =IF(NOT(ISBLANK($C30)),OR(ISBLANK(BH30),AND(LEN(BH30)<14,ISNUMBER(BH30))),"") -> TRUE | BK30: Invoice | BL30: =IF(NOT(ISBLANK($C30)),IF(NOT(ISBLANK(BK30)),TRUE,FALSE),"") -> TRUE | BM30: =IF(NOT(ISBLANK($C30)),AND(BL30=TRUE,NOT(COUNTIF('List of Values'!$A$2:$A$20,BK30)=0)),"") -> TRUE | BN30: Active | BO30: =IF(NOT(ISBLANK($C30)),IF(NOT(ISBLANK(BN30)),TRUE,FALSE),"") -> TRUE | BP30: =IF(NOT(ISBLANK($C30)),OR(BN30="active",BN30="delisted"),"") -> TRUE | BR30: =IF(NOT(ISBLANK($C30)),OR(AND($E30="intercompany",NOT(ISBLANK(BQ30))),AND(NOT($E30="intercompany"),ISBLANK(BQ30))),"") -> TRUE | BS30: =IF(NOT(ISBLANK($C30)),OR(ISBLANK(BQ30),NOT(COUNTIF('List of Values'!$K$2:$K$30,BQ30)=0)),"") -> TRUE | BU30: =IF(NOT(ISBLANK($C30)),TRUE,"") -> TRUE | BV30: =IF(NOT(ISBLANK($C30)),OR(ISBLANK(BT30),BT30="duty paid",BT30="bond"),"") -> TRUE | BX30: =IF(NOT(ISBLANK($C30)),TRUE,"") -> TRUE | BY30: =IF(NOT(ISBLANK($C30)),OR(ISBLANK(BW30),BW30="duty paid",BW30="bond"),"") -> TRUE | BZ30: =_xlfn.XLOOKUP(C30,[1]Blad1!$A:$A,[1]Blad1!$D:$D,"")
B31: =COUNTIF(C31:XFD31,"FALSE") -> 0 | C31: 218015 | D31: STADSBUDENS MAGASIN 40 | E31: Indirect | F31: 7164174125 | G31: =IF(NOT(ISBLANK($C31)),IF(NOT(ISBLANK(F31)),TRUE,FALSE),"") -> TRUE | H31: {=IF(NOT(ISBLANK($C31)),AND(G31=TRUE,LEN(F31)<30,NOT(ISNUMBER(FIND('List of Values'!$C$2:$C$20,F31)))),"")} -> TRUE | I31: SE716417412501 | J31: =IF(NOT(ISBLANK($C31)),TRUE,"") -> TRUE | K31: {=IF(NOT(ISBLANK($C31)),AND(J31=TRUE,LEN(I31)<20,NOT(ISNUMBER(FIND('List of Values'!$C$2:$C$20,I31)))),"")} -> TRUE | L31: HALLVÄGEN 36 | M31: =IF(NOT(ISBLANK($C31)),IF(NOT(ISBLANK(L31)),TRUE,FALSE),"") -> TRUE | N31: {=IF(NOT(ISBLANK($C31)),AND(M31=TRUE,LEN(L31)<81,NOT(ISNUMBER(FIND('List of Values'!$C$2:$C$20,L31)))),"")} -> TRUE | P31: =IF(NOT(ISBLANK($C31)),TRUE,"") -> TRUE | Q31: {=IF(NOT(ISBLANK($C31)),AND(P31=TRUE,LEN(O31)<81,NOT(ISNUMBER(FIND('List of Values'!$C$2:$C$20,O31)))),"")} -> TRUE | R31: JOHANNESHOV | S31: =IF(NOT(ISBLANK($C31)),IF(NOT(ISBLANK(R31)),TRUE,FALSE),"") -> TRUE | T31: {=IF(NOT(ISBLANK($C31)),AND(S31=TRUE,LEN(R31)<61,NOT(ISNUMBER(FIND('List of Values'!$C$2:$C$23,R31)))),"")} -> TRUE | V31: =IF(NOT(ISBLANK($C31)),TRUE,"") -> TRUE | W31: {=IF(NOT(ISBLANK($C31)),AND(V31=TRUE,LEN(U31)<61,NOT(ISNUMBER(FIND('List of Values'!$C$2:$C$23,U31)))),"")} -> TRUE | X31: 121 62 | Y31: =IF(NOT(ISBLANK($C31)),IF(NOT(ISBLANK(X31)),TRUE,FALSE),"") -> TRUE | Z31: {=IF(NOT(ISBLANK($C31)),AND(Y31=TRUE,LEN(X31)<81,NOT(ISNUMBER(FIND('List of Values'!$C$2:$C$23,X31)))),"")} -> TRUE | AA31: SE | AB31: =IF(NOT(ISBLANK($C31)),IF(NOT(ISBLANK(AA31)),TRUE,FALSE),"") -> TRUE | AC31: =IF(NOT(ISBLANK($C31)),AND(AB31=TRUE,NOT(COUNTIF('List of Values'!$B$2:$B$255,AA31)=0)),"") -> TRUE | AD31: SEK | AE31: =IF(NOT(ISBLANK($C31)),IF(NOT(ISBLANK(AD31)),TRUE,FALSE),"") -> TRUE | AF31: =IF(NOT(ISBLANK($C31)),AND(AE31=TRUE,NOT(COUNTIF('List of Values'!$F$2:$F$255,AD31)=0)),"") -> TRUE | AG31: V_10EOM | AH31: =IF(NOT(ISBLANK($C31)),IF(NOT(ISBLANK(AG31)),TRUE,FALSE),"") -> TRUE | AI31: =IF(NOT(ISBLANK($C31)),AND(AH31=TRUE,NOT(COUNTIF('List of Values'!$N$2:$N$40,AG31)=0)),"") -> TRUE | AJ31: V_BANK | AK31: =IF(NOT(ISBLANK($C31)),IF(NOT(ISBLANK(AJ31)),TRUE,FALSE),"") -> TRUE | AL31: =IF(NOT(ISBLANK($C31)),AND(AK31=TRUE,NOT(COUNTIF('List of Values'!$O$2:$O$30,AJ31)=0)),"") -> TRUE | AM31: S-DOM | AN31: =IF(NOT(ISBLANK($C31)),IF(NOT(ISBLANK(AM31)),TRUE,FALSE),"") -> TRUE | AO31: =IF(NOT(ISBLANK($C31)),AND(AN31=TRUE,NOT(COUNTIF('List of Values'!$AF$2:$AF$20,AM31)=0)),"") -> TRUE | AQ31: =IF(NOT(ISBLANK($C31)),TRUE,"") -> TRUE | AR31: {=IF(NOT(ISBLANK($C31)),AND(AQ31=TRUE,LEN(AP31)<81,NOT(ISNUMBER(FIND('List of Values'!$C$2:$C$20,AP31)))),"")} -> TRUE | AS31: =D31 -> STADSBUDENS MAGASIN 40 | AT31: =IF(NOT(ISBLANK($C31)),IF(NOT(ISBLANK(AS31)),TRUE,FALSE),"") -> TRUE | AU31: {=IF(NOT(ISBLANK($C31)),AND(AT31=TRUE,LEN(AS31)<81,NOT(ISNUMBER(FIND('List of Values'!$C$2:$C$20,AS31)))),"")} -> TRUE | AV31: STADSBUDENSMAGASIN40 | AW31: =IF(NOT(ISBLANK($C31)),IF(NOT(ISBLANK(AV31)),TRUE,FALSE),"") -> TRUE | AX31: {=IF(NOT(ISBLANK($C31)),AND(AW31=TRUE,LEN(AV31)<21,NOT(ISNUMBER(FIND('List of Values'!$C$2:$C$20,AV31)))),"")} -> TRUE | AY31: 10001 | AZ31: =IF(NOT(ISBLANK($C31)),TRUE,"") -> TRUE | BA31: =IF(NOT(ISBLANK($C31)),AND(AZ31=TRUE,NOT(COUNTIF('List of Values'!$R$2:$R$400,AY31)=0)),"") -> TRUE | BC31: =IF(NOT(ISBLANK($C31)),TRUE,"") -> TRUE | BD31: {=IF(NOT(ISBLANK($C31)),OR(ISBLANK(BB31),AND(NOT(ISNUMBER(FIND('List of Values'!$C$2:$C$23,BB31))),ISNUMBER(DATEVALUE(BB31)))),"")} -> TRUE | BF31: =IF(NOT(ISBLANK($C31)),TRUE,"") -> TRUE | BG31: {=IF(NOT(ISBLANK($C31)),OR(ISBLANK(BE31),AND(NOT(ISNUMBER(FIND('List of Values'!$C$2:$C$23,BE31))),ISNUMBER(DATEVALUE(BE31)))),"")} -> TRUE | BI31: =IF(NOT(ISBLANK($C31)),TRUE,"") -> TRUE | BJ31: =IF(NOT(ISBLANK($C31)),OR(ISBLANK(BH31),AND(LEN(BH31)<14,ISNUMBER(BH31))),"") -> TRUE | BK31: Invoice | BL31: =IF(NOT(ISBLANK($C31)),IF(NOT(ISBLANK(BK31)),TRUE,FALSE),"") -> TRUE | BM31: =IF(NOT(ISBLANK($C31)),AND(BL31=TRUE,NOT(COUNTIF('List of Values'!$A$2:$A$20,BK31)=0)),"") -> TRUE | BN31: Active | BO31: =IF(NOT(ISBLANK($C31)),IF(NOT(ISBLANK(BN31)),TRUE,FALSE),"") -> TRUE | BP31: =IF(NOT(ISBLANK($C31)),OR(BN31="active",BN31="delisted"),"") -> TRUE | BR31: =IF(NOT(ISBLANK($C31)),OR(AND($E31="intercompany",NOT(ISBLANK(BQ31))),AND(NOT($E31="intercompany"),ISBLANK(BQ31))),"") -> TRUE | BS31: =IF(NOT(ISBLANK($C31)),OR(ISBLANK(BQ31),NOT(COUNTIF('List of Values'!$K$2:$K$30,BQ31)=0)),"") -> TRUE | BU31: =IF(NOT(ISBLANK($C31)),TRUE,"") -> TRUE | BV31: =IF(NOT(ISBLANK($C31)),OR(ISBLANK(BT31),BT31="duty paid",BT31="bond"),"") -> TRUE | BX31: =IF(NOT(ISBLANK($C31)),TRUE,"") -> TRUE | BY31: =IF(NOT(ISBLANK($C31)),OR(ISBLANK(BW31),BW31="duty paid",BW31="bond"),"") -> TRUE | BZ31: =_xlfn.XLOOKUP(C31,[1]Blad1!$A:$A,[1]Blad1!$D:$D,"")
B32: =COUNTIF(C32:XFD32,"FALSE") -> 0 | C32: 217998 | D32: NEVID APS | E32: Trade | F32: DK33382871 | G32: =IF(NOT(ISBLANK($C32)),IF(NOT(ISBLANK(F32)),TRUE,FALSE),"") -> TRUE | H32: {=IF(NOT(ISBLANK($C32)),AND(G32=TRUE,LEN(F32)<30,NOT(ISNUMBER(FIND('List of Values'!$C$2:$C$20,F32)))),"")} -> TRUE | I32: DK33382871 | J32: =IF(NOT(ISBLANK($C32)),TRUE,"") -> TRUE | K32: {=IF(NOT(ISBLANK($C32)),AND(J32=TRUE,LEN(I32)<20,NOT(ISNUMBER(FIND('List of Values'!$C$2:$C$20,I32)))),"")} -> TRUE | L32: C/O BLUE WATER TRANSPORT A/S | M32: =IF(NOT(ISBLANK($C32)),IF(NOT(ISBLANK(L32)),TRUE,FALSE),"") -> TRUE | N32: {=IF(NOT(ISBLANK($C32)),AND(M32=TRUE,LEN(L32)<81,NOT(ISNUMBER(FIND('List of Values'!$C$2:$C$20,L32)))),"")} -> TRUE | O32: ISTEDVEJ 7 | P32: =IF(NOT(ISBLANK($C32)),TRUE,"") -> TRUE | Q32: {=IF(NOT(ISBLANK($C32)),AND(P32=TRUE,LEN(O32)<81,NOT(ISNUMBER(FIND('List of Values'!$C$2:$C$20,O32)))),"")} -> TRUE | R32: PADBORG | S32: =IF(NOT(ISBLANK($C32)),IF(NOT(ISBLANK(R32)),TRUE,FALSE),"") -> TRUE | T32: {=IF(NOT(ISBLANK($C32)),AND(S32=TRUE,LEN(R32)<61,NOT(ISNUMBER(FIND('List of Values'!$C$2:$C$23,R32)))),"")} -> TRUE | V32: =IF(NOT(ISBLANK($C32)),TRUE,"") -> TRUE | W32: {=IF(NOT(ISBLANK($C32)),AND(V32=TRUE,LEN(U32)<61,NOT(ISNUMBER(FIND('List of Values'!$C$2:$C$23,U32)))),"")} -> TRUE | X32: DK-6330 | Y32: =IF(NOT(ISBLANK($C32)),IF(NOT(ISBLANK(X32)),TRUE,FALSE),"") -> TRUE | Z32: {=IF(NOT(ISBLANK($C32)),AND(Y32=TRUE,LEN(X32)<81,NOT(ISNUMBER(FIND('List of Values'!$C$2:$C$23,X32)))),"")} -> TRUE | AA32: DK | AB32: =IF(NOT(ISBLANK($C32)),IF(NOT(ISBLANK(AA32)),TRUE,FALSE),"") -> TRUE | AC32: =IF(NOT(ISBLANK($C32)),AND(AB32=TRUE,NOT(COUNTIF('List of Values'!$B$2:$B$255,AA32)=0)),"") -> TRUE | AD32: DKK | AE32: =IF(NOT(ISBLANK($C32)),IF(NOT(ISBLANK(AD32)),TRUE,FALSE),"") -> TRUE | AF32: =IF(NOT(ISBLANK($C32)),AND(AE32=TRUE,NOT(COUNTIF('List of Values'!$F$2:$F$255,AD32)=0)),"") -> TRUE | AG32: V_10EOM | AH32: =IF(NOT(ISBLANK($C32)),IF(NOT(ISBLANK(AG32)),TRUE,FALSE),"") -> TRUE | AI32: =IF(NOT(ISBLANK($C32)),AND(AH32=TRUE,NOT(COUNTIF('List of Values'!$N$2:$N$40,AG32)=0)),"") -> TRUE | AJ32: V_BANK | AK32: =IF(NOT(ISBLANK($C32)),IF(NOT(ISBLANK(AJ32)),TRUE,FALSE),"") -> TRUE | AL32: =IF(NOT(ISBLANK($C32)),AND(AK32=TRUE,NOT(COUNTIF('List of Values'!$O$2:$O$30,AJ32)=0)),"") -> TRUE | AM32: S-EU | AN32: =IF(NOT(ISBLANK($C32)),IF(NOT(ISBLANK(AM32)),TRUE,FALSE),"") -> TRUE | AO32: =IF(NOT(ISBLANK($C32)),AND(AN32=TRUE,NOT(COUNTIF('List of Values'!$AF$2:$AF$20,AM32)=0)),"") -> TRUE | AQ32: =IF(NOT(ISBLANK($C32)),TRUE,"") -> TRUE | AR32: {=IF(NOT(ISBLANK($C32)),AND(AQ32=TRUE,LEN(AP32)<81,NOT(ISNUMBER(FIND('List of Values'!$C$2:$C$20,AP32)))),"")} -> TRUE | AS32: =D32 -> NEVID APS | AT32: =IF(NOT(ISBLANK($C32)),IF(NOT(ISBLANK(AS32)),TRUE,FALSE),"") -> TRUE | AU32: {=IF(NOT(ISBLANK($C32)),AND(AT32=TRUE,LEN(AS32)<81,NOT(ISNUMBER(FIND('List of Values'!$C$2:$C$20,AS32)))),"")} -> TRUE | AV32: NEVIDAPS | AW32: =IF(NOT(ISBLANK($C32)),IF(NOT(ISBLANK(AV32)),TRUE,FALSE),"") -> TRUE | AX32: {=IF(NOT(ISBLANK($C32)),AND(AW32=TRUE,LEN(AV32)<21,NOT(ISNUMBER(FIND('List of Values'!$C$2:$C$20,AV32)))),"")} -> TRUE | AY32: 13618 | AZ32: =IF(NOT(ISBLANK($C32)),TRUE,"") -> TRUE | BA32: =IF(NOT(ISBLANK($C32)),AND(AZ32=TRUE,NOT(COUNTIF('List of Values'!$R$2:$R$400,AY32)=0)),"") -> TRUE | BC32: =IF(NOT(ISBLANK($C32)),TRUE,"") -> TRUE | BD32: {=IF(NOT(ISBLANK($C32)),OR(ISBLANK(BB32),AND(NOT(ISNUMBER(FIND('List of Values'!$C$2:$C$23,BB32))),ISNUMBER(DATEVALUE(BB32)))),"")} -> TRUE | BF32: =IF(NOT(ISBLANK($C32)),TRUE,"") -> TRUE | BG32: {=IF(NOT(ISBLANK($C32)),OR(ISBLANK(BE32),AND(NOT(ISNUMBER(FIND('List of Values'!$C$2:$C$23,BE32))),ISNUMBER(DATEVALUE(BE32)))),"")} -> TRUE | BI32: =IF(NOT(ISBLANK($C32)),TRUE,"") -> TRUE | BJ32: =IF(NOT(ISBLANK($C32)),OR(ISBLANK(BH32),AND(LEN(BH32)<14,ISNUMBER(BH32))),"") -> TRUE | BK32: Invoice | BL32: =IF(NOT(ISBLANK($C32)),IF(NOT(ISBLANK(BK32)),TRUE,FALSE),"") -> TRUE | BM32: =IF(NOT(ISBLANK($C32)),AND(BL32=TRUE,NOT(COUNTIF('List of Values'!$A$2:$A$20,BK32)=0)),"") -> TRUE | BN32: Active | BO32: =IF(NOT(ISBLANK($C32)),IF(NOT(ISBLANK(BN32)),TRUE,FALSE),"") -> TRUE | BP32: =IF(NOT(ISBLANK($C32)),OR(BN32="active",BN32="delisted"),"") -> TRUE | BR32: =IF(NOT(ISBLANK($C32)),OR(AND($E32="intercompany",NOT(ISBLANK(BQ32))),AND(NOT($E32="intercompany"),ISBLANK(BQ32))),"") -> TRUE | BS32: =IF(NOT(ISBLANK($C32)),OR(ISBLANK(BQ32),NOT(COUNTIF('List of Values'!$K$2:$K$30,BQ32)=0)),"") -> TRUE | BU32: =IF(NOT(ISBLANK($C32)),TRUE,"") -> TRUE | BV32: =IF(NOT(ISBLANK($C32)),OR(ISBLANK(BT32),BT32="duty paid",BT32="bond"),"") -> TRUE | BX32: =IF(NOT(ISBLANK($C32)),TRUE,"") -> TRUE | BY32: =IF(NOT(ISBLANK($C32)),OR(ISBLANK(BW32),BW32="duty paid",BW32="bond"),"") -> TRUE | BZ32: =_xlfn.XLOOKUP(C32,[1]Blad1!$A:$A,[1]Blad1!$D:$D,"")
B33: =COUNTIF(C33:XFD33,"FALSE") -> 0 | C33: 217973 | D33: VINGA SEAFOOD AB | E33: Trade | F33: 5569759458 | G33: =IF(NOT(ISBLANK($C33)),IF(NOT(ISBLANK(F33)),TRUE,FALSE),"") -> TRUE | H33: {=IF(NOT(ISBLANK($C33)),AND(G33=TRUE,LEN(F33)<30,NOT(ISNUMBER(FIND('List of Values'!$C$2:$C$20,F33)))),"")} -> TRUE | I33: SE556975945801 | J33: =IF(NOT(ISBLANK($C33)),TRUE,"") -> TRUE | K33: {=IF(NOT(ISBLANK($C33)),AND(J33=TRUE,LEN(I33)<20,NOT(ISNUMBER(FIND('List of Values'!$C$2:$C$20,I33)))),"")} -> TRUE | L33: BOX 1052 | M33: =IF(NOT(ISBLANK($C33)),IF(NOT(ISBLANK(L33)),TRUE,FALSE),"") -> TRUE | N33: {=IF(NOT(ISBLANK($C33)),AND(M33=TRUE,LEN(L33)<81,NOT(ISNUMBER(FIND('List of Values'!$C$2:$C$20,L33)))),"")} -> TRUE | P33: =IF(NOT(ISBLANK($C33)),TRUE,"") -> TRUE | Q33: {=IF(NOT(ISBLANK($C33)),AND(P33=TRUE,LEN(O33)<81,NOT(ISNUMBER(FIND('List of Values'!$C$2:$C$20,O33)))),"")} -> TRUE | R33: ÖCKERÖ | S33: =IF(NOT(ISBLANK($C33)),IF(NOT(ISBLANK(R33)),TRUE,FALSE),"") -> TRUE | T33: {=IF(NOT(ISBLANK($C33)),AND(S33=TRUE,LEN(R33)<61,NOT(ISNUMBER(FIND('List of Values'!$C$2:$C$23,R33)))),"")} -> TRUE | V33: =IF(NOT(ISBLANK($C33)),TRUE,"") -> TRUE | W33: {=IF(NOT(ISBLANK($C33)),AND(V33=TRUE,LEN(U33)<61,NOT(ISNUMBER(FIND('List of Values'!$C$2:$C$23,U33)))),"")} -> TRUE | X33: 475 22 | Y33: =IF(NOT(ISBLANK($C33)),IF(NOT(ISBLANK(X33)),TRUE,FALSE),"") -> TRUE | Z33: {=IF(NOT(ISBLANK($C33)),AND(Y33=TRUE,LEN(X33)<81,NOT(ISNUMBER(FIND('List of Values'!$C$2:$C$23,X33)))),"")} -> TRUE | AA33: SE | AB33: =IF(NOT(ISBLANK($C33)),IF(NOT(ISBLANK(AA33)),TRUE,FALSE),"") -> TRUE | AC33: =IF(NOT(ISBLANK($C33)),AND(AB33=TRUE,NOT(COUNTIF('List of Values'!$B$2:$B$255,AA33)=0)),"") -> TRUE | AD33: SEK | AE33: =IF(NOT(ISBLANK($C33)),IF(NOT(ISBLANK(AD33)),TRUE,FALSE),"") -> TRUE | AF33: =IF(NOT(ISBLANK($C33)),AND(AE33=TRUE,NOT(COUNTIF('List of Values'!$F$2:$F$255,AD33)=0)),"") -> TRUE | AG33: V_20NET | AH33: =IF(NOT(ISBLANK($C33)),IF(NOT(ISBLANK(AG33)),TRUE,FALSE),"") -> TRUE | AI33: =IF(NOT(ISBLANK($C33)),AND(AH33=TRUE,NOT(COUNTIF('List of Values'!$N$2:$N$40,AG33)=0)),"") -> TRUE | AJ33: V_BANK | AK33: =IF(NOT(ISBLANK($C33)),IF(NOT(ISBLANK(AJ33)),TRUE,FALSE),"") -> TRUE | AL33: =IF(NOT(ISBLANK($C33)),AND(AK33=TRUE,NOT(COUNTIF('List of Values'!$O$2:$O$30,AJ33)=0)),"") -> TRUE | AM33: S-DOM | AN33: =IF(NOT(ISBLANK($C33)),IF(NOT(ISBLANK(AM33)),TRUE,FALSE),"") -> TRUE | AO33: =IF(NOT(ISBLANK($C33)),AND(AN33=TRUE,NOT(COUNTIF('List of Values'!$AF$2:$AF$20,AM33)=0)),"") -> TRUE | AQ33: =IF(NOT(ISBLANK($C33)),TRUE,"") -> TRUE | AR33: {=IF(NOT(ISBLANK($C33)),AND(AQ33=TRUE,LEN(AP33)<81,NOT(ISNUMBER(FIND('List of Values'!$C$2:$C$20,AP33)))),"")} -> TRUE | AS33: =D33 -> VINGA SEAFOOD AB | AT33: =IF(NOT(ISBLANK($C33)),IF(NOT(ISBLANK(AS33)),TRUE,FALSE),"") -> TRUE | AU33: {=IF(NOT(ISBLANK($C33)),AND(AT33=TRUE,LEN(AS33)<81,NOT(ISNUMBER(FIND('List of Values'!$C$2:$C$20,AS33)))),"")} -> TRUE | AV33: VINGASEAFOODAB | AW33: =IF(NOT(ISBLANK($C33)),IF(NOT(ISBLANK(AV33)),TRUE,FALSE),"") -> TRUE | AX33: {=IF(NOT(ISBLANK($C33)),AND(AW33=TRUE,LEN(AV33)<21,NOT(ISNUMBER(FIND('List of Values'!$C$2:$C$20,AV33)))),"")} -> TRUE | AY33: 15344 | AZ33: =IF(NOT(ISBLANK($C33)),TRUE,"") -> TRUE | BA33: =IF(NOT(ISBLANK($C33)),AND(AZ33=TRUE,NOT(COUNTIF('List of Values'!$R$2:$R$400,AY33)=0)),"") -> TRUE | BC33: =IF(NOT(ISBLANK($C33)),TRUE,"") -> TRUE | BD33: {=IF(NOT(ISBLANK($C33)),OR(ISBLANK(BB33),AND(NOT(ISNUMBER(FIND('List of Values'!$C$2:$C$23,BB33))),ISNUMBER(DATEVALUE(BB33)))),"")} -> TRUE | BF33: =IF(NOT(ISBLANK($C33)),TRUE,"") -> TRUE | BG33: {=IF(NOT(ISBLANK($C33)),OR(ISBLANK(BE33),AND(NOT(ISNUMBER(FIND('List of Values'!$C$2:$C$23,BE33))),ISNUMBER(DATEVALUE(BE33)))),"")} -> TRUE | BI33: =IF(NOT(ISBLANK($C33)),TRUE,"") -> TRUE | BJ33: =IF(NOT(ISBLANK($C33)),OR(ISBLANK(BH33),AND(LEN(BH33)<14,ISNUMBER(BH33))),"") -> TRUE | BK33: Invoice | BL33: =IF(NOT(ISBLANK($C33)),IF(NOT(ISBLANK(BK33)),TRUE,FALSE),"") -> TRUE | BM33: =IF(NOT(ISBLANK($C33)),AND(BL33=TRUE,NOT(COUNTIF('List of Values'!$A$2:$A$20,BK33)=0)),"") -> TRUE | BN33: Active | BO33: =IF(NOT(ISBLANK($C33)),IF(NOT(ISBLANK(BN33)),TRUE,FALSE),"") -> TRUE | BP33: =IF(NOT(ISBLANK($C33)),OR(BN33="active",BN33="delisted"),"") -> TRUE | BR33: =IF(NOT(ISBLANK($C33)),OR(AND($E33="intercompany",NOT(ISBLANK(BQ33))),AND(NOT($E33="intercompany"),ISBLANK(BQ33))),"") -> TRUE | BS33: =IF(NOT(ISBLANK($C33)),OR(ISBLANK(BQ33),NOT(COUNTIF('List of Values'!$K$2:$K$30,BQ33)=0)),"") -> TRUE | BU33: =IF(NOT(ISBLANK($C33)),TRUE,"") -> TRUE | BV33: =IF(NOT(ISBLANK($C33)),OR(ISBLANK(BT33),BT33="duty paid",BT33="bond"),"") -> TRUE | BX33: =IF(NOT(ISBLANK($C33)),TRUE,"") -> TRUE | BY33: =IF(NOT(ISBLANK($C33)),OR(ISBLANK(BW33),BW33="duty paid",BW33="bond"),"") -> TRUE | BZ33: =_xlfn.XLOOKUP(C33,[1]Blad1!$A:$A,[1]Blad1!$D:$D,"") -> x
B34: =COUNTIF(C34:XFD34,"FALSE") -> 0 | C34: 218021 | D34: TRANSPORTSTYRELSEN | E34: Indirect | F34: 2021006297 | G34: =IF(NOT(ISBLANK($C34)),IF(NOT(ISBLANK(F34)),TRUE,FALSE),"") -> TRUE | H34: {=IF(NOT(ISBLANK($C34)),AND(G34=TRUE,LEN(F34)<30,NOT(ISNUMBER(FIND('List of Values'!$C$2:$C$20,F34)))),"")} -> TRUE | I34: SE202100629701 | J34: =IF(NOT(ISBLANK($C34)),TRUE,"") -> TRUE | K34: {=IF(NOT(ISBLANK($C34)),AND(J34=TRUE,LEN(I34)<20,NOT(ISNUMBER(FIND('List of Values'!$C$2:$C$20,I34)))),"")} -> TRUE | L34: UNAVAILABLE | M34: =IF(NOT(ISBLANK($C34)),IF(NOT(ISBLANK(L34)),TRUE,FALSE),"") -> TRUE | N34: {=IF(NOT(ISBLANK($C34)),AND(M34=TRUE,LEN(L34)<81,NOT(ISNUMBER(FIND('List of Values'!$C$2:$C$20,L34)))),"")} -> TRUE | P34: =IF(NOT(ISBLANK($C34)),TRUE,"") -> TRUE | Q34: {=IF(NOT(ISBLANK($C34)),AND(P34=TRUE,LEN(O34)<81,NOT(ISNUMBER(FIND('List of Values'!$C$2:$C$20,O34)))),"")} -> TRUE | R34: ÖREBRO | S34: =IF(NOT(ISBLANK($C34)),IF(NOT(ISBLANK(R34)),TRUE,FALSE),"") -> TRUE | T34: {=IF(NOT(ISBLANK($C34)),AND(S34=TRUE,LEN(R34)<61,NOT(ISNUMBER(FIND('List of Values'!$C$2:$C$23,R34)))),"")} -> TRUE | V34: =IF(NOT(ISBLANK($C34)),TRUE,"") -> TRUE | W34: {=IF(NOT(ISBLANK($C34)),AND(V34=TRUE,LEN(U34)<61,NOT(ISNUMBER(FIND('List of Values'!$C$2:$C$23,U34)))),"")} -> TRUE | X34: 701 81 | Y34: =IF(NOT(ISBLANK($C34)),IF(NOT(ISBLANK(X34)),TRUE,FALSE),"") -> TRUE | Z34: {=IF(NOT(ISBLANK($C34)),AND(Y34=TRUE,LEN(X34)<81,NOT(ISNUMBER(FIND('List of Values'!$C$2:$C$23,X34)))),"")} -> TRUE | AA34: SE | AB34: =IF(NOT(ISBLANK($C34)),IF(NOT(ISBLANK(AA34)),TRUE,FALSE),"") -> TRUE | AC34: =IF(NOT(ISBLANK($C34)),AND(AB34=TRUE,NOT(COUNTIF('List of Values'!$B$2:$B$255,AA34)=0)),"") -> TRUE | AD34: SEK | AE34: =IF(NOT(ISBLANK($C34)),IF(NOT(ISBLANK(AD34)),TRUE,FALSE),"") -> TRUE | AF34: =IF(NOT(ISBLANK($C34)),AND(AE34=TRUE,NOT(COUNTIF('List of Values'!$F$2:$F$255,AD34)=0)),"") -> TRUE | AG34: V_10EOM | AH34: =IF(NOT(ISBLANK($C34)),IF(NOT(ISBLANK(AG34)),TRUE,FALSE),"") -> TRUE | AI34: =IF(NOT(ISBLANK($C34)),AND(AH34=TRUE,NOT(COUNTIF('List of Values'!$N$2:$N$40,AG34)=0)),"") -> TRUE | AJ34: V_BANK | AK34: =IF(NOT(ISBLANK($C34)),IF(NOT(ISBLANK(AJ34)),TRUE,FALSE),"") -> TRUE | AL34: =IF(NOT(ISBLANK($C34)),AND(AK34=TRUE,NOT(COUNTIF('List of Values'!$O$2:$O$30,AJ34)=0)),"") -> TRUE | AM34: S-DOM | AN34: =IF(NOT(ISBLANK($C34)),IF(NOT(ISBLANK(AM34)),TRUE,FALSE),"") -> TRUE | AO34: =IF(NOT(ISBLANK($C34)),AND(AN34=TRUE,NOT(COUNTIF('List of Values'!$AF$2:$AF$20,AM34)=0)),"") -> TRUE | AQ34: =IF(NOT(ISBLANK($C34)),TRUE,"") -> TRUE | AR34: {=IF(NOT(ISBLANK($C34)),AND(AQ34=TRUE,LEN(AP34)<81,NOT(ISNUMBER(FIND('List of Values'!$C$2:$C$20,AP34)))),"")} -> TRUE | AS34: =D34 -> TRANSPORTSTYRELSEN | AT34: =IF(NOT(ISBLANK($C34)),IF(NOT(ISBLANK(AS34)),TRUE,FALSE),"") -> TRUE | AU34: {=IF(NOT(ISBLANK($C34)),AND(AT34=TRUE,LEN(AS34)<81,NOT(ISNUMBER(FIND('List of Values'!$C$2:$C$20,AS34)))),"")} -> TRUE | AV34: VÄGVERKET.BILREGISTR | AW34: =IF(NOT(ISBLANK($C34)),IF(NOT(ISBLANK(AV34)),TRUE,FALSE),"") -> TRUE | AX34: {=IF(NOT(ISBLANK($C34)),AND(AW34=TRUE,LEN(AV34)<21,NOT(ISNUMBER(FIND('List of Values'!$C$2:$C$20,AV34)))),"")} -> TRUE | AY34: 10001 | AZ34: =IF(NOT(ISBLANK($C34)),TRUE,"") -> TRUE | BA34: =IF(NOT(ISBLANK($C34)),AND(AZ34=TRUE,NOT(COUNTIF('List of Values'!$R$2:$R$400,AY34)=0)),"") -> TRUE | BC34: =IF(NOT(ISBLANK($C34)),TRUE,"") -> TRUE | BD34: {=IF(NOT(ISBLANK($C34)),OR(ISBLANK(BB34),AND(NOT(ISNUMBER(FIND('List of Values'!$C$2:$C$23,BB34))),ISNUMBER(DATEVALUE(BB34)))),"")} -> TRUE | BF34: =IF(NOT(ISBLANK($C34)),TRUE,"") -> TRUE | BG34: {=IF(NOT(ISBLANK($C34)),OR(ISBLANK(BE34),AND(NOT(ISNUMBER(FIND('List of Values'!$C$2:$C$23,BE34))),ISNUMBER(DATEVALUE(BE34)))),"")} -> TRUE | BI34: =IF(NOT(ISBLANK($C34)),TRUE,"") -> TRUE | BJ34: =IF(NOT(ISBLANK($C34)),OR(ISBLANK(BH34),AND(LEN(BH34)<14,ISNUMBER(BH34))),"") -> TRUE | BK34: Invoice | BL34: =IF(NOT(ISBLANK($C34)),IF(NOT(ISBLANK(BK34)),TRUE,FALSE),"") -> TRUE | BM34: =IF(NOT(ISBLANK($C34)),AND(BL34=TRUE,NOT(COUNTIF('List of Values'!$A$2:$A$20,BK34)=0)),"") -> TRUE | BN34: Active | BO34: =IF(NOT(ISBLANK($C34)),IF(NOT(ISBLANK(BN34)),TRUE,FALSE),"") -> TRUE | BP34: =IF(NOT(ISBLANK($C34)),OR(BN34="active",BN34="delisted"),"") -> TRUE | BR34: =IF(NOT(ISBLANK($C34)),OR(AND($E34="intercompany",NOT(ISBLANK(BQ34))),AND(NOT($E34="intercompany"),ISBLANK(BQ34))),"") -> TRUE | BS34: =IF(NOT(ISBLANK($C34)),OR(ISBLANK(BQ34),NOT(COUNTIF('List of Values'!$K$2:$K$30,BQ34)=0)),"") -> TRUE | BU34: =IF(NOT(ISBLANK($C34)),TRUE,"") -> TRUE | BV34: =IF(NOT(ISBLANK($C34)),OR(ISBLANK(BT34),BT34="duty paid",BT34="bond"),"") -> TRUE | BX34: =IF(NOT(ISBLANK($C34)),TRUE,"") -> TRUE | BY34: =IF(NOT(ISBLANK($C34)),OR(ISBLANK(BW34),BW34="duty paid",BW34="bond"),"") -> TRUE | BZ34: =_xlfn.XLOOKUP(C34,[1]Blad1!$A:$A,[1]Blad1!$D:$D,"")
B35: =COUNTIF(C35:XFD35,"FALSE") -> 0 | C35: 217945 | D35: KVALITETSFISK AB | E35: Trade | F35: 5563281996 | G35: =IF(NOT(ISBLANK($C35)),IF(NOT(ISBLANK(F35)),TRUE,FALSE),"") -> TRUE | H35: {=IF(NOT(ISBLANK($C35)),AND(G35=TRUE,LEN(F35)<30,NOT(ISNUMBER(FIND('List of Values'!$C$2:$C$20,F35)))),"")} -> TRUE | I35: SE556328199601 | J35: =IF(NOT(ISBLANK($C35)),TRUE,"") -> TRUE | K35: {=IF(NOT(ISBLANK($C35)),AND(J35=TRUE,LEN(I35)<20,NOT(ISNUMBER(FIND('List of Values'!$C$2:$C$20,I35)))),"")} -> TRUE | L35: BOX 55 | M35: =IF(NOT(ISBLANK($C35)),IF(NOT(ISBLANK(L35)),TRUE,FALSE),"") -> TRUE | N35: {=IF(NOT(ISBLANK($C35)),AND(M35=TRUE,LEN(L35)<81,NOT(ISNUMBER(FIND('List of Values'!$C$2:$C$20,L35)))),"")} -> TRUE | P35: =IF(NOT(ISBLANK($C35)),TRUE,"") -> TRUE | Q35: {=IF(NOT(ISBLANK($C35)),AND(P35=TRUE,LEN(O35)<81,NOT(ISNUMBER(FIND('List of Values'!$C$2:$C$20,O35)))),"")} -> TRUE | R35: FARSTA | S35: =IF(NOT(ISBLANK($C35)),IF(NOT(ISBLANK(R35)),TRUE,FALSE),"") -> TRUE | T35: {=IF(NOT(ISBLANK($C35)),AND(S35=TRUE,LEN(R35)<61,NOT(ISNUMBER(FIND('List of Values'!$C$2:$C$23,R35)))),"")} -> TRUE | V35: =IF(NOT(ISBLANK($C35)),TRUE,"") -> TRUE | W35: {=IF(NOT(ISBLANK($C35)),AND(V35=TRUE,LEN(U35)<61,NOT(ISNUMBER(FIND('List of Values'!$C$2:$C$23,U35)))),"")} -> TRUE | X35: 123 21 | Y35: =IF(NOT(ISBLANK($C35)),IF(NOT(ISBLANK(X35)),TRUE,FALSE),"") -> TRUE | Z35: {=IF(NOT(ISBLANK($C35)),AND(Y35=TRUE,LEN(X35)<81,NOT(ISNUMBER(FIND('List of Values'!$C$2:$C$23,X35)))),"")} -> TRUE | AA35: SE | AB35: =IF(NOT(ISBLANK($C35)),IF(NOT(ISBLANK(AA35)),TRUE,FALSE),"") -> TRUE | AC35: =IF(NOT(ISBLANK($C35)),AND(AB35=TRUE,NOT(COUNTIF('List of Values'!$B$2:$B$255,AA35)=0)),"") -> TRUE | AD35: SEK | AE35: =IF(NOT(ISBLANK($C35)),IF(NOT(ISBLANK(AD35)),TRUE,FALSE),"") -> TRUE | AF35: =IF(NOT(ISBLANK($C35)),AND(AE35=TRUE,NOT(COUNTIF('List of Values'!$F$2:$F$255,AD35)=0)),"") -> TRUE | AG35: V_20NET | AH35: =IF(NOT(ISBLANK($C35)),IF(NOT(ISBLANK(AG35)),TRUE,FALSE),"") -> TRUE | AI35: =IF(NOT(ISBLANK($C35)),AND(AH35=TRUE,NOT(COUNTIF('List of Values'!$N$2:$N$40,AG35)=0)),"") -> TRUE | AJ35: V_BANK | AK35: =IF(NOT(ISBLANK($C35)),IF(NOT(ISBLANK(AJ35)),TRUE,FALSE),"") -> TRUE | AL35: =IF(NOT(ISBLANK($C35)),AND(AK35=TRUE,NOT(COUNTIF('List of Values'!$O$2:$O$30,AJ35)=0)),"") -> TRUE | AM35: S-DOM | AN35: =IF(NOT(ISBLANK($C35)),IF(NOT(ISBLANK(AM35)),TRUE,FALSE),"") -> TRUE | AO35: =IF(NOT(ISBLANK($C35)),AND(AN35=TRUE,NOT(COUNTIF('List of Values'!$AF$2:$AF$20,AM35)=0)),"") -> TRUE | AQ35: =IF(NOT(ISBLANK($C35)),TRUE,"") -> TRUE | AR35: {=IF(NOT(ISBLANK($C35)),AND(AQ35=TRUE,LEN(AP35)<81,NOT(ISNUMBER(FIND('List of Values'!$C$2:$C$20,AP35)))),"")} -> TRUE | AS35: =D35 -> KVALITETSFISK AB | AT35: =IF(NOT(ISBLANK($C35)),IF(NOT(ISBLANK(AS35)),TRUE,FALSE),"") -> TRUE | AU35: {=IF(NOT(ISBLANK($C35)),AND(AT35=TRUE,LEN(AS35)<81,NOT(ISNUMBER(FIND('List of Values'!$C$2:$C$20,AS35)))),"")} -> TRUE | AV35: KVALITETSFISKAB | AW35: =IF(NOT(ISBLANK($C35)),IF(NOT(ISBLANK(AV35)),TRUE,FALSE),"") -> TRUE | AX35: {=IF(NOT(ISBLANK($C35)),AND(AW35=TRUE,LEN(AV35)<21,NOT(ISNUMBER(FIND('List of Values'!$C$2:$C$20,AV35)))),"")} -> TRUE | AY35: 12932 | AZ35: =IF(NOT(ISBLANK($C35)),TRUE,"") -> TRUE | BA35: =IF(NOT(ISBLANK($C35)),AND(AZ35=TRUE,NOT(COUNTIF('List of Values'!$R$2:$R$400,AY35)=0)),"") -> TRUE | BC35: =IF(NOT(ISBLANK($C35)),TRUE,"") -> TRUE | BD35: {=IF(NOT(ISBLANK($C35)),OR(ISBLANK(BB35),AND(NOT(ISNUMBER(FIND('List of Values'!$C$2:$C$23,BB35))),ISNUMBER(DATEVALUE(BB35)))),"")} -> TRUE | BF35: =IF(NOT(ISBLANK($C35)),TRUE,"") -> TRUE | BG35: {=IF(NOT(ISBLANK($C35)),OR(ISBLANK(BE35),AND(NOT(ISNUMBER(FIND('List of Values'!$C$2:$C$23,BE35))),ISNUMBER(DATEVALUE(BE35)))),"")} -> TRUE | BI35: =IF(NOT(ISBLANK($C35)),TRUE,"") -> TRUE | BJ35: =IF(NOT(ISBLANK($C35)),OR(ISBLANK(BH35),AND(LEN(BH35)<14,ISNUMBER(BH35))),"") -> TRUE | BK35: Invoice | BL35: =IF(NOT(ISBLANK($C35)),IF(NOT(ISBLANK(BK35)),TRUE,FALSE),"") -> TRUE | BM35: =IF(NOT(ISBLANK($C35)),AND(BL35=TRUE,NOT(COUNTIF('List of Values'!$A$2:$A$20,BK35)=0)),"") -> TRUE | BN35: Active | BO35: =IF(NOT(ISBLANK($C35)),IF(NOT(ISBLANK(BN35)),TRUE,FALSE),"") -> TRUE | BP35: =IF(NOT(ISBLANK($C35)),OR(BN35="active",BN35="delisted"),"") -> TRUE | BR35: =IF(NOT(ISBLANK($C35)),OR(AND($E35="intercompany",NOT(ISBLANK(BQ35))),AND(NOT($E35="intercompany"),ISBLANK(BQ35))),"") -> TRUE | BS35: =IF(NOT(ISBLANK($C35)),OR(ISBLANK(BQ35),NOT(COUNTIF('List of Values'!$K$2:$K$30,BQ35)=0)),"") -> TRUE | BU35: =IF(NOT(ISBLANK($C35)),TRUE,"") -> TRUE | BV35: =IF(NOT(ISBLANK($C35)),OR(ISBLANK(BT35),BT35="duty paid",BT35="bond"),"") -> TRUE | BX35: =IF(NOT(ISBLANK($C35)),TRUE,"") -> TRUE | BY35: =IF(NOT(ISBLANK($C35)),OR(ISBLANK(BW35),BW35="duty paid",BW35="bond"),"") -> TRUE | BZ35: =_xlfn.XLOOKUP(C35,[1]Blad1!$A:$A,[1]Blad1!$D:$D,"")
B36: =COUNTIF(C36:XFD36,"FALSE") -> 0 | C36: 217971 | D36: SMÖGENS FISKAUKTION AB | E36: Trade | F36: 5568881238 | G36: =IF(NOT(ISBLANK($C36)),IF(NOT(ISBLANK(F36)),TRUE,FALSE),"") -> TRUE | H36: {=IF(NOT(ISBLANK($C36)),AND(G36=TRUE,LEN(F36)<30,NOT(ISNUMBER(FIND('List of Values'!$C$2:$C$20,F36)))),"")} -> TRUE | I36: SE556888123801 | J36: =IF(NOT(ISBLANK($C36)),TRUE,"") -> TRUE | K36: {=IF(NOT(ISBLANK($C36)),AND(J36=TRUE,LEN(I36)<20,NOT(ISNUMBER(FIND('List of Values'!$C$2:$C$20,I36)))),"")} -> TRUE | L36: FISKHAMNSGATAN 31 | M36: =IF(NOT(ISBLANK($C36)),IF(NOT(ISBLANK(L36)),TRUE,FALSE),"") -> TRUE | N36: {=IF(NOT(ISBLANK($C36)),AND(M36=TRUE,LEN(L36)<81,NOT(ISNUMBER(FIND('List of Values'!$C$2:$C$20,L36)))),"")} -> TRUE | P36: =IF(NOT(ISBLANK($C36)),TRUE,"") -> TRUE | Q36: {=IF(NOT(ISBLANK($C36)),AND(P36=TRUE,LEN(O36)<81,NOT(ISNUMBER(FIND('List of Values'!$C$2:$C$20,O36)))),"")} -> TRUE | R36: SMÖGEN | S36: =IF(NOT(ISBLANK($C36)),IF(NOT(ISBLANK(R36)),TRUE,FALSE),"") -> TRUE | T36: {=IF(NOT(ISBLANK($C36)),AND(S36=TRUE,LEN(R36)<61,NOT(ISNUMBER(FIND('List of Values'!$C$2:$C$23,R36)))),"")} -> TRUE | V36: =IF(NOT(ISBLANK($C36)),TRUE,"") -> TRUE | W36: {=IF(NOT(ISBLANK($C36)),AND(V36=TRUE,LEN(U36)<61,NOT(ISNUMBER(FIND('List of Values'!$C$2:$C$23,U36)))),"")} -> TRUE | X36: 456 51 | Y36: =IF(NOT(ISBLANK($C36)),IF(NOT(ISBLANK(X36)),TRUE,FALSE),"") -> TRUE | Z36: {=IF(NOT(ISBLANK($C36)),AND(Y36=TRUE,LEN(X36)<81,NOT(ISNUMBER(FIND('List of Values'!$C$2:$C$23,X36)))),"")} -> TRUE | AA36: SE | AB36: =IF(NOT(ISBLANK($C36)),IF(NOT(ISBLANK(AA36)),TRUE,FALSE),"") -> TRUE | AC36: =IF(NOT(ISBLANK($C36)),AND(AB36=TRUE,NOT(COUNTIF('List of Values'!$B$2:$B$255,AA36)=0)),"") -> TRUE | AD36: SEK | AE36: =IF(NOT(ISBLANK($C36)),IF(NOT(ISBLANK(AD36)),TRUE,FALSE),"") -> TRUE | AF36: =IF(NOT(ISBLANK($C36)),AND(AE36=TRUE,NOT(COUNTIF('List of Values'!$F$2:$F$255,AD36)=0)),"") -> TRUE | AG36: V_10EOM | AH36: =IF(NOT(ISBLANK($C36)),IF(NOT(ISBLANK(AG36)),TRUE,FALSE),"") -> TRUE | AI36: =IF(NOT(ISBLANK($C36)),AND(AH36=TRUE,NOT(COUNTIF('List of Values'!$N$2:$N$40,AG36)=0)),"") -> TRUE | AJ36: V_BANK | AK36: =IF(NOT(ISBLANK($C36)),IF(NOT(ISBLANK(AJ36)),TRUE,FALSE),"") -> TRUE | AL36: =IF(NOT(ISBLANK($C36)),AND(AK36=TRUE,NOT(COUNTIF('List of Values'!$O$2:$O$30,AJ36)=0)),"") -> TRUE | AM36: S-DOM | AN36: =IF(NOT(ISBLANK($C36)),IF(NOT(ISBLANK(AM36)),TRUE,FALSE),"") -> TRUE | AO36: =IF(NOT(ISBLANK($C36)),AND(AN36=TRUE,NOT(COUNTIF('List of Values'!$AF$2:$AF$20,AM36)=0)),"") -> TRUE | AQ36: =IF(NOT(ISBLANK($C36)),TRUE,"") -> TRUE | AR36: {=IF(NOT(ISBLANK($C36)),AND(AQ36=TRUE,LEN(AP36)<81,NOT(ISNUMBER(FIND('List of Values'!$C$2:$C$20,AP36)))),"")} -> TRUE | AS36: =D36 -> SMÖGENS FISKAUKTION AB | AT36: =IF(NOT(ISBLANK($C36)),IF(NOT(ISBLANK(AS36)),TRUE,FALSE),"") -> TRUE | AU36: {=IF(NOT(ISBLANK($C36)),AND(AT36=TRUE,LEN(AS36)<81,NOT(ISNUMBER(FIND('List of Values'!$C$2:$C$20,AS36)))),"")} -> TRUE | AV36: SMÖGENSFISKAUKTIONAB | AW36: =IF(NOT(ISBLANK($C36)),IF(NOT(ISBLANK(AV36)),TRUE,FALSE),"") -> TRUE | AX36: {=IF(NOT(ISBLANK($C36)),AND(AW36=TRUE,LEN(AV36)<21,NOT(ISNUMBER(FIND('List of Values'!$C$2:$C$20,AV36)))),"")} -> TRUE | AY36: 14639 | AZ36: =IF(NOT(ISBLANK($C36)),TRUE,"") -> TRUE | BA36: =IF(NOT(ISBLANK($C36)),AND(AZ36=TRUE,NOT(COUNTIF('List of Values'!$R$2:$R$400,AY36)=0)),"") -> TRUE | BC36: =IF(NOT(ISBLANK($C36)),TRUE,"") -> TRUE | BD36: {=IF(NOT(ISBLANK($C36)),OR(ISBLANK(BB36),AND(NOT(ISNUMBER(FIND('List of Values'!$C$2:$C$23,BB36))),ISNUMBER(DATEVALUE(BB36)))),"")} -> TRUE | BF36: =IF(NOT(ISBLANK($C36)),TRUE,"") -> TRUE | BG36: {=IF(NOT(ISBLANK($C36)),OR(ISBLANK(BE36),AND(NOT(ISNUMBER(FIND('List of Values'!$C$2:$C$23,BE36))),ISNUMBER(DATEVALUE(BE36)))),"")} -> TRUE | BI36: =IF(NOT(ISBLANK($C36)),TRUE,"") -> TRUE | BJ36: =IF(NOT(ISBLANK($C36)),OR(ISBLANK(BH36),AND(LEN(BH36)<14,ISNUMBER(BH36))),"") -> TRUE | BK36: Invoice | BL36: =IF(NOT(ISBLANK($C36)),IF(NOT(ISBLANK(BK36)),TRUE,FALSE),"") -> TRUE | BM36: =IF(NOT(ISBLANK($C36)),AND(BL36=TRUE,NOT(COUNTIF('List of Values'!$A$2:$A$20,BK36)=0)),"") -> TRUE | BN36: Active | BO36: =IF(NOT(ISBLANK($C36)),IF(NOT(ISBLANK(BN36)),TRUE,FALSE),"") -> TRUE | BP36: =IF(NOT(ISBLANK($C36)),OR(BN36="active",BN36="delisted"),"") -> TRUE | BR36: =IF(NOT(ISBLANK($C36)),OR(AND($E36="intercompany",NOT(ISBLANK(BQ36))),AND(NOT($E36="intercompany"),ISBLANK(BQ36))),"") -> TRUE | BS36: =IF(NOT(ISBLANK($C36)),OR(ISBLANK(BQ36),NOT(COUNTIF('List of Values'!$K$2:$K$30,BQ36)=0)),"") -> TRUE | BU36: =IF(NOT(ISBLANK($C36)),TRUE,"") -> TRUE | BV36: =IF(NOT(ISBLANK($C36)),OR(ISBLANK(BT36),BT36="duty paid",BT36="bond"),"") -> TRUE | BX36: =IF(NOT(ISBLANK($C36)),TRUE,"") -> TRUE | BY36: =IF(NOT(ISBLANK($C36)),OR(ISBLANK(BW36),BW36="duty paid",BW36="bond"),"") -> TRUE | BZ36: =_xlfn.XLOOKUP(C36,[1]Blad1!$A:$A,[1]Blad1!$D:$D,"")
B37: =COUNTIF(C37:XFD37,"FALSE") -> 0 | C37: 218111 | D37: GRAND GOURMET SWEDEN AB | E37: Trade | F37: 5569102675 | G37: =IF(NOT(ISBLANK($C37)),IF(NOT(ISBLANK(F37)),TRUE,FALSE),"") -> TRUE | H37: {=IF(NOT(ISBLANK($C37)),AND(G37=TRUE,LEN(F37)<30,NOT(ISNUMBER(FIND('List of Values'!$C$2:$C$20,F37)))),"")} -> TRUE | I37: SE556910267501 | J37: =IF(NOT(ISBLANK($C37)),TRUE,"") -> TRUE | K37: {=IF(NOT(ISBLANK($C37)),AND(J37=TRUE,LEN(I37)<20,NOT(ISNUMBER(FIND('List of Values'!$C$2:$C$20,I37)))),"")} -> TRUE | L37: WOLLMAR YXKULLSGATAN 31 | M37: =IF(NOT(ISBLANK($C37)),IF(NOT(ISBLANK(L37)),TRUE,FALSE),"") -> TRUE | N37: {=IF(NOT(ISBLANK($C37)),AND(M37=TRUE,LEN(L37)<81,NOT(ISNUMBER(FIND('List of Values'!$C$2:$C$20,L37)))),"")} -> TRUE | P37: =IF(NOT(ISBLANK($C37)),TRUE,"") -> TRUE | Q37: {=IF(NOT(ISBLANK($C37)),AND(P37=TRUE,LEN(O37)<81,NOT(ISNUMBER(FIND('List of Values'!$C$2:$C$20,O37)))),"")} -> TRUE | R37: STOCKHOLM | S37: =IF(NOT(ISBLANK($C37)),IF(NOT(ISBLANK(R37)),TRUE,FALSE),"") -> TRUE | T37: {=IF(NOT(ISBLANK($C37)),AND(S37=TRUE,LEN(R37)<61,NOT(ISNUMBER(FIND('List of Values'!$C$2:$C$23,R37)))),"")} -> TRUE | V37: =IF(NOT(ISBLANK($C37)),TRUE,"") -> TRUE | W37: {=IF(NOT(ISBLANK($C37)),AND(V37=TRUE,LEN(U37)<61,NOT(ISNUMBER(FIND('List of Values'!$C$2:$C$23,U37)))),"")} -> TRUE | X37: 118 50 | Y37: =IF(NOT(ISBLANK($C37)),IF(NOT(ISBLANK(X37)),TRUE,FALSE),"") -> TRUE | Z37: {=IF(NOT(ISBLANK($C37)),AND(Y37=TRUE,LEN(X37)<81,NOT(ISNUMBER(FIND('List of Values'!$C$2:$C$23,X37)))),"")} -> TRUE | AA37: SE | AB37: =IF(NOT(ISBLANK($C37)),IF(NOT(ISBLANK(AA37)),TRUE,FALSE),"") -> TRUE | AC37: =IF(NOT(ISBLANK($C37)),AND(AB37=TRUE,NOT(COUNTIF('List of Values'!$B$2:$B$255,AA37)=0)),"") -> TRUE | AD37: SEK | AE37: =IF(NOT(ISBLANK($C37)),IF(NOT(ISBLANK(AD37)),TRUE,FALSE),"") -> TRUE | AF37: =IF(NOT(ISBLANK($C37)),AND(AE37=TRUE,NOT(COUNTIF('List of Values'!$F$2:$F$255,AD37)=0)),"") -> TRUE | AG37: V_20NET | AH37: =IF(NOT(ISBLANK($C37)),IF(NOT(ISBLANK(AG37)),TRUE,FALSE),"") -> TRUE | AI37: =IF(NOT(ISBLANK($C37)),AND(AH37=TRUE,NOT(COUNTIF('List of Values'!$N$2:$N$40,AG37)=0)),"") -> TRUE | AJ37: V_BANK | AK37: =IF(NOT(ISBLANK($C37)),IF(NOT(ISBLANK(AJ37)),TRUE,FALSE),"") -> TRUE | AL37: =IF(NOT(ISBLANK($C37)),AND(AK37=TRUE,NOT(COUNTIF('List of Values'!$O$2:$O$30,AJ37)=0)),"") -> TRUE | AM37: S-DOM | AN37: =IF(NOT(ISBLANK($C37)),IF(NOT(ISBLANK(AM37)),TRUE,FALSE),"") -> TRUE | AO37: =IF(NOT(ISBLANK($C37)),AND(AN37=TRUE,NOT(COUNTIF('List of Values'!$AF$2:$AF$20,AM37)=0)),"") -> TRUE | AQ37: =IF(NOT(ISBLANK($C37)),TRUE,"") -> TRUE | AR37: {=IF(NOT(ISBLANK($C37)),AND(AQ37=TRUE,LEN(AP37)<81,NOT(ISNUMBER(FIND('List of Values'!$C$2:$C$20,AP37)))),"")} -> TRUE | AS37: =D37 -> GRAND GOURMET SWEDEN AB | AT37: =IF(NOT(ISBLANK($C37)),IF(NOT(ISBLANK(AS37)),TRUE,FALSE),"") -> TRUE | AU37: {=IF(NOT(ISBLANK($C37)),AND(AT37=TRUE,LEN(AS37)<81,NOT(ISNUMBER(FIND('List of Values'!$C$2:$C$20,AS37)))),"")} -> TRUE | AV37: GRANDGOURMETSWEDENAB | AW37: =IF(NOT(ISBLANK($C37)),IF(NOT(ISBLANK(AV37)),TRUE,FALSE),"") -> TRUE | AX37: {=IF(NOT(ISBLANK($C37)),AND(AW37=TRUE,LEN(AV37)<21,NOT(ISNUMBER(FIND('List of Values'!$C$2:$C$20,AV37)))),"")} -> TRUE | AY37: 12258 | AZ37: =IF(NOT(ISBLANK($C37)),TRUE,"") -> TRUE | BA37: =IF(NOT(ISBLANK($C37)),AND(AZ37=TRUE,NOT(COUNTIF('List of Values'!$R$2:$R$400,AY37)=0)),"") -> TRUE | BC37: =IF(NOT(ISBLANK($C37)),TRUE,"") -> TRUE | BD37: {=IF(NOT(ISBLANK($C37)),OR(ISBLANK(BB37),AND(NOT(ISNUMBER(FIND('List of Values'!$C$2:$C$23,BB37))),ISNUMBER(DATEVALUE(BB37)))),"")} -> TRUE | BF37: =IF(NOT(ISBLANK($C37)),TRUE,"") -> TRUE | BG37: {=IF(NOT(ISBLANK($C37)),OR(ISBLANK(BE37),AND(NOT(ISNUMBER(FIND('List of Values'!$C$2:$C$23,BE37))),ISNUMBER(DATEVALUE(BE37)))),"")} -> TRUE | BI37: =IF(NOT(ISBLANK($C37)),TRUE,"") -> TRUE | BJ37: =IF(NOT(ISBLANK($C37)),OR(ISBLANK(BH37),AND(LEN(BH37)<14,ISNUMBER(BH37))),"") -> TRUE | BK37: Invoice | BL37: =IF(NOT(ISBLANK($C37)),IF(NOT(ISBLANK(BK37)),TRUE,FALSE),"") -> TRUE | BM37: =IF(NOT(ISBLANK($C37)),AND(BL37=TRUE,NOT(COUNTIF('List of Values'!$A$2:$A$20,BK37)=0)),"") -> TRUE | BN37: Active | BO37: =IF(NOT(ISBLANK($C37)),IF(NOT(ISBLANK(BN37)),TRUE,FALSE),"") -> TRUE | BP37: =IF(NOT(ISBLANK($C37)),OR(BN37="active",BN37="delisted"),"") -> TRUE | BR37: =IF(NOT(ISBLANK($C37)),OR(AND($E37="intercompany",NOT(ISBLANK(BQ37))),AND(NOT($E37="intercompany"),ISBLANK(BQ37))),"") -> TRUE | BS37: =IF(NOT(ISBLANK($C37)),OR(ISBLANK(BQ37),NOT(COUNTIF('List of Values'!$K$2:$K$30,BQ37)=0)),"") -> TRUE | BU37: =IF(NOT(ISBLANK($C37)),TRUE,"") -> TRUE | BV37: =IF(NOT(ISBLANK($C37)),OR(ISBLANK(BT37),BT37="duty paid",BT37="bond"),"") -> TRUE | BX37: =IF(NOT(ISBLANK($C37)),TRUE,"") -> TRUE | BY37: =IF(NOT(ISBLANK($C37)),OR(ISBLANK(BW37),BW37="duty paid",BW37="bond"),"") -> TRUE | BZ37: =_xlfn.XLOOKUP(C37,[1]Blad1!$A:$A,[1]Blad1!$D:$D,"")
B38: =COUNTIF(C38:XFD38,"FALSE") -> 0 | C38: 217978 | D38: EKELÖFS GROSSIST AB | E38: Trade | F38: 5590546924 | G38: =IF(NOT(ISBLANK($C38)),IF(NOT(ISBLANK(F38)),TRUE,FALSE),"") -> TRUE | H38: {=IF(NOT(ISBLANK($C38)),AND(G38=TRUE,LEN(F38)<30,NOT(ISNUMBER(FIND('List of Values'!$C$2:$C$20,F38)))),"")} -> TRUE | I38: SE559054692401 | J38: =IF(NOT(ISBLANK($C38)),TRUE,"") -> TRUE | K38: {=IF(NOT(ISBLANK($C38)),AND(J38=TRUE,LEN(I38)<20,NOT(ISNUMBER(FIND('List of Values'!$C$2:$C$20,I38)))),"")} -> TRUE | L38: FISKHAMNSGATAN 31 | M38: =IF(NOT(ISBLANK($C38)),IF(NOT(ISBLANK(L38)),TRUE,FALSE),"") -> TRUE | N38: {=IF(NOT(ISBLANK($C38)),AND(M38=TRUE,LEN(L38)<81,NOT(ISNUMBER(FIND('List of Values'!$C$2:$C$20,L38)))),"")} -> TRUE | P38: =IF(NOT(ISBLANK($C38)),TRUE,"") -> TRUE | Q38: {=IF(NOT(ISBLANK($C38)),AND(P38=TRUE,LEN(O38)<81,NOT(ISNUMBER(FIND('List of Values'!$C$2:$C$20,O38)))),"")} -> TRUE | R38: SMÖGEN | S38: =IF(NOT(ISBLANK($C38)),IF(NOT(ISBLANK(R38)),TRUE,FALSE),"") -> TRUE | T38: {=IF(NOT(ISBLANK($C38)),AND(S38=TRUE,LEN(R38)<61,NOT(ISNUMBER(FIND('List of Values'!$C$2:$C$23,R38)))),"")} -> TRUE | V38: =IF(NOT(ISBLANK($C38)),TRUE,"") -> TRUE | W38: {=IF(NOT(ISBLANK($C38)),AND(V38=TRUE,LEN(U38)<61,NOT(ISNUMBER(FIND('List of Values'!$C$2:$C$23,U38)))),"")} -> TRUE | X38: 456 51 | Y38: =IF(NOT(ISBLANK($C38)),IF(NOT(ISBLANK(X38)),TRUE,FALSE),"") -> TRUE | Z38: {=IF(NOT(ISBLANK($C38)),AND(Y38=TRUE,LEN(X38)<81,NOT(ISNUMBER(FIND('List of Values'!$C$2:$C$23,X38)))),"")} -> TRUE | AA38: SE | AB38: =IF(NOT(ISBLANK($C38)),IF(NOT(ISBLANK(AA38)),TRUE,FALSE),"") -> TRUE | AC38: =IF(NOT(ISBLANK($C38)),AND(AB38=TRUE,NOT(COUNTIF('List of Values'!$B$2:$B$255,AA38)=0)),"") -> TRUE | AD38: SEK | AE38: =IF(NOT(ISBLANK($C38)),IF(NOT(ISBLANK(AD38)),TRUE,FALSE),"") -> TRUE | AF38: =IF(NOT(ISBLANK($C38)),AND(AE38=TRUE,NOT(COUNTIF('List of Values'!$F$2:$F$255,AD38)=0)),"") -> TRUE | AG38: V_20NET | AH38: =IF(NOT(ISBLANK($C38)),IF(NOT(ISBLANK(AG38)),TRUE,FALSE),"") -> TRUE | AI38: =IF(NOT(ISBLANK($C38)),AND(AH38=TRUE,NOT(COUNTIF('List of Values'!$N$2:$N$40,AG38)=0)),"") -> TRUE | AJ38: V_BANK | AK38: =IF(NOT(ISBLANK($C38)),IF(NOT(ISBLANK(AJ38)),TRUE,FALSE),"") -> TRUE | AL38: =IF(NOT(ISBLANK($C38)),AND(AK38=TRUE,NOT(COUNTIF('List of Values'!$O$2:$O$30,AJ38)=0)),"") -> TRUE | AM38: S-DOM | AN38: =IF(NOT(ISBLANK($C38)),IF(NOT(ISBLANK(AM38)),TRUE,FALSE),"") -> TRUE | AO38: =IF(NOT(ISBLANK($C38)),AND(AN38=TRUE,NOT(COUNTIF('List of Values'!$AF$2:$AF$20,AM38)=0)),"") -> TRUE | AQ38: =IF(NOT(ISBLANK($C38)),TRUE,"") -> TRUE | AR38: {=IF(NOT(ISBLANK($C38)),AND(AQ38=TRUE,LEN(AP38)<81,NOT(ISNUMBER(FIND('List of Values'!$C$2:$C$20,AP38)))),"")} -> TRUE | AS38: =D38 -> EKELÖFS GROSSIST AB | AT38: =IF(NOT(ISBLANK($C38)),IF(NOT(ISBLANK(AS38)),TRUE,FALSE),"") -> TRUE | AU38: {=IF(NOT(ISBLANK($C38)),AND(AT38=TRUE,LEN(AS38)<81,NOT(ISNUMBER(FIND('List of Values'!$C$2:$C$20,AS38)))),"")} -> TRUE | AV38: EKELÖFSGROSSISTAB | AW38: =IF(NOT(ISBLANK($C38)),IF(NOT(ISBLANK(AV38)),TRUE,FALSE),"") -> TRUE | AX38: {=IF(NOT(ISBLANK($C38)),AND(AW38=TRUE,LEN(AV38)<21,NOT(ISNUMBER(FIND('List of Values'!$C$2:$C$20,AV38)))),"")} -> TRUE | AY38: 11663 | AZ38: =IF(NOT(ISBLANK($C38)),TRUE,"") -> TRUE | BA38: =IF(NOT(ISBLANK($C38)),AND(AZ38=TRUE,NOT(COUNTIF('List of Values'!$R$2:$R$400,AY38)=0)),"") -> TRUE | BC38: =IF(NOT(ISBLANK($C38)),TRUE,"") -> TRUE | BD38: {=IF(NOT(ISBLANK($C38)),OR(ISBLANK(BB38),AND(NOT(ISNUMBER(FIND('List of Values'!$C$2:$C$23,BB38))),ISNUMBER(DATEVALUE(BB38)))),"")} -> TRUE | BF38: =IF(NOT(ISBLANK($C38)),TRUE,"") -> TRUE | BG38: {=IF(NOT(ISBLANK($C38)),OR(ISBLANK(BE38),AND(NOT(ISNUMBER(FIND('List of Values'!$C$2:$C$23,BE38))),ISNUMBER(DATEVALUE(BE38)))),"")} -> TRUE | BI38: =IF(NOT(ISBLANK($C38)),TRUE,"") -> TRUE | BJ38: =IF(NOT(ISBLANK($C38)),OR(ISBLANK(BH38),AND(LEN(BH38)<14,ISNUMBER(BH38))),"") -> TRUE | BK38: Invoice | BL38: =IF(NOT(ISBLANK($C38)),IF(NOT(ISBLANK(BK38)),TRUE,FALSE),"") -> TRUE | BM38: =IF(NOT(ISBLANK($C38)),AND(BL38=TRUE,NOT(COUNTIF('List of Values'!$A$2:$A$20,BK38)=0)),"") -> TRUE | BN38: Active | BO38: =IF(NOT(ISBLANK($C38)),IF(NOT(ISBLANK(BN38)),TRUE,FALSE),"") -> TRUE | BP38: =IF(NOT(ISBLANK($C38)),OR(BN38="active",BN38="delisted"),"") -> TRUE | BR38: =IF(NOT(ISBLANK($C38)),OR(AND($E38="intercompany",NOT(ISBLANK(BQ38))),AND(NOT($E38="intercompany"),ISBLANK(BQ38))),"") -> TRUE | BS38: =IF(NOT(ISBLANK($C38)),OR(ISBLANK(BQ38),NOT(COUNTIF('List of Values'!$K$2:$K$30,BQ38)=0)),"") -> TRUE | BU38: =IF(NOT(ISBLANK($C38)),TRUE,"") -> TRUE | BV38: =IF(NOT(ISBLANK($C38)),OR(ISBLANK(BT38),BT38="duty paid",BT38="bond"),"") -> TRUE | BX38: =IF(NOT(ISBLANK($C38)),TRUE,"") -> TRUE | BY38: =IF(NOT(ISBLANK($C38)),OR(ISBLANK(BW38),BW38="duty paid",BW38="bond"),"") -> TRUE | BZ38: =_xlfn.XLOOKUP(C38,[1]Blad1!$A:$A,[1]Blad1!$D:$D,"")
B39: =COUNTIF(C39:XFD39,"FALSE") -> 0 | C39: 217935 | D39: BEXANDERS RÖKERI AB | E39: Trade | F39: 5560631250 | G39: =IF(NOT(ISBLANK($C39)),IF(NOT(ISBLANK(F39)),TRUE,FALSE),"") -> TRUE | H39: {=IF(NOT(ISBLANK($C39)),AND(G39=TRUE,LEN(F39)<30,NOT(ISNUMBER(FIND('List of Values'!$C$2:$C$20,F39)))),"")} -> TRUE | I39: SE556063125001 | J39: =IF(NOT(ISBLANK($C39)),TRUE,"") -> TRUE | K39: {=IF(NOT(ISBLANK($C39)),AND(J39=TRUE,LEN(I39)<20,NOT(ISNUMBER(FIND('List of Values'!$C$2:$C$20,I39)))),"")} -> TRUE | L39: FISKHALLSVÄGEN 6 | M39: =IF(NOT(ISBLANK($C39)),IF(NOT(ISBLANK(L39)),TRUE,FALSE),"") -> TRUE | N39: {=IF(NOT(ISBLANK($C39)),AND(M39=TRUE,LEN(L39)<81,NOT(ISNUMBER(FIND('List of Values'!$C$2:$C$20,L39)))),"")} -> TRUE | P39: =IF(NOT(ISBLANK($C39)),TRUE,"") -> TRUE | Q39: {=IF(NOT(ISBLANK($C39)),AND(P39=TRUE,LEN(O39)<81,NOT(ISNUMBER(FIND('List of Values'!$C$2:$C$20,O39)))),"")} -> TRUE | R39: ÅRSTA | S39: =IF(NOT(ISBLANK($C39)),IF(NOT(ISBLANK(R39)),TRUE,FALSE),"") -> TRUE | T39: {=IF(NOT(ISBLANK($C39)),AND(S39=TRUE,LEN(R39)<61,NOT(ISNUMBER(FIND('List of Values'!$C$2:$C$23,R39)))),"")} -> TRUE | V39: =IF(NOT(ISBLANK($C39)),TRUE,"") -> TRUE | W39: {=IF(NOT(ISBLANK($C39)),AND(V39=TRUE,LEN(U39)<61,NOT(ISNUMBER(FIND('List of Values'!$C$2:$C$23,U39)))),"")} -> TRUE | X39: 120 44 | Y39: =IF(NOT(ISBLANK($C39)),IF(NOT(ISBLANK(X39)),TRUE,FALSE),"") -> TRUE | Z39: {=IF(NOT(ISBLANK($C39)),AND(Y39=TRUE,LEN(X39)<81,NOT(ISNUMBER(FIND('List of Values'!$C$2:$C$23,X39)))),"")} -> TRUE | AA39: SE | AB39: =IF(NOT(ISBLANK($C39)),IF(NOT(ISBLANK(AA39)),TRUE,FALSE),"") -> TRUE | AC39: =IF(NOT(ISBLANK($C39)),AND(AB39=TRUE,NOT(COUNTIF('List of Values'!$B$2:$B$255,AA39)=0)),"") -> TRUE | AD39: SEK | AE39: =IF(NOT(ISBLANK($C39)),IF(NOT(ISBLANK(AD39)),TRUE,FALSE),"") -> TRUE | AF39: =IF(NOT(ISBLANK($C39)),AND(AE39=TRUE,NOT(COUNTIF('List of Values'!$F$2:$F$255,AD39)=0)),"") -> TRUE | AG39: V_10EOM | AH39: =IF(NOT(ISBLANK($C39)),IF(NOT(ISBLANK(AG39)),TRUE,FALSE),"") -> TRUE | AI39: =IF(NOT(ISBLANK($C39)),AND(AH39=TRUE,NOT(COUNTIF('List of Values'!$N$2:$N$40,AG39)=0)),"") -> TRUE | AJ39: V_BANK | AK39: =IF(NOT(ISBLANK($C39)),IF(NOT(ISBLANK(AJ39)),TRUE,FALSE),"") -> TRUE | AL39: =IF(NOT(ISBLANK($C39)),AND(AK39=TRUE,NOT(COUNTIF('List of Values'!$O$2:$O$30,AJ39)=0)),"") -> TRUE | AM39: S-DOM | AN39: =IF(NOT(ISBLANK($C39)),IF(NOT(ISBLANK(AM39)),TRUE,FALSE),"") -> TRUE | AO39: =IF(NOT(ISBLANK($C39)),AND(AN39=TRUE,NOT(COUNTIF('List of Values'!$AF$2:$AF$20,AM39)=0)),"") -> TRUE | AQ39: =IF(NOT(ISBLANK($C39)),TRUE,"") -> TRUE | AR39: {=IF(NOT(ISBLANK($C39)),AND(AQ39=TRUE,LEN(AP39)<81,NOT(ISNUMBER(FIND('List of Values'!$C$2:$C$20,AP39)))),"")} -> TRUE | AS39: =D39 -> BEXANDERS RÖKERI AB | AT39: =IF(NOT(ISBLANK($C39)),IF(NOT(ISBLANK(AS39)),TRUE,FALSE),"") -> TRUE | AU39: {=IF(NOT(ISBLANK($C39)),AND(AT39=TRUE,LEN(AS39)<81,NOT(ISNUMBER(FIND('List of Values'!$C$2:$C$20,AS39)))),"")} -> TRUE | AV39: BEXANDERSRÖKERIAB | AW39: =IF(NOT(ISBLANK($C39)),IF(NOT(ISBLANK(AV39)),TRUE,FALSE),"") -> TRUE | AX39: {=IF(NOT(ISBLANK($C39)),AND(AW39=TRUE,LEN(AV39)<21,NOT(ISNUMBER(FIND('List of Values'!$C$2:$C$20,AV39)))),"")} -> TRUE | AY39: 10770 | AZ39: =IF(NOT(ISBLANK($C39)),TRUE,"") -> TRUE | BA39: =IF(NOT(ISBLANK($C39)),AND(AZ39=TRUE,NOT(COUNTIF('List of Values'!$R$2:$R$400,AY39)=0)),"") -> TRUE | BC39: =IF(NOT(ISBLANK($C39)),TRUE,"") -> TRUE | BD39: {=IF(NOT(ISBLANK($C39)),OR(ISBLANK(BB39),AND(NOT(ISNUMBER(FIND('List of Values'!$C$2:$C$23,BB39))),ISNUMBER(DATEVALUE(BB39)))),"")} -> TRUE | BF39: =IF(NOT(ISBLANK($C39)),TRUE,"") -> TRUE | BG39: {=IF(NOT(ISBLANK($C39)),OR(ISBLANK(BE39),AND(NOT(ISNUMBER(FIND('List of Values'!$C$2:$C$23,BE39))),ISNUMBER(DATEVALUE(BE39)))),"")} -> TRUE | BI39: =IF(NOT(ISBLANK($C39)),TRUE,"") -> TRUE | BJ39: =IF(NOT(ISBLANK($C39)),OR(ISBLANK(BH39),AND(LEN(BH39)<14,ISNUMBER(BH39))),"") -> TRUE | BK39: Invoice | BL39: =IF(NOT(ISBLANK($C39)),IF(NOT(ISBLANK(BK39)),TRUE,FALSE),"") -> TRUE | BM39: =IF(NOT(ISBLANK($C39)),AND(BL39=TRUE,NOT(COUNTIF('List of Values'!$A$2:$A$20,BK39)=0)),"") -> TRUE | BN39: Active | BO39: =IF(NOT(ISBLANK($C39)),IF(NOT(ISBLANK(BN39)),TRUE,FALSE),"") -> TRUE | BP39: =IF(NOT(ISBLANK($C39)),OR(BN39="active",BN39="delisted"),"") -> TRUE | BR39: =IF(NOT(ISBLANK($C39)),OR(AND($E39="intercompany",NOT(ISBLANK(BQ39))),AND(NOT($E39="intercompany"),ISBLANK(BQ39))),"") -> TRUE | BS39: =IF(NOT(ISBLANK($C39)),OR(ISBLANK(BQ39),NOT(COUNTIF('List of Values'!$K$2:$K$30,BQ39)=0)),"") -> TRUE | BU39: =IF(NOT(ISBLANK($C39)),TRUE,"") -> TRUE | BV39: =IF(NOT(ISBLANK($C39)),OR(ISBLANK(BT39),BT39="duty paid",BT39="bond"),"") -> TRUE | BX39: =IF(NOT(ISBLANK($C39)),TRUE,"") -> TRUE | BY39: =IF(NOT(ISBLANK($C39)),OR(ISBLANK(BW39),BW39="duty paid",BW39="bond"),"") -> TRUE | BZ39: =_xlfn.XLOOKUP(C39,[1]Blad1!$A:$A,[1]Blad1!$D:$D,"") -> x
B40: =COUNTIF(C40:XFD40,"FALSE") -> 0 | C40: 209933 | D40: QUALITY CAVIAR STOCKHOLM AB | E40: Trade | F40: 5591931141 | G40: =IF(NOT(ISBLANK($C40)),IF(NOT(ISBLANK(F40)),TRUE,FALSE),"") -> TRUE | H40: {=IF(NOT(ISBLANK($C40)),AND(G40=TRUE,LEN(F40)<30,NOT(ISNUMBER(FIND('List of Values'!$C$2:$C$20,F40)))),"")} -> TRUE | I40: SE559193114101 | J40: =IF(NOT(ISBLANK($C40)),TRUE,"") -> TRUE | K40: {=IF(NOT(ISBLANK($C40)),AND(J40=TRUE,LEN(I40)<20,NOT(ISNUMBER(FIND('List of Values'!$C$2:$C$20,I40)))),"")} -> TRUE | L40: STUREGATAN 20 | M40: =IF(NOT(ISBLANK($C40)),IF(NOT(ISBLANK(L40)),TRUE,FALSE),"") -> TRUE | N40: {=IF(NOT(ISBLANK($C40)),AND(M40=TRUE,LEN(L40)<81,NOT(ISNUMBER(FIND('List of Values'!$C$2:$C$20,L40)))),"")} -> TRUE | P40: =IF(NOT(ISBLANK($C40)),TRUE,"") -> TRUE | Q40: {=IF(NOT(ISBLANK($C40)),AND(P40=TRUE,LEN(O40)<81,NOT(ISNUMBER(FIND('List of Values'!$C$2:$C$20,O40)))),"")} -> TRUE | R40: STOCKHOLM | S40: =IF(NOT(ISBLANK($C40)),IF(NOT(ISBLANK(R40)),TRUE,FALSE),"") -> TRUE | T40: {=IF(NOT(ISBLANK($C40)),AND(S40=TRUE,LEN(R40)<61,NOT(ISNUMBER(FIND('List of Values'!$C$2:$C$23,R40)))),"")} -> TRUE | V40: =IF(NOT(ISBLANK($C40)),TRUE,"") -> TRUE | W40: {=IF(NOT(ISBLANK($C40)),AND(V40=TRUE,LEN(U40)<61,NOT(ISNUMBER(FIND('List of Values'!$C$2:$C$23,U40)))),"")} -> TRUE | X40: 114 36 | Y40: =IF(NOT(ISBLANK($C40)),IF(NOT(ISBLANK(X40)),TRUE,FALSE),"") -> TRUE | Z40: {=IF(NOT(ISBLANK($C40)),AND(Y40=TRUE,LEN(X40)<81,NOT(ISNUMBER(FIND('List of Values'!$C$2:$C$23,X40)))),"")} -> TRUE | AA40: SE | AB40: =IF(NOT(ISBLANK($C40)),IF(NOT(ISBLANK(AA40)),TRUE,FALSE),"") -> TRUE | AC40: =IF(NOT(ISBLANK($C40)),AND(AB40=TRUE,NOT(COUNTIF('List of Values'!$B$2:$B$255,AA40)=0)),"") -> TRUE | AD40: SEK | AE40: =IF(NOT(ISBLANK($C40)),IF(NOT(ISBLANK(AD40)),TRUE,FALSE),"") -> TRUE | AF40: =IF(NOT(ISBLANK($C40)),AND(AE40=TRUE,NOT(COUNTIF('List of Values'!$F$2:$F$255,AD40)=0)),"") -> TRUE | AG40: V_30NET | AH40: =IF(NOT(ISBLANK($C40)),IF(NOT(ISBLANK(AG40)),TRUE,FALSE),"") -> TRUE | AI40: =IF(NOT(ISBLANK($C40)),AND(AH40=TRUE,NOT(COUNTIF('List of Values'!$N$2:$N$40,AG40)=0)),"") -> TRUE | AJ40: V_BANK | AK40: =IF(NOT(ISBLANK($C40)),IF(NOT(ISBLANK(AJ40)),TRUE,FALSE),"") -> TRUE | AL40: =IF(NOT(ISBLANK($C40)),AND(AK40=TRUE,NOT(COUNTIF('List of Values'!$O$2:$O$30,AJ40)=0)),"") -> TRUE | AM40: S-DOM | AN40: =IF(NOT(ISBLANK($C40)),IF(NOT(ISBLANK(AM40)),TRUE,FALSE),"") -> TRUE | AO40: =IF(NOT(ISBLANK($C40)),AND(AN40=TRUE,NOT(COUNTIF('List of Values'!$AF$2:$AF$20,AM40)=0)),"") -> TRUE | AQ40: =IF(NOT(ISBLANK($C40)),TRUE,"") -> TRUE | AR40: {=IF(NOT(ISBLANK($C40)),AND(AQ40=TRUE,LEN(AP40)<81,NOT(ISNUMBER(FIND('List of Values'!$C$2:$C$20,AP40)))),"")} -> TRUE | AS40: =D40 -> QUALITY CAVIAR STOCKHOLM AB | AT40: =IF(NOT(ISBLANK($C40)),IF(NOT(ISBLANK(AS40)),TRUE,FALSE),"") -> TRUE | AU40: {=IF(NOT(ISBLANK($C40)),AND(AT40=TRUE,LEN(AS40)<81,NOT(ISNUMBER(FIND('List of Values'!$C$2:$C$20,AS40)))),"")} -> TRUE | AV40: QUALITYCAVIARSTOCKHO | AW40: =IF(NOT(ISBLANK($C40)),IF(NOT(ISBLANK(AV40)),TRUE,FALSE),"") -> TRUE | AX40: {=IF(NOT(ISBLANK($C40)),AND(AW40=TRUE,LEN(AV40)<21,NOT(ISNUMBER(FIND('List of Values'!$C$2:$C$20,AV40)))),"")} -> TRUE | AY40: 25037 | AZ40: =IF(NOT(ISBLANK($C40)),TRUE,"") -> TRUE | BA40: =IF(NOT(ISBLANK($C40)),AND(AZ40=TRUE,NOT(COUNTIF('List of Values'!$R$2:$R$400,AY40)=0)),"") -> TRUE | BC40: =IF(NOT(ISBLANK($C40)),TRUE,"") -> TRUE | BD40: {=IF(NOT(ISBLANK($C40)),OR(ISBLANK(BB40),AND(NOT(ISNUMBER(FIND('List of Values'!$C$2:$C$23,BB40))),ISNUMBER(DATEVALUE(BB40)))),"")} -> TRUE | BF40: =IF(NOT(ISBLANK($C40)),TRUE,"") -> TRUE | BG40: {=IF(NOT(ISBLANK($C40)),OR(ISBLANK(BE40),AND(NOT(ISNUMBER(FIND('List of Values'!$C$2:$C$23,BE40))),ISNUMBER(DATEVALUE(BE40)))),"")} -> TRUE | BI40: =IF(NOT(ISBLANK($C40)),TRUE,"") -> TRUE | BJ40: =IF(NOT(ISBLANK($C40)),OR(ISBLANK(BH40),AND(LEN(BH40)<14,ISNUMBER(BH40))),"") -> TRUE | BK40: Invoice | BL40: =IF(NOT(ISBLANK($C40)),IF(NOT(ISBLANK(BK40)),TRUE,FALSE),"") -> TRUE | BM40: =IF(NOT(ISBLANK($C40)),AND(BL40=TRUE,NOT(COUNTIF('List of Values'!$A$2:$A$20,BK40)=0)),"") -> TRUE | BN40: Active | BO40: =IF(NOT(ISBLANK($C40)),IF(NOT(ISBLANK(BN40)),TRUE,FALSE),"") -> TRUE | BP40: =IF(NOT(ISBLANK($C40)),OR(BN40="active",BN40="delisted"),"") -> TRUE | BR40: =IF(NOT(ISBLANK($C40)),OR(AND($E40="intercompany",NOT(ISBLANK(BQ40))),AND(NOT($E40="intercompany"),ISBLANK(BQ40))),"") -> TRUE | BS40: =IF(NOT(ISBLANK($C40)),OR(ISBLANK(BQ40),NOT(COUNTIF('List of Values'!$K$2:$K$30,BQ40)=0)),"") -> TRUE | BU40: =IF(NOT(ISBLANK($C40)),TRUE,"") -> TRUE | BV40: =IF(NOT(ISBLANK($C40)),OR(ISBLANK(BT40),BT40="duty paid",BT40="bond"),"") -> TRUE | BX40: =IF(NOT(ISBLANK($C40)),TRUE,"") -> TRUE | BY40: =IF(NOT(ISBLANK($C40)),OR(ISBLANK(BW40),BW40="duty paid",BW40="bond"),"") -> TRUE | BZ40: =_xlfn.XLOOKUP(C40,[1]Blad1!$A:$A,[1]Blad1!$D:$D,"")
B41: =COUNTIF(C41:XFD41,"FALSE") -> 0 | C41: 218068 | D41: WOLTERS KLUWER SCANDINAVIA AB | E41: Indirect | F41: 5564598521 | G41: =IF(NOT(ISBLANK($C41)),IF(NOT(ISBLANK(F41)),TRUE,FALSE),"") -> TRUE | H41: {=IF(NOT(ISBLANK($C41)),AND(G41=TRUE,LEN(F41)<30,NOT(ISNUMBER(FIND('List of Values'!$C$2:$C$20,F41)))),"")} -> TRUE | I41: SE556459852101 | J41: =IF(NOT(ISBLANK($C41)),TRUE,"") -> TRUE | K41: {=IF(NOT(ISBLANK($C41)),AND(J41=TRUE,LEN(I41)<20,NOT(ISNUMBER(FIND('List of Values'!$C$2:$C$20,I41)))),"")} -> TRUE | L41: EMIGRANTVÄGEN 2G | M41: =IF(NOT(ISBLANK($C41)),IF(NOT(ISBLANK(L41)),TRUE,FALSE),"") -> TRUE | N41: {=IF(NOT(ISBLANK($C41)),AND(M41=TRUE,LEN(L41)<81,NOT(ISNUMBER(FIND('List of Values'!$C$2:$C$20,L41)))),"")} -> TRUE | P41: =IF(NOT(ISBLANK($C41)),TRUE,"") -> TRUE | Q41: {=IF(NOT(ISBLANK($C41)),AND(P41=TRUE,LEN(O41)<81,NOT(ISNUMBER(FIND('List of Values'!$C$2:$C$20,O41)))),"")} -> TRUE | R41: GÖTEBORG | S41: =IF(NOT(ISBLANK($C41)),IF(NOT(ISBLANK(R41)),TRUE,FALSE),"") -> TRUE | T41: {=IF(NOT(ISBLANK($C41)),AND(S41=TRUE,LEN(R41)<61,NOT(ISNUMBER(FIND('List of Values'!$C$2:$C$23,R41)))),"")} -> TRUE | V41: =IF(NOT(ISBLANK($C41)),TRUE,"") -> TRUE | W41: {=IF(NOT(ISBLANK($C41)),AND(V41=TRUE,LEN(U41)<61,NOT(ISNUMBER(FIND('List of Values'!$C$2:$C$23,U41)))),"")} -> TRUE | X41: 414 63 | Y41: =IF(NOT(ISBLANK($C41)),IF(NOT(ISBLANK(X41)),TRUE,FALSE),"") -> TRUE | Z41: {=IF(NOT(ISBLANK($C41)),AND(Y41=TRUE,LEN(X41)<81,NOT(ISNUMBER(FIND('List of Values'!$C$2:$C$23,X41)))),"")} -> TRUE | AA41: SE | AB41: =IF(NOT(ISBLANK($C41)),IF(NOT(ISBLANK(AA41)),TRUE,FALSE),"") -> TRUE | AC41: =IF(NOT(ISBLANK($C41)),AND(AB41=TRUE,NOT(COUNTIF('List of Values'!$B$2:$B$255,AA41)=0)),"") -> TRUE | AD41: SEK | AE41: =IF(NOT(ISBLANK($C41)),IF(NOT(ISBLANK(AD41)),TRUE,FALSE),"") -> TRUE | AF41: =IF(NOT(ISBLANK($C41)),AND(AE41=TRUE,NOT(COUNTIF('List of Values'!$F$2:$F$255,AD41)=0)),"") -> TRUE | AG41: V_20NET | AH41: =IF(NOT(ISBLANK($C41)),IF(NOT(ISBLANK(AG41)),TRUE,FALSE),"") -> TRUE | AI41: =IF(NOT(ISBLANK($C41)),AND(AH41=TRUE,NOT(COUNTIF('List of Values'!$N$2:$N$40,AG41)=0)),"") -> TRUE | AJ41: V_BANK | AK41: =IF(NOT(ISBLANK($C41)),IF(NOT(ISBLANK(AJ41)),TRUE,FALSE),"") -> TRUE | AL41: =IF(NOT(ISBLANK($C41)),AND(AK41=TRUE,NOT(COUNTIF('List of Values'!$O$2:$O$30,AJ41)=0)),"") -> TRUE | AM41: S-DOM | AN41: =IF(NOT(ISBLANK($C41)),IF(NOT(ISBLANK(AM41)),TRUE,FALSE),"") -> TRUE | AO41: =IF(NOT(ISBLANK($C41)),AND(AN41=TRUE,NOT(COUNTIF('List of Values'!$AF$2:$AF$20,AM41)=0)),"") -> TRUE | AQ41: =IF(NOT(ISBLANK($C41)),TRUE,"") -> TRUE | AR41: {=IF(NOT(ISBLANK($C41)),AND(AQ41=TRUE,LEN(AP41)<81,NOT(ISNUMBER(FIND('List of Values'!$C$2:$C$20,AP41)))),"")} -> TRUE | AS41: =D41 -> WOLTERS KLUWER SCANDINAVIA AB | AT41: =IF(NOT(ISBLANK($C41)),IF(NOT(ISBLANK(AS41)),TRUE,FALSE),"") -> TRUE | AU41: {=IF(NOT(ISBLANK($C41)),AND(AT41=TRUE,LEN(AS41)<81,NOT(ISNUMBER(FIND('List of Values'!$C$2:$C$20,AS41)))),"")} -> TRUE | AV41: WOLTERSKLUWERSCANDIN | AW41: =IF(NOT(ISBLANK($C41)),IF(NOT(ISBLANK(AV41)),TRUE,FALSE),"") -> TRUE | AX41: {=IF(NOT(ISBLANK($C41)),AND(AW41=TRUE,LEN(AV41)<21,NOT(ISNUMBER(FIND('List of Values'!$C$2:$C$20,AV41)))),"")} -> TRUE | AY41: 10001 | AZ41: =IF(NOT(ISBLANK($C41)),TRUE,"") -> TRUE | BA41: =IF(NOT(ISBLANK($C41)),AND(AZ41=TRUE,NOT(COUNTIF('List of Values'!$R$2:$R$400,AY41)=0)),"") -> TRUE | BC41: =IF(NOT(ISBLANK($C41)),TRUE,"") -> TRUE | BD41: {=IF(NOT(ISBLANK($C41)),OR(ISBLANK(BB41),AND(NOT(ISNUMBER(FIND('List of Values'!$C$2:$C$23,BB41))),ISNUMBER(DATEVALUE(BB41)))),"")} -> TRUE | BF41: =IF(NOT(ISBLANK($C41)),TRUE,"") -> TRUE | BG41: {=IF(NOT(ISBLANK($C41)),OR(ISBLANK(BE41),AND(NOT(ISNUMBER(FIND('List of Values'!$C$2:$C$23,BE41))),ISNUMBER(DATEVALUE(BE41)))),"")} -> TRUE | BI41: =IF(NOT(ISBLANK($C41)),TRUE,"") -> TRUE | BJ41: =IF(NOT(ISBLANK($C41)),OR(ISBLANK(BH41),AND(LEN(BH41)<14,ISNUMBER(BH41))),"") -> TRUE | BK41: Invoice | BL41: =IF(NOT(ISBLANK($C41)),IF(NOT(ISBLANK(BK41)),TRUE,FALSE),"") -> TRUE | BM41: =IF(NOT(ISBLANK($C41)),AND(BL41=TRUE,NOT(COUNTIF('List of Values'!$A$2:$A$20,BK41)=0)),"") -> TRUE | BN41: Active | BO41: =IF(NOT(ISBLANK($C41)),IF(NOT(ISBLANK(BN41)),TRUE,FALSE),"") -> TRUE | BP41: =IF(NOT(ISBLANK($C41)),OR(BN41="active",BN41="delisted"),"") -> TRUE | BR41: =IF(NOT(ISBLANK($C41)),OR(AND($E41="intercompany",NOT(ISBLANK(BQ41))),AND(NOT($E41="intercompany"),ISBLANK(BQ41))),"") -> TRUE | BS41: =IF(NOT(ISBLANK($C41)),OR(ISBLANK(BQ41),NOT(COUNTIF('List of Values'!$K$2:$K$30,BQ41)=0)),"") -> TRUE | BU41: =IF(NOT(ISBLANK($C41)),TRUE,"") -> TRUE | BV41: =IF(NOT(ISBLANK($C41)),OR(ISBLANK(BT41),BT41="duty paid",BT41="bond"),"") -> TRUE | BX41: =IF(NOT(ISBLANK($C41)),TRUE,"") -> TRUE | BY41: =IF(NOT(ISBLANK($C41)),OR(ISBLANK(BW41),BW41="duty paid",BW41="bond"),"") -> TRUE | BZ41: =_xlfn.XLOOKUP(C41,[1]Blad1!$A:$A,[1]Blad1!$D:$D,"")
B42: =COUNTIF(C42:XFD42,"FALSE") -> 0 | C42: 218093 | D42: VÄSTERNORRLANDS LOGISITK AB (RIKSBUD) | E42: Indirect | F42: 5568254766 | G42: =IF(NOT(ISBLANK($C42)),IF(NOT(ISBLANK(F42)),TRUE,FALSE),"") -> TRUE | H42: {=IF(NOT(ISBLANK($C42)),AND(G42=TRUE,LEN(F42)<30,NOT(ISNUMBER(FIND('List of Values'!$C$2:$C$20,F42)))),"")} -> TRUE | I42: SE556825476601 | J42: =IF(NOT(ISBLANK($C42)),TRUE,"") -> TRUE | K42: {=IF(NOT(ISBLANK($C42)),AND(J42=TRUE,LEN(I42)<20,NOT(ISNUMBER(FIND('List of Values'!$C$2:$C$20,I42)))),"")} -> TRUE | L42: MIDLANDAVÄGEN 22 | M42: =IF(NOT(ISBLANK($C42)),IF(NOT(ISBLANK(L42)),TRUE,FALSE),"") -> TRUE | N42: {=IF(NOT(ISBLANK($C42)),AND(M42=TRUE,LEN(L42)<81,NOT(ISNUMBER(FIND('List of Values'!$C$2:$C$20,L42)))),"")} -> TRUE | P42: =IF(NOT(ISBLANK($C42)),TRUE,"") -> TRUE | Q42: {=IF(NOT(ISBLANK($C42)),AND(P42=TRUE,LEN(O42)<81,NOT(ISNUMBER(FIND('List of Values'!$C$2:$C$20,O42)))),"")} -> TRUE | R42: SÖRBERGE | S42: =IF(NOT(ISBLANK($C42)),IF(NOT(ISBLANK(R42)),TRUE,FALSE),"") -> TRUE | T42: {=IF(NOT(ISBLANK($C42)),AND(S42=TRUE,LEN(R42)<61,NOT(ISNUMBER(FIND('List of Values'!$C$2:$C$23,R42)))),"")} -> TRUE | V42: =IF(NOT(ISBLANK($C42)),TRUE,"") -> TRUE | W42: {=IF(NOT(ISBLANK($C42)),AND(V42=TRUE,LEN(U42)<61,NOT(ISNUMBER(FIND('List of Values'!$C$2:$C$23,U42)))),"")} -> TRUE | X42: 861 41 | Y42: =IF(NOT(ISBLANK($C42)),IF(NOT(ISBLANK(X42)),TRUE,FALSE),"") -> TRUE | Z42: {=IF(NOT(ISBLANK($C42)),AND(Y42=TRUE,LEN(X42)<81,NOT(ISNUMBER(FIND('List of Values'!$C$2:$C$23,X42)))),"")} -> TRUE | AA42: SE | AB42: =IF(NOT(ISBLANK($C42)),IF(NOT(ISBLANK(AA42)),TRUE,FALSE),"") -> TRUE | AC42: =IF(NOT(ISBLANK($C42)),AND(AB42=TRUE,NOT(COUNTIF('List of Values'!$B$2:$B$255,AA42)=0)),"") -> TRUE | AD42: SEK | AE42: =IF(NOT(ISBLANK($C42)),IF(NOT(ISBLANK(AD42)),TRUE,FALSE),"") -> TRUE | AF42: =IF(NOT(ISBLANK($C42)),AND(AE42=TRUE,NOT(COUNTIF('List of Values'!$F$2:$F$255,AD42)=0)),"") -> TRUE | AG42: V_10EOM | AH42: =IF(NOT(ISBLANK($C42)),IF(NOT(ISBLANK(AG42)),TRUE,FALSE),"") -> TRUE | AI42: =IF(NOT(ISBLANK($C42)),AND(AH42=TRUE,NOT(COUNTIF('List of Values'!$N$2:$N$40,AG42)=0)),"") -> TRUE | AJ42: V_BANK | AK42: =IF(NOT(ISBLANK($C42)),IF(NOT(ISBLANK(AJ42)),TRUE,FALSE),"") -> TRUE | AL42: =IF(NOT(ISBLANK($C42)),AND(AK42=TRUE,NOT(COUNTIF('List of Values'!$O$2:$O$30,AJ42)=0)),"") -> TRUE | AM42: S-DOM | AN42: =IF(NOT(ISBLANK($C42)),IF(NOT(ISBLANK(AM42)),TRUE,FALSE),"") -> TRUE | AO42: =IF(NOT(ISBLANK($C42)),AND(AN42=TRUE,NOT(COUNTIF('List of Values'!$AF$2:$AF$20,AM42)=0)),"") -> TRUE | AQ42: =IF(NOT(ISBLANK($C42)),TRUE,"") -> TRUE | AR42: {=IF(NOT(ISBLANK($C42)),AND(AQ42=TRUE,LEN(AP42)<81,NOT(ISNUMBER(FIND('List of Values'!$C$2:$C$20,AP42)))),"")} -> TRUE | AS42: =D42 -> VÄSTERNORRLANDS LOGISITK AB (RIKSBUD) | AT42: =IF(NOT(ISBLANK($C42)),IF(NOT(ISBLANK(AS42)),TRUE,FALSE),"") -> TRUE | AU42: {=IF(NOT(ISBLANK($C42)),AND(AT42=TRUE,LEN(AS42)<81,NOT(ISNUMBER(FIND('List of Values'!$C$2:$C$20,AS42)))),"")} -> TRUE | AV42: VÄSTERNORRLANDSLOGIS | AW42: =IF(NOT(ISBLANK($C42)),IF(NOT(ISBLANK(AV42)),TRUE,FALSE),"") -> TRUE | AX42: {=IF(NOT(ISBLANK($C42)),AND(AW42=TRUE,LEN(AV42)<21,NOT(ISNUMBER(FIND('List of Values'!$C$2:$C$20,AV42)))),"")} -> TRUE | AY42: 10001 | AZ42: =IF(NOT(ISBLANK($C42)),TRUE,"") -> TRUE | BA42: =IF(NOT(ISBLANK($C42)),AND(AZ42=TRUE,NOT(COUNTIF('List of Values'!$R$2:$R$400,AY42)=0)),"") -> TRUE | BC42: =IF(NOT(ISBLANK($C42)),TRUE,"") -> TRUE | BD42: {=IF(NOT(ISBLANK($C42)),OR(ISBLANK(BB42),AND(NOT(ISNUMBER(FIND('List of Values'!$C$2:$C$23,BB42))),ISNUMBER(DATEVALUE(BB42)))),"")} -> TRUE | BF42: =IF(NOT(ISBLANK($C42)),TRUE,"") -> TRUE | BG42: {=IF(NOT(ISBLANK($C42)),OR(ISBLANK(BE42),AND(NOT(ISNUMBER(FIND('List of Values'!$C$2:$C$23,BE42))),ISNUMBER(DATEVALUE(BE42)))),"")} -> TRUE | BI42: =IF(NOT(ISBLANK($C42)),TRUE,"") -> TRUE | BJ42: =IF(NOT(ISBLANK($C42)),OR(ISBLANK(BH42),AND(LEN(BH42)<14,ISNUMBER(BH42))),"") -> TRUE | BK42: Invoice | BL42: =IF(NOT(ISBLANK($C42)),IF(NOT(ISBLANK(BK42)),TRUE,FALSE),"") -> TRUE | BM42: =IF(NOT(ISBLANK($C42)),AND(BL42=TRUE,NOT(COUNTIF('List of Values'!$A$2:$A$20,BK42)=0)),"") -> TRUE | BN42: Delisted | BO42: =IF(NOT(ISBLANK($C42)),IF(NOT(ISBLANK(BN42)),TRUE,FALSE),"") -> TRUE | BP42: =IF(NOT(ISBLANK($C42)),OR(BN42="active",BN42="delisted"),"") -> TRUE | BR42: =IF(NOT(ISBLANK($C42)),OR(AND($E42="intercompany",NOT(ISBLANK(BQ42))),AND(NOT($E42="intercompany"),ISBLANK(BQ42))),"") -> TRUE | BS42: =IF(NOT(ISBLANK($C42)),OR(ISBLANK(BQ42),NOT(COUNTIF('List of Values'!$K$2:$K$30,BQ42)=0)),"") -> TRUE | BU42: =IF(NOT(ISBLANK($C42)),TRUE,"") -> TRUE | BV42: =IF(NOT(ISBLANK($C42)),OR(ISBLANK(BT42),BT42="duty paid",BT42="bond"),"") -> TRUE | BX42: =IF(NOT(ISBLANK($C42)),TRUE,"") -> TRUE | BY42: =IF(NOT(ISBLANK($C42)),OR(ISBLANK(BW42),BW42="duty paid",BW42="bond"),"") -> TRUE | BZ42: =_xlfn.XLOOKUP(C42,[1]Blad1!$A:$A,[1]Blad1!$D:$D,"")
B43: =COUNTIF(C43:XFD43,"FALSE") -> 0 | C43: 217993 | D43: COLDWATER UNITED SEAFOOD APS | E43: Trade | F43: DK12593945 | G43: =IF(NOT(ISBLANK($C43)),IF(NOT(ISBLANK(F43)),TRUE,FALSE),"") -> TRUE | H43: {=IF(NOT(ISBLANK($C43)),AND(G43=TRUE,LEN(F43)<30,NOT(ISNUMBER(FIND('List of Values'!$C$2:$C$20,F43)))),"")} -> TRUE | I43: DK12593945 | J43: =IF(NOT(ISBLANK($C43)),TRUE,"") -> TRUE | K43: {=IF(NOT(ISBLANK($C43)),AND(J43=TRUE,LEN(I43)<20,NOT(ISNUMBER(FIND('List of Values'!$C$2:$C$20,I43)))),"")} -> TRUE | L43: BOX 66 | M43: =IF(NOT(ISBLANK($C43)),IF(NOT(ISBLANK(L43)),TRUE,FALSE),"") -> TRUE | N43: {=IF(NOT(ISBLANK($C43)),AND(M43=TRUE,LEN(L43)<81,NOT(ISNUMBER(FIND('List of Values'!$C$2:$C$20,L43)))),"")} -> TRUE | P43: =IF(NOT(ISBLANK($C43)),TRUE,"") -> TRUE | Q43: {=IF(NOT(ISBLANK($C43)),AND(P43=TRUE,LEN(O43)<81,NOT(ISNUMBER(FIND('List of Values'!$C$2:$C$20,O43)))),"")} -> TRUE | R43: VODSKOV | S43: =IF(NOT(ISBLANK($C43)),IF(NOT(ISBLANK(R43)),TRUE,FALSE),"") -> TRUE | T43: {=IF(NOT(ISBLANK($C43)),AND(S43=TRUE,LEN(R43)<61,NOT(ISNUMBER(FIND('List of Values'!$C$2:$C$23,R43)))),"")} -> TRUE | V43: =IF(NOT(ISBLANK($C43)),TRUE,"") -> TRUE | W43: {=IF(NOT(ISBLANK($C43)),AND(V43=TRUE,LEN(U43)<61,NOT(ISNUMBER(FIND('List of Values'!$C$2:$C$23,U43)))),"")} -> TRUE | X43: DK-9310 | Y43: =IF(NOT(ISBLANK($C43)),IF(NOT(ISBLANK(X43)),TRUE,FALSE),"") -> TRUE | Z43: {=IF(NOT(ISBLANK($C43)),AND(Y43=TRUE,LEN(X43)<81,NOT(ISNUMBER(FIND('List of Values'!$C$2:$C$23,X43)))),"")} -> TRUE | AA43: DK | AB43: =IF(NOT(ISBLANK($C43)),IF(NOT(ISBLANK(AA43)),TRUE,FALSE),"") -> TRUE | AC43: =IF(NOT(ISBLANK($C43)),AND(AB43=TRUE,NOT(COUNTIF('List of Values'!$B$2:$B$255,AA43)=0)),"") -> TRUE | AD43: SEK | AE43: =IF(NOT(ISBLANK($C43)),IF(NOT(ISBLANK(AD43)),TRUE,FALSE),"") -> TRUE | AF43: =IF(NOT(ISBLANK($C43)),AND(AE43=TRUE,NOT(COUNTIF('List of Values'!$F$2:$F$255,AD43)=0)),"") -> TRUE | AG43: V_20NET | AH43: =IF(NOT(ISBLANK($C43)),IF(NOT(ISBLANK(AG43)),TRUE,FALSE),"") -> TRUE | AI43: =IF(NOT(ISBLANK($C43)),AND(AH43=TRUE,NOT(COUNTIF('List of Values'!$N$2:$N$40,AG43)=0)),"") -> TRUE | AJ43: V_BANK | AK43: =IF(NOT(ISBLANK($C43)),IF(NOT(ISBLANK(AJ43)),TRUE,FALSE),"") -> TRUE | AL43: =IF(NOT(ISBLANK($C43)),AND(AK43=TRUE,NOT(COUNTIF('List of Values'!$O$2:$O$30,AJ43)=0)),"") -> TRUE | AM43: S-EU | AN43: =IF(NOT(ISBLANK($C43)),IF(NOT(ISBLANK(AM43)),TRUE,FALSE),"") -> TRUE | AO43: =IF(NOT(ISBLANK($C43)),AND(AN43=TRUE,NOT(COUNTIF('List of Values'!$AF$2:$AF$20,AM43)=0)),"") -> TRUE | AQ43: =IF(NOT(ISBLANK($C43)),TRUE,"") -> TRUE | AR43: {=IF(NOT(ISBLANK($C43)),AND(AQ43=TRUE,LEN(AP43)<81,NOT(ISNUMBER(FIND('List of Values'!$C$2:$C$20,AP43)))),"")} -> TRUE | AS43: =D43 -> COLDWATER UNITED SEAFOOD APS | AT43: =IF(NOT(ISBLANK($C43)),IF(NOT(ISBLANK(AS43)),TRUE,FALSE),"") -> TRUE | AU43: {=IF(NOT(ISBLANK($C43)),AND(AT43=TRUE,LEN(AS43)<81,NOT(ISNUMBER(FIND('List of Values'!$C$2:$C$20,AS43)))),"")} -> TRUE | AV43: COLDWATERUNITEDSEAFO | AW43: =IF(NOT(ISBLANK($C43)),IF(NOT(ISBLANK(AV43)),TRUE,FALSE),"") -> TRUE | AX43: {=IF(NOT(ISBLANK($C43)),AND(AW43=TRUE,LEN(AV43)<21,NOT(ISNUMBER(FIND('List of Values'!$C$2:$C$20,AV43)))),"")} -> TRUE | AY43: 11225 | AZ43: =IF(NOT(ISBLANK($C43)),TRUE,"") -> TRUE | BA43: =IF(NOT(ISBLANK($C43)),AND(AZ43=TRUE,NOT(COUNTIF('List of Values'!$R$2:$R$400,AY43)=0)),"") -> TRUE | BC43: =IF(NOT(ISBLANK($C43)),TRUE,"") -> TRUE | BD43: {=IF(NOT(ISBLANK($C43)),OR(ISBLANK(BB43),AND(NOT(ISNUMBER(FIND('List of Values'!$C$2:$C$23,BB43))),ISNUMBER(DATEVALUE(BB43)))),"")} -> TRUE | BF43: =IF(NOT(ISBLANK($C43)),TRUE,"") -> TRUE | BG43: {=IF(NOT(ISBLANK($C43)),OR(ISBLANK(BE43),AND(NOT(ISNUMBER(FIND('List of Values'!$C$2:$C$23,BE43))),ISNUMBER(DATEVALUE(BE43)))),"")} -> TRUE | BI43: =IF(NOT(ISBLANK($C43)),TRUE,"") -> TRUE | BJ43: =IF(NOT(ISBLANK($C43)),OR(ISBLANK(BH43),AND(LEN(BH43)<14,ISNUMBER(BH43))),"") -> TRUE | BK43: Invoice | BL43: =IF(NOT(ISBLANK($C43)),IF(NOT(ISBLANK(BK43)),TRUE,FALSE),"") -> TRUE | BM43: =IF(NOT(ISBLANK($C43)),AND(BL43=TRUE,NOT(COUNTIF('List of Values'!$A$2:$A$20,BK43)=0)),"") -> TRUE | BN43: Active | BO43: =IF(NOT(ISBLANK($C43)),IF(NOT(ISBLANK(BN43)),TRUE,FALSE),"") -> TRUE | BP43: =IF(NOT(ISBLANK($C43)),OR(BN43="active",BN43="delisted"),"") -> TRUE | BR43: =IF(NOT(ISBLANK($C43)),OR(AND($E43="intercompany",NOT(ISBLANK(BQ43))),AND(NOT($E43="intercompany"),ISBLANK(BQ43))),"") -> TRUE | BS43: =IF(NOT(ISBLANK($C43)),OR(ISBLANK(BQ43),NOT(COUNTIF('List of Values'!$K$2:$K$30,BQ43)=0)),"") -> TRUE | BU43: =IF(NOT(ISBLANK($C43)),TRUE,"") -> TRUE | BV43: =IF(NOT(ISBLANK($C43)),OR(ISBLANK(BT43),BT43="duty paid",BT43="bond"),"") -> TRUE | BX43: =IF(NOT(ISBLANK($C43)),TRUE,"") -> TRUE | BY43: =IF(NOT(ISBLANK($C43)),OR(ISBLANK(BW43),BW43="duty paid",BW43="bond"),"") -> TRUE | BZ43: =_xlfn.XLOOKUP(C43,[1]Blad1!$A:$A,[1]Blad1!$D:$D,"") -> x
